[
    {
        "open": 9.93,
        "high": 9.94,
        "low": 9.9,
        "close": 9.91,
        "volume": 6837839,
        "datetime": "2021-12-10 06:00:00"
    },
    {
        "open": 9.92,
        "high": 9.98,
        "low": 9.905,
        "close": 9.91,
        "volume": 461790,
        "datetime": "2021-12-13 06:00:00"
    },
    {
        "open": 9.91,
        "high": 9.94,
        "low": 9.91,
        "close": 9.94,
        "volume": 51802,
        "datetime": "2021-12-14 06:00:00"
    },
    {
        "open": 9.94,
        "high": 9.94,
        "low": 9.925,
        "close": 9.93,
        "volume": 71347,
        "datetime": "2021-12-15 06:00:00"
    },
    {
        "open": 9.92,
        "high": 9.92,
        "low": 9.89,
        "close": 9.9,
        "volume": 5254,
        "datetime": "2021-12-16 06:00:00"
    },
    {
        "open": 9.9,
        "high": 9.92,
        "low": 9.9,
        "close": 9.91,
        "volume": 14040,
        "datetime": "2021-12-17 06:00:00"
    },
    {
        "open": 10.01,
        "high": 10.01,
        "low": 9.93,
        "close": 9.9334,
        "volume": 5877,
        "datetime": "2021-12-21 06:00:00"
    },
    {
        "open": 9.93,
        "high": 9.94,
        "low": 9.93,
        "close": 9.94,
        "volume": 4512,
        "datetime": "2021-12-22 06:00:00"
    },
    {
        "open": 9.94,
        "high": 9.9475,
        "low": 9.9374,
        "close": 9.945,
        "volume": 29753,
        "datetime": "2021-12-23 06:00:00"
    },
    {
        "open": 9.94,
        "high": 9.94,
        "low": 9.94,
        "close": 9.94,
        "volume": 411,
        "datetime": "2021-12-27 06:00:00"
    },
    {
        "open": 9.9385,
        "high": 9.94,
        "low": 9.93,
        "close": 9.94,
        "volume": 5855,
        "datetime": "2021-12-28 06:00:00"
    },
    {
        "open": 9.9331,
        "high": 9.94,
        "low": 9.9,
        "close": 9.9218,
        "volume": 7406,
        "datetime": "2021-12-29 06:00:00"
    },
    {
        "open": 9.92,
        "high": 9.94,
        "low": 9.9075,
        "close": 9.9234,
        "volume": 2300,
        "datetime": "2021-12-30 06:00:00"
    },
    {
        "open": 9.94,
        "high": 9.94,
        "low": 9.91,
        "close": 9.93,
        "volume": 1802,
        "datetime": "2021-12-31 06:00:00"
    },
    {
        "open": 9.93,
        "high": 9.9326,
        "low": 9.93,
        "close": 9.9326,
        "volume": 731,
        "datetime": "2022-01-03 06:00:00"
    },
    {
        "open": 9.91,
        "high": 9.98,
        "low": 9.91,
        "close": 9.96,
        "volume": 40318,
        "datetime": "2022-01-04 06:00:00"
    },
    {
        "open": 9.98,
        "high": 9.98,
        "low": 9.98,
        "close": 9.98,
        "volume": 253,
        "datetime": "2022-01-06 06:00:00"
    },
    {
        "open": 10.05,
        "high": 10.05,
        "low": 10.0,
        "close": 10.0,
        "volume": 1044,
        "datetime": "2022-01-07 06:00:00"
    },
    {
        "open": 9.97,
        "high": 9.97,
        "low": 9.95,
        "close": 9.97,
        "volume": 3825,
        "datetime": "2022-01-10 06:00:00"
    },
    {
        "open": 9.9662,
        "high": 9.97,
        "low": 9.9662,
        "close": 9.97,
        "volume": 1803,
        "datetime": "2022-01-12 06:00:00"
    },
    {
        "open": 9.97,
        "high": 9.97,
        "low": 9.9475,
        "close": 9.96,
        "volume": 21829,
        "datetime": "2022-01-13 06:00:00"
    },
    {
        "open": 9.98,
        "high": 9.98,
        "low": 9.98,
        "close": 9.98,
        "volume": 2164,
        "datetime": "2022-01-18 06:00:00"
    },
    {
        "open": 9.91,
        "high": 9.92,
        "low": 9.89,
        "close": 9.89,
        "volume": 9049,
        "datetime": "2022-01-21 06:00:00"
    },
    {
        "open": 9.89,
        "high": 9.905,
        "low": 9.86,
        "close": 9.86,
        "volume": 21865,
        "datetime": "2022-01-24 06:00:00"
    },
    {
        "open": 9.8744,
        "high": 9.93,
        "low": 9.8744,
        "close": 9.93,
        "volume": 31597,
        "datetime": "2022-01-25 06:00:00"
    },
    {
        "open": 9.95,
        "high": 9.95,
        "low": 9.94,
        "close": 9.94,
        "volume": 1333,
        "datetime": "2022-01-26 06:00:00"
    },
    {
        "open": 9.94,
        "high": 9.94,
        "low": 9.94,
        "close": 9.94,
        "volume": 2532,
        "datetime": "2022-01-31 06:00:00"
    },
    {
        "open": 9.94,
        "high": 9.94,
        "low": 9.9,
        "close": 9.94,
        "volume": 4739,
        "datetime": "2022-02-02 06:00:00"
    },
    {
        "open": 9.93,
        "high": 9.955,
        "low": 9.93,
        "close": 9.955,
        "volume": 5061,
        "datetime": "2022-02-03 06:00:00"
    },
    {
        "open": 9.95,
        "high": 9.95,
        "low": 9.95,
        "close": 9.95,
        "volume": 5319,
        "datetime": "2022-02-07 06:00:00"
    },
    {
        "open": 9.95,
        "high": 9.95,
        "low": 9.95,
        "close": 9.95,
        "volume": 77219,
        "datetime": "2022-02-08 06:00:00"
    },
    {
        "open": 10.0,
        "high": 10.0,
        "low": 9.88,
        "close": 9.92,
        "volume": 10425,
        "datetime": "2022-02-14 06:00:00"
    },
    {
        "open": 9.94,
        "high": 9.94,
        "low": 9.94,
        "close": 9.94,
        "volume": 2281,
        "datetime": "2022-02-18 06:00:00"
    },
    {
        "open": 9.9288,
        "high": 9.9288,
        "low": 9.87,
        "close": 9.87,
        "volume": 1028,
        "datetime": "2022-02-24 06:00:00"
    },
    {
        "open": 9.8311,
        "high": 9.9399,
        "low": 9.8311,
        "close": 9.9399,
        "volume": 200,
        "datetime": "2022-03-09 06:00:00"
    },
    {
        "open": 9.925,
        "high": 9.925,
        "low": 9.925,
        "close": 9.925,
        "volume": 56330,
        "datetime": "2022-03-28 05:00:00"
    },
    {
        "open": 9.88,
        "high": 9.88,
        "low": 9.87,
        "close": 9.87,
        "volume": 7600,
        "datetime": "2022-03-29 05:00:00"
    },
    {
        "open": 9.86,
        "high": 9.86,
        "low": 9.86,
        "close": 9.86,
        "volume": 200,
        "datetime": "2022-04-26 05:00:00"
    },
    {
        "open": 9.8739,
        "high": 9.99,
        "low": 9.8739,
        "close": 9.99,
        "volume": 522,
        "datetime": "2022-05-11 05:00:00"
    },
    {
        "open": 9.86,
        "high": 9.893,
        "low": 9.86,
        "close": 9.86,
        "volume": 5000,
        "datetime": "2022-05-23 05:00:00"
    },
    {
        "open": 9.79,
        "high": 9.9,
        "low": 9.7815,
        "close": 9.86,
        "volume": 20125,
        "datetime": "2022-05-25 05:00:00"
    },
    {
        "open": 9.89,
        "high": 9.9,
        "low": 9.85,
        "close": 9.85,
        "volume": 11575,
        "datetime": "2022-06-07 05:00:00"
    },
    {
        "open": 9.9,
        "high": 9.9,
        "low": 9.865,
        "close": 9.895,
        "volume": 4700,
        "datetime": "2022-06-09 05:00:00"
    },
    {
        "open": 9.94,
        "high": 9.94,
        "low": 9.94,
        "close": 9.94,
        "volume": 300,
        "datetime": "2022-06-10 05:00:00"
    },
    {
        "open": 9.84,
        "high": 9.94,
        "low": 9.84,
        "close": 9.94,
        "volume": 1600,
        "datetime": "2022-06-13 05:00:00"
    },
    {
        "open": 9.875,
        "high": 9.875,
        "low": 9.875,
        "close": 9.875,
        "volume": 200,
        "datetime": "2022-06-21 05:00:00"
    },
    {
        "open": 9.84,
        "high": 9.84,
        "low": 9.84,
        "close": 9.84,
        "volume": 102,
        "datetime": "2022-07-06 05:00:00"
    },
    {
        "open": 9.86,
        "high": 9.89,
        "low": 9.84,
        "close": 9.88,
        "volume": 16950,
        "datetime": "2022-07-11 05:00:00"
    }
]