[
    {
        "open": 1.05,
        "high": 1.05,
        "low": 1.05,
        "close": 1.05,
        "volume": 610,
        "datetime": "2022-05-27 13:30:00"
    },
    {
        "open": 1.0099,
        "high": 1.0099,
        "low": 1.0099,
        "close": 1.0099,
        "volume": 150,
        "datetime": "2022-05-27 13:46:00"
    },
    {
        "open": 1.01,
        "high": 1.01,
        "low": 1.01,
        "close": 1.01,
        "volume": 1200,
        "datetime": "2022-05-27 14:25:00"
    },
    {
        "open": 1.0,
        "high": 1.0,
        "low": 1.0,
        "close": 1.0,
        "volume": 2899,
        "datetime": "2022-05-27 15:10:00"
    },
    {
        "open": 1.005,
        "high": 1.01,
        "low": 1.005,
        "close": 1.01,
        "volume": 400,
        "datetime": "2022-05-27 15:18:00"
    },
    {
        "open": 1.01,
        "high": 1.01,
        "low": 1.01,
        "close": 1.01,
        "volume": 200,
        "datetime": "2022-05-27 15:30:00"
    },
    {
        "open": 1.005,
        "high": 1.01,
        "low": 1.005,
        "close": 1.01,
        "volume": 200,
        "datetime": "2022-05-27 15:37:00"
    },
    {
        "open": 1.01,
        "high": 1.01,
        "low": 1.005,
        "close": 1.01,
        "volume": 6125,
        "datetime": "2022-05-27 15:46:00"
    },
    {
        "open": 1.01,
        "high": 1.01,
        "low": 1.01,
        "close": 1.01,
        "volume": 200,
        "datetime": "2022-05-27 15:56:00"
    },
    {
        "open": 1.01,
        "high": 1.01,
        "low": 1.01,
        "close": 1.01,
        "volume": 100,
        "datetime": "2022-05-27 16:11:00"
    },
    {
        "open": 1.001,
        "high": 1.001,
        "low": 1.001,
        "close": 1.001,
        "volume": 1300,
        "datetime": "2022-05-27 16:37:00"
    },
    {
        "open": 1.01,
        "high": 1.02,
        "low": 1.01,
        "close": 1.015,
        "volume": 7797,
        "datetime": "2022-05-27 17:19:00"
    },
    {
        "open": 1.03,
        "high": 1.03,
        "low": 1.03,
        "close": 1.03,
        "volume": 200,
        "datetime": "2022-05-27 17:24:00"
    },
    {
        "open": 1.04,
        "high": 1.04,
        "low": 1.04,
        "close": 1.04,
        "volume": 100,
        "datetime": "2022-05-27 17:47:00"
    },
    {
        "open": 1.07,
        "high": 1.07,
        "low": 1.07,
        "close": 1.07,
        "volume": 100,
        "datetime": "2022-05-27 18:30:00"
    },
    {
        "open": 1.046,
        "high": 1.046,
        "low": 1.0427,
        "close": 1.0427,
        "volume": 2000,
        "datetime": "2022-05-27 18:32:00"
    },
    {
        "open": 1.04,
        "high": 1.04,
        "low": 1.04,
        "close": 1.04,
        "volume": 100,
        "datetime": "2022-05-27 18:38:00"
    },
    {
        "open": 1.0394,
        "high": 1.0394,
        "low": 1.0394,
        "close": 1.0394,
        "volume": 172,
        "datetime": "2022-05-27 18:50:00"
    },
    {
        "open": 1.04,
        "high": 1.04,
        "low": 1.04,
        "close": 1.04,
        "volume": 200,
        "datetime": "2022-05-27 19:11:00"
    },
    {
        "open": 1.05,
        "high": 1.05,
        "low": 1.05,
        "close": 1.05,
        "volume": 200,
        "datetime": "2022-05-27 19:59:00"
    },
    {
        "open": 1.47,
        "high": 1.47,
        "low": 1.47,
        "close": 1.47,
        "volume": 270,
        "datetime": "2022-05-31 12:48:00"
    },
    {
        "open": 1.37,
        "high": 1.37,
        "low": 1.37,
        "close": 1.37,
        "volume": 400,
        "datetime": "2022-05-31 12:55:00"
    },
    {
        "open": 1.35,
        "high": 1.35,
        "low": 1.35,
        "close": 1.35,
        "volume": 100,
        "datetime": "2022-05-31 12:58:00"
    },
    {
        "open": 1.08,
        "high": 1.08,
        "low": 1.08,
        "close": 1.08,
        "volume": 1201,
        "datetime": "2022-05-31 13:30:00"
    },
    {
        "open": 1.11,
        "high": 1.11,
        "low": 1.11,
        "close": 1.11,
        "volume": 144,
        "datetime": "2022-05-31 13:31:00"
    },
    {
        "open": 1.1,
        "high": 1.1,
        "low": 1.1,
        "close": 1.1,
        "volume": 400,
        "datetime": "2022-05-31 13:32:00"
    },
    {
        "open": 1.1,
        "high": 1.1,
        "low": 1.1,
        "close": 1.1,
        "volume": 144,
        "datetime": "2022-05-31 13:33:00"
    },
    {
        "open": 1.1,
        "high": 1.1,
        "low": 1.1,
        "close": 1.1,
        "volume": 101,
        "datetime": "2022-05-31 14:04:00"
    },
    {
        "open": 1.1,
        "high": 1.1,
        "low": 1.1,
        "close": 1.1,
        "volume": 300,
        "datetime": "2022-05-31 14:08:00"
    },
    {
        "open": 1.1257,
        "high": 1.1257,
        "low": 1.1257,
        "close": 1.1257,
        "volume": 750,
        "datetime": "2022-05-31 14:11:00"
    },
    {
        "open": 1.13,
        "high": 1.13,
        "low": 1.13,
        "close": 1.13,
        "volume": 157,
        "datetime": "2022-05-31 14:15:00"
    },
    {
        "open": 1.11,
        "high": 1.11,
        "low": 1.11,
        "close": 1.11,
        "volume": 1797,
        "datetime": "2022-05-31 14:45:00"
    },
    {
        "open": 1.1099,
        "high": 1.1099,
        "low": 1.1099,
        "close": 1.1099,
        "volume": 250,
        "datetime": "2022-05-31 14:47:00"
    },
    {
        "open": 1.0886,
        "high": 1.0886,
        "low": 1.0886,
        "close": 1.0886,
        "volume": 400,
        "datetime": "2022-05-31 15:06:00"
    },
    {
        "open": 1.0783,
        "high": 1.0783,
        "low": 1.0783,
        "close": 1.0783,
        "volume": 1801,
        "datetime": "2022-05-31 15:22:00"
    },
    {
        "open": 1.06,
        "high": 1.06,
        "low": 1.06,
        "close": 1.06,
        "volume": 1400,
        "datetime": "2022-05-31 15:32:00"
    },
    {
        "open": 1.07,
        "high": 1.07,
        "low": 1.07,
        "close": 1.07,
        "volume": 1500,
        "datetime": "2022-05-31 16:03:00"
    },
    {
        "open": 1.07,
        "high": 1.07,
        "low": 1.07,
        "close": 1.07,
        "volume": 400,
        "datetime": "2022-05-31 16:04:00"
    },
    {
        "open": 1.075,
        "high": 1.075,
        "low": 1.075,
        "close": 1.075,
        "volume": 350,
        "datetime": "2022-05-31 16:43:00"
    },
    {
        "open": 1.07,
        "high": 1.07,
        "low": 1.07,
        "close": 1.07,
        "volume": 100,
        "datetime": "2022-05-31 16:49:00"
    },
    {
        "open": 1.08,
        "high": 1.08,
        "low": 1.08,
        "close": 1.08,
        "volume": 1204,
        "datetime": "2022-05-31 16:56:00"
    },
    {
        "open": 1.07,
        "high": 1.07,
        "low": 1.07,
        "close": 1.07,
        "volume": 200,
        "datetime": "2022-05-31 17:27:00"
    },
    {
        "open": 1.07,
        "high": 1.07,
        "low": 1.0695,
        "close": 1.0695,
        "volume": 1460,
        "datetime": "2022-05-31 17:43:00"
    },
    {
        "open": 1.08,
        "high": 1.08,
        "low": 1.08,
        "close": 1.08,
        "volume": 100,
        "datetime": "2022-05-31 18:01:00"
    },
    {
        "open": 1.07,
        "high": 1.08,
        "low": 1.07,
        "close": 1.08,
        "volume": 2785,
        "datetime": "2022-05-31 18:30:00"
    },
    {
        "open": 1.0701,
        "high": 1.0701,
        "low": 1.0701,
        "close": 1.0701,
        "volume": 2115,
        "datetime": "2022-05-31 18:42:00"
    },
    {
        "open": 1.07,
        "high": 1.07,
        "low": 1.06,
        "close": 1.06,
        "volume": 3062,
        "datetime": "2022-05-31 18:56:00"
    },
    {
        "open": 1.06,
        "high": 1.06,
        "low": 1.06,
        "close": 1.06,
        "volume": 182,
        "datetime": "2022-05-31 19:11:00"
    },
    {
        "open": 1.06,
        "high": 1.06,
        "low": 1.06,
        "close": 1.06,
        "volume": 500,
        "datetime": "2022-05-31 19:17:00"
    },
    {
        "open": 1.06,
        "high": 1.06,
        "low": 1.06,
        "close": 1.06,
        "volume": 954,
        "datetime": "2022-05-31 19:50:00"
    },
    {
        "open": 1.06,
        "high": 1.06,
        "low": 1.06,
        "close": 1.06,
        "volume": 326,
        "datetime": "2022-05-31 19:57:00"
    },
    {
        "open": 1.11,
        "high": 1.2612,
        "low": 1.11,
        "close": 1.2612,
        "volume": 1285,
        "datetime": "2022-06-01 13:30:00"
    },
    {
        "open": 1.2248,
        "high": 1.2248,
        "low": 1.1533,
        "close": 1.1533,
        "volume": 683,
        "datetime": "2022-06-01 13:37:00"
    },
    {
        "open": 1.16,
        "high": 1.16,
        "low": 1.14,
        "close": 1.14,
        "volume": 880,
        "datetime": "2022-06-01 13:41:00"
    },
    {
        "open": 1.19,
        "high": 1.19,
        "low": 1.19,
        "close": 1.19,
        "volume": 150,
        "datetime": "2022-06-01 13:46:00"
    },
    {
        "open": 1.18,
        "high": 1.18,
        "low": 1.18,
        "close": 1.18,
        "volume": 790,
        "datetime": "2022-06-01 13:50:00"
    },
    {
        "open": 1.18,
        "high": 1.18,
        "low": 1.18,
        "close": 1.18,
        "volume": 100,
        "datetime": "2022-06-01 13:54:00"
    },
    {
        "open": 1.2,
        "high": 1.2,
        "low": 1.2,
        "close": 1.2,
        "volume": 214,
        "datetime": "2022-06-01 13:55:00"
    },
    {
        "open": 1.175,
        "high": 1.175,
        "low": 1.175,
        "close": 1.175,
        "volume": 418,
        "datetime": "2022-06-01 14:02:00"
    },
    {
        "open": 1.15,
        "high": 1.1525,
        "low": 1.14,
        "close": 1.1525,
        "volume": 3310,
        "datetime": "2022-06-01 14:07:00"
    },
    {
        "open": 1.16,
        "high": 1.16,
        "low": 1.16,
        "close": 1.16,
        "volume": 100,
        "datetime": "2022-06-01 14:36:00"
    },
    {
        "open": 1.15,
        "high": 1.15,
        "low": 1.15,
        "close": 1.15,
        "volume": 216,
        "datetime": "2022-06-01 14:48:00"
    },
    {
        "open": 1.0775,
        "high": 1.0775,
        "low": 1.0775,
        "close": 1.0775,
        "volume": 425,
        "datetime": "2022-06-01 16:27:00"
    },
    {
        "open": 1.1,
        "high": 1.1,
        "low": 1.0984,
        "close": 1.0984,
        "volume": 3600,
        "datetime": "2022-06-01 16:29:00"
    },
    {
        "open": 1.12,
        "high": 1.12,
        "low": 1.117,
        "close": 1.12,
        "volume": 700,
        "datetime": "2022-06-01 16:30:00"
    },
    {
        "open": 1.0932,
        "high": 1.0932,
        "low": 1.0932,
        "close": 1.0932,
        "volume": 300,
        "datetime": "2022-06-01 16:51:00"
    },
    {
        "open": 1.11,
        "high": 1.11,
        "low": 1.11,
        "close": 1.11,
        "volume": 100,
        "datetime": "2022-06-01 17:04:00"
    },
    {
        "open": 1.11,
        "high": 1.11,
        "low": 1.11,
        "close": 1.11,
        "volume": 100,
        "datetime": "2022-06-01 17:28:00"
    },
    {
        "open": 1.09,
        "high": 1.11,
        "low": 1.0885,
        "close": 1.0885,
        "volume": 3600,
        "datetime": "2022-06-01 18:00:00"
    },
    {
        "open": 1.11,
        "high": 1.12,
        "low": 1.11,
        "close": 1.12,
        "volume": 200,
        "datetime": "2022-06-01 18:01:00"
    },
    {
        "open": 1.13,
        "high": 1.13,
        "low": 1.13,
        "close": 1.13,
        "volume": 2200,
        "datetime": "2022-06-01 18:04:00"
    },
    {
        "open": 1.1242,
        "high": 1.1242,
        "low": 1.1242,
        "close": 1.1242,
        "volume": 153,
        "datetime": "2022-06-01 18:10:00"
    },
    {
        "open": 1.1242,
        "high": 1.1242,
        "low": 1.1242,
        "close": 1.1242,
        "volume": 200,
        "datetime": "2022-06-01 18:11:00"
    },
    {
        "open": 1.0954,
        "high": 1.0954,
        "low": 1.0954,
        "close": 1.0954,
        "volume": 400,
        "datetime": "2022-06-01 18:53:00"
    },
    {
        "open": 1.11,
        "high": 1.11,
        "low": 1.11,
        "close": 1.11,
        "volume": 100,
        "datetime": "2022-06-01 19:44:00"
    },
    {
        "open": 1.11,
        "high": 1.11,
        "low": 1.11,
        "close": 1.11,
        "volume": 518,
        "datetime": "2022-06-01 19:59:00"
    },
    {
        "open": 1.1,
        "high": 1.1,
        "low": 1.1,
        "close": 1.1,
        "volume": 300,
        "datetime": "2022-06-01 20:00:00"
    },
    {
        "open": 1.0689,
        "high": 1.0689,
        "low": 1.0689,
        "close": 1.0689,
        "volume": 291,
        "datetime": "2022-06-02 14:23:00"
    },
    {
        "open": 1.1,
        "high": 1.1,
        "low": 1.1,
        "close": 1.1,
        "volume": 506,
        "datetime": "2022-06-02 15:16:00"
    },
    {
        "open": 1.1,
        "high": 1.1,
        "low": 1.1,
        "close": 1.1,
        "volume": 101,
        "datetime": "2022-06-02 15:17:00"
    },
    {
        "open": 1.0971,
        "high": 1.0971,
        "low": 1.0971,
        "close": 1.0971,
        "volume": 400,
        "datetime": "2022-06-02 16:14:00"
    },
    {
        "open": 1.1,
        "high": 1.1,
        "low": 1.1,
        "close": 1.1,
        "volume": 300,
        "datetime": "2022-06-02 17:09:00"
    },
    {
        "open": 1.1,
        "high": 1.1,
        "low": 1.08,
        "close": 1.08,
        "volume": 400,
        "datetime": "2022-06-02 17:35:00"
    },
    {
        "open": 1.1,
        "high": 1.1,
        "low": 1.1,
        "close": 1.1,
        "volume": 100,
        "datetime": "2022-06-02 17:36:00"
    },
    {
        "open": 1.08,
        "high": 1.08,
        "low": 1.08,
        "close": 1.08,
        "volume": 300,
        "datetime": "2022-06-02 17:59:00"
    },
    {
        "open": 1.06,
        "high": 1.06,
        "low": 1.06,
        "close": 1.06,
        "volume": 6100,
        "datetime": "2022-06-02 19:47:00"
    },
    {
        "open": 1.0631,
        "high": 1.0631,
        "low": 1.0631,
        "close": 1.0631,
        "volume": 696,
        "datetime": "2022-06-02 19:54:00"
    },
    {
        "open": 1.06,
        "high": 1.06,
        "low": 1.06,
        "close": 1.06,
        "volume": 322,
        "datetime": "2022-06-02 20:00:00"
    },
    {
        "open": 1.06,
        "high": 1.06,
        "low": 1.06,
        "close": 1.06,
        "volume": 399,
        "datetime": "2022-06-03 14:05:00"
    },
    {
        "open": 1.0,
        "high": 1.0,
        "low": 1.0,
        "close": 1.0,
        "volume": 199,
        "datetime": "2022-06-03 15:29:00"
    },
    {
        "open": 1.02,
        "high": 1.02,
        "low": 1.01,
        "close": 1.01,
        "volume": 300,
        "datetime": "2022-06-03 15:52:00"
    },
    {
        "open": 1.015,
        "high": 1.02,
        "low": 1.015,
        "close": 1.02,
        "volume": 347,
        "datetime": "2022-06-03 15:54:00"
    },
    {
        "open": 1.015,
        "high": 1.015,
        "low": 1.015,
        "close": 1.015,
        "volume": 112,
        "datetime": "2022-06-03 16:28:00"
    },
    {
        "open": 1.02,
        "high": 1.02,
        "low": 1.011,
        "close": 1.011,
        "volume": 1500,
        "datetime": "2022-06-03 16:29:00"
    },
    {
        "open": 1.01,
        "high": 1.01,
        "low": 1.01,
        "close": 1.01,
        "volume": 698,
        "datetime": "2022-06-03 16:41:00"
    },
    {
        "open": 1.0,
        "high": 1.0,
        "low": 1.0,
        "close": 1.0,
        "volume": 100,
        "datetime": "2022-06-03 17:14:00"
    },
    {
        "open": 1.0,
        "high": 1.0,
        "low": 1.0,
        "close": 1.0,
        "volume": 100,
        "datetime": "2022-06-03 19:59:00"
    },
    {
        "open": 1.0,
        "high": 1.0,
        "low": 1.0,
        "close": 1.0,
        "volume": 139,
        "datetime": "2022-06-03 20:00:00"
    },
    {
        "open": 1.0,
        "high": 1.0,
        "low": 1.0,
        "close": 1.0,
        "volume": 1499,
        "datetime": "2022-06-06 13:30:00"
    },
    {
        "open": 1.0027,
        "high": 1.0027,
        "low": 1.0027,
        "close": 1.0027,
        "volume": 800,
        "datetime": "2022-06-06 13:51:00"
    },
    {
        "open": 1.02,
        "high": 1.02,
        "low": 1.02,
        "close": 1.02,
        "volume": 270,
        "datetime": "2022-06-06 14:06:00"
    },
    {
        "open": 1.01,
        "high": 1.02,
        "low": 1.01,
        "close": 1.0199,
        "volume": 737,
        "datetime": "2022-06-06 14:07:00"
    },
    {
        "open": 1.03,
        "high": 1.03,
        "low": 1.03,
        "close": 1.03,
        "volume": 100,
        "datetime": "2022-06-06 14:36:00"
    },
    {
        "open": 1.04,
        "high": 1.04,
        "low": 1.04,
        "close": 1.04,
        "volume": 100,
        "datetime": "2022-06-06 14:55:00"
    },
    {
        "open": 1.03,
        "high": 1.04,
        "low": 1.03,
        "close": 1.04,
        "volume": 1381,
        "datetime": "2022-06-06 15:02:00"
    },
    {
        "open": 1.03,
        "high": 1.03,
        "low": 1.03,
        "close": 1.03,
        "volume": 100,
        "datetime": "2022-06-06 15:05:00"
    },
    {
        "open": 1.03,
        "high": 1.0302,
        "low": 1.03,
        "close": 1.0302,
        "volume": 5388,
        "datetime": "2022-06-06 15:07:00"
    },
    {
        "open": 1.0009,
        "high": 1.0009,
        "low": 1.0009,
        "close": 1.0009,
        "volume": 4489,
        "datetime": "2022-06-06 15:16:00"
    },
    {
        "open": 1.0129,
        "high": 1.0129,
        "low": 1.0129,
        "close": 1.0129,
        "volume": 100,
        "datetime": "2022-06-06 15:27:00"
    },
    {
        "open": 1.02,
        "high": 1.02,
        "low": 1.02,
        "close": 1.02,
        "volume": 1500,
        "datetime": "2022-06-06 15:42:00"
    },
    {
        "open": 1.01,
        "high": 1.01,
        "low": 1.01,
        "close": 1.01,
        "volume": 100,
        "datetime": "2022-06-06 15:56:00"
    },
    {
        "open": 1.0,
        "high": 1.0,
        "low": 1.0,
        "close": 1.0,
        "volume": 2796,
        "datetime": "2022-06-06 16:03:00"
    },
    {
        "open": 1.01,
        "high": 1.01,
        "low": 1.01,
        "close": 1.01,
        "volume": 148,
        "datetime": "2022-06-06 16:47:00"
    },
    {
        "open": 1.0,
        "high": 1.0,
        "low": 1.0,
        "close": 1.0,
        "volume": 593,
        "datetime": "2022-06-06 17:13:00"
    },
    {
        "open": 1.01,
        "high": 1.01,
        "low": 1.01,
        "close": 1.01,
        "volume": 100,
        "datetime": "2022-06-06 19:07:00"
    },
    {
        "open": 0.99,
        "high": 0.99,
        "low": 0.99,
        "close": 0.99,
        "volume": 219,
        "datetime": "2022-06-07 13:30:00"
    },
    {
        "open": 1.0422,
        "high": 1.0422,
        "low": 1.0422,
        "close": 1.0422,
        "volume": 710,
        "datetime": "2022-06-07 13:36:00"
    },
    {
        "open": 1.025,
        "high": 1.025,
        "low": 1.025,
        "close": 1.025,
        "volume": 200,
        "datetime": "2022-06-07 13:46:00"
    },
    {
        "open": 1.02,
        "high": 1.02,
        "low": 1.02,
        "close": 1.02,
        "volume": 200,
        "datetime": "2022-06-07 14:26:00"
    },
    {
        "open": 1.02,
        "high": 1.02,
        "low": 1.02,
        "close": 1.02,
        "volume": 2497,
        "datetime": "2022-06-07 14:36:00"
    },
    {
        "open": 1.02,
        "high": 1.02,
        "low": 1.02,
        "close": 1.02,
        "volume": 100,
        "datetime": "2022-06-07 15:25:00"
    },
    {
        "open": 1.02,
        "high": 1.02,
        "low": 1.02,
        "close": 1.02,
        "volume": 100,
        "datetime": "2022-06-07 15:36:00"
    },
    {
        "open": 1.0031,
        "high": 1.0031,
        "low": 1.0031,
        "close": 1.0031,
        "volume": 800,
        "datetime": "2022-06-07 15:49:00"
    },
    {
        "open": 1.01,
        "high": 1.01,
        "low": 1.01,
        "close": 1.01,
        "volume": 100,
        "datetime": "2022-06-07 16:44:00"
    },
    {
        "open": 1.02,
        "high": 1.02,
        "low": 1.02,
        "close": 1.02,
        "volume": 168,
        "datetime": "2022-06-07 17:04:00"
    },
    {
        "open": 1.01,
        "high": 1.01,
        "low": 1.01,
        "close": 1.01,
        "volume": 100,
        "datetime": "2022-06-07 17:13:00"
    },
    {
        "open": 1.0,
        "high": 1.0044,
        "low": 0.99,
        "close": 1.0,
        "volume": 4044,
        "datetime": "2022-06-07 17:19:00"
    },
    {
        "open": 0.99,
        "high": 0.9901,
        "low": 0.98,
        "close": 0.98,
        "volume": 3138,
        "datetime": "2022-06-07 17:44:00"
    },
    {
        "open": 0.9339,
        "high": 0.9339,
        "low": 0.9339,
        "close": 0.9339,
        "volume": 500,
        "datetime": "2022-06-07 17:46:00"
    },
    {
        "open": 0.933799,
        "high": 0.933799,
        "low": 0.933799,
        "close": 0.933799,
        "volume": 1000,
        "datetime": "2022-06-07 17:52:00"
    },
    {
        "open": 0.93,
        "high": 0.93,
        "low": 0.93,
        "close": 0.93,
        "volume": 1300,
        "datetime": "2022-06-07 18:19:00"
    },
    {
        "open": 0.9339,
        "high": 0.9339,
        "low": 0.9339,
        "close": 0.9339,
        "volume": 200,
        "datetime": "2022-06-07 18:32:00"
    },
    {
        "open": 0.9488,
        "high": 0.9488,
        "low": 0.9488,
        "close": 0.9488,
        "volume": 1300,
        "datetime": "2022-06-07 19:13:00"
    },
    {
        "open": 0.968,
        "high": 0.968,
        "low": 0.968,
        "close": 0.968,
        "volume": 100,
        "datetime": "2022-06-07 19:52:00"
    },
    {
        "open": 0.946,
        "high": 0.946,
        "low": 0.946,
        "close": 0.946,
        "volume": 1002,
        "datetime": "2022-06-07 20:00:00"
    },
    {
        "open": 0.95,
        "high": 0.95,
        "low": 0.95,
        "close": 0.95,
        "volume": 1900,
        "datetime": "2022-06-08 14:17:00"
    },
    {
        "open": 0.9401,
        "high": 0.9401,
        "low": 0.92,
        "close": 0.92,
        "volume": 12307,
        "datetime": "2022-06-08 14:19:00"
    },
    {
        "open": 0.9262,
        "high": 0.9262,
        "low": 0.9262,
        "close": 0.9262,
        "volume": 200,
        "datetime": "2022-06-08 14:20:00"
    },
    {
        "open": 0.9201,
        "high": 0.9201,
        "low": 0.9201,
        "close": 0.9201,
        "volume": 100,
        "datetime": "2022-06-08 14:22:00"
    },
    {
        "open": 0.9201,
        "high": 0.9201,
        "low": 0.92,
        "close": 0.92,
        "volume": 12535,
        "datetime": "2022-06-08 14:35:00"
    },
    {
        "open": 0.897,
        "high": 0.897,
        "low": 0.897,
        "close": 0.897,
        "volume": 600,
        "datetime": "2022-06-08 14:36:00"
    },
    {
        "open": 0.891,
        "high": 0.891,
        "low": 0.891,
        "close": 0.891,
        "volume": 1000,
        "datetime": "2022-06-08 14:37:00"
    },
    {
        "open": 0.9755,
        "high": 0.9755,
        "low": 0.9755,
        "close": 0.9755,
        "volume": 300,
        "datetime": "2022-06-08 16:19:00"
    },
    {
        "open": 0.96,
        "high": 0.96,
        "low": 0.96,
        "close": 0.96,
        "volume": 17222,
        "datetime": "2022-06-08 17:01:00"
    },
    {
        "open": 0.9792,
        "high": 0.9792,
        "low": 0.9792,
        "close": 0.9792,
        "volume": 200,
        "datetime": "2022-06-08 17:20:00"
    },
    {
        "open": 0.9551,
        "high": 0.9551,
        "low": 0.9551,
        "close": 0.9551,
        "volume": 180,
        "datetime": "2022-06-08 17:37:00"
    },
    {
        "open": 0.979,
        "high": 0.979,
        "low": 0.931,
        "close": 0.931,
        "volume": 400,
        "datetime": "2022-06-08 17:49:00"
    },
    {
        "open": 0.9316,
        "high": 0.9316,
        "low": 0.9313,
        "close": 0.9316,
        "volume": 691,
        "datetime": "2022-06-08 17:50:00"
    },
    {
        "open": 0.9316,
        "high": 0.9316,
        "low": 0.9316,
        "close": 0.9316,
        "volume": 100,
        "datetime": "2022-06-08 17:51:00"
    },
    {
        "open": 0.98,
        "high": 0.98,
        "low": 0.98,
        "close": 0.98,
        "volume": 199,
        "datetime": "2022-06-08 19:40:00"
    },
    {
        "open": 0.999,
        "high": 0.999,
        "low": 0.999,
        "close": 0.999,
        "volume": 200,
        "datetime": "2022-06-08 19:45:00"
    },
    {
        "open": 1.0,
        "high": 1.0,
        "low": 1.0,
        "close": 1.0,
        "volume": 300,
        "datetime": "2022-06-08 19:46:00"
    },
    {
        "open": 0.95,
        "high": 0.95,
        "low": 0.95,
        "close": 0.95,
        "volume": 1000,
        "datetime": "2022-06-08 19:47:00"
    },
    {
        "open": 1.02,
        "high": 1.02,
        "low": 1.02,
        "close": 1.02,
        "volume": 100,
        "datetime": "2022-06-08 19:59:00"
    },
    {
        "open": 0.996,
        "high": 0.996,
        "low": 0.996,
        "close": 0.996,
        "volume": 330,
        "datetime": "2022-06-08 20:00:00"
    },
    {
        "open": 0.998999,
        "high": 0.998999,
        "low": 0.998999,
        "close": 0.998999,
        "volume": 100,
        "datetime": "2022-06-09 14:48:00"
    },
    {
        "open": 0.9501,
        "high": 0.9501,
        "low": 0.9501,
        "close": 0.9501,
        "volume": 361,
        "datetime": "2022-06-09 15:07:00"
    },
    {
        "open": 0.959899,
        "high": 0.959899,
        "low": 0.959899,
        "close": 0.959899,
        "volume": 167,
        "datetime": "2022-06-09 15:28:00"
    },
    {
        "open": 0.96,
        "high": 0.96,
        "low": 0.96,
        "close": 0.96,
        "volume": 300,
        "datetime": "2022-06-09 17:37:00"
    },
    {
        "open": 0.9856,
        "high": 0.9856,
        "low": 0.9856,
        "close": 0.9856,
        "volume": 100,
        "datetime": "2022-06-09 17:39:00"
    },
    {
        "open": 0.9856,
        "high": 0.9856,
        "low": 0.9856,
        "close": 0.9856,
        "volume": 100,
        "datetime": "2022-06-09 18:59:00"
    },
    {
        "open": 0.9857,
        "high": 0.9857,
        "low": 0.9856,
        "close": 0.9856,
        "volume": 900,
        "datetime": "2022-06-09 19:00:00"
    },
    {
        "open": 0.9894,
        "high": 0.9894,
        "low": 0.96,
        "close": 0.96,
        "volume": 200,
        "datetime": "2022-06-09 19:06:00"
    },
    {
        "open": 0.95,
        "high": 0.95,
        "low": 0.95,
        "close": 0.95,
        "volume": 2419,
        "datetime": "2022-06-09 19:25:00"
    },
    {
        "open": 0.950001,
        "high": 0.969751,
        "low": 0.950001,
        "close": 0.969751,
        "volume": 2500,
        "datetime": "2022-06-09 19:26:00"
    },
    {
        "open": 0.95,
        "high": 0.95,
        "low": 0.95,
        "close": 0.95,
        "volume": 2500,
        "datetime": "2022-06-09 19:27:00"
    },
    {
        "open": 0.9894,
        "high": 0.9894,
        "low": 0.9894,
        "close": 0.9894,
        "volume": 100,
        "datetime": "2022-06-09 19:33:00"
    },
    {
        "open": 0.95,
        "high": 0.95,
        "low": 0.95,
        "close": 0.95,
        "volume": 2500,
        "datetime": "2022-06-09 19:35:00"
    },
    {
        "open": 0.95,
        "high": 0.95,
        "low": 0.95,
        "close": 0.95,
        "volume": 2500,
        "datetime": "2022-06-09 19:37:00"
    },
    {
        "open": 0.950001,
        "high": 0.9697,
        "low": 0.950001,
        "close": 0.9697,
        "volume": 2500,
        "datetime": "2022-06-09 19:38:00"
    },
    {
        "open": 0.95,
        "high": 0.95,
        "low": 0.95,
        "close": 0.95,
        "volume": 2500,
        "datetime": "2022-06-09 19:39:00"
    },
    {
        "open": 0.95,
        "high": 0.95,
        "low": 0.95,
        "close": 0.95,
        "volume": 2500,
        "datetime": "2022-06-09 19:40:00"
    },
    {
        "open": 0.95,
        "high": 0.95,
        "low": 0.95,
        "close": 0.95,
        "volume": 4201,
        "datetime": "2022-06-09 19:42:00"
    },
    {
        "open": 0.95,
        "high": 0.95,
        "low": 0.95,
        "close": 0.95,
        "volume": 2900,
        "datetime": "2022-06-09 19:43:00"
    },
    {
        "open": 0.9894,
        "high": 0.9894,
        "low": 0.9894,
        "close": 0.9894,
        "volume": 100,
        "datetime": "2022-06-09 19:49:00"
    },
    {
        "open": 0.9697,
        "high": 0.9697,
        "low": 0.9697,
        "close": 0.9697,
        "volume": 100,
        "datetime": "2022-06-09 19:56:00"
    },
    {
        "open": 0.9299,
        "high": 0.9299,
        "low": 0.9299,
        "close": 0.9299,
        "volume": 221,
        "datetime": "2022-06-10 15:33:00"
    },
    {
        "open": 0.929899,
        "high": 0.929899,
        "low": 0.929899,
        "close": 0.929899,
        "volume": 200,
        "datetime": "2022-06-10 15:58:00"
    },
    {
        "open": 0.9299,
        "high": 0.93,
        "low": 0.9299,
        "close": 0.93,
        "volume": 1300,
        "datetime": "2022-06-10 15:59:00"
    },
    {
        "open": 0.9015,
        "high": 0.9015,
        "low": 0.75,
        "close": 0.753,
        "volume": 7515,
        "datetime": "2022-06-10 17:11:00"
    },
    {
        "open": 0.763,
        "high": 0.763,
        "low": 0.763,
        "close": 0.763,
        "volume": 100,
        "datetime": "2022-06-10 17:12:00"
    },
    {
        "open": 0.770101,
        "high": 0.770101,
        "low": 0.770101,
        "close": 0.770101,
        "volume": 1000,
        "datetime": "2022-06-10 17:25:00"
    },
    {
        "open": 0.7727,
        "high": 0.7727,
        "low": 0.7727,
        "close": 0.7727,
        "volume": 1200,
        "datetime": "2022-06-10 17:28:00"
    },
    {
        "open": 0.7727,
        "high": 0.79,
        "low": 0.7727,
        "close": 0.7727,
        "volume": 600,
        "datetime": "2022-06-10 17:29:00"
    },
    {
        "open": 0.92,
        "high": 0.92,
        "low": 0.92,
        "close": 0.92,
        "volume": 100,
        "datetime": "2022-06-10 17:32:00"
    },
    {
        "open": 0.925,
        "high": 0.925,
        "low": 0.925,
        "close": 0.925,
        "volume": 100,
        "datetime": "2022-06-10 17:35:00"
    },
    {
        "open": 0.9249,
        "high": 0.925,
        "low": 0.9249,
        "close": 0.925,
        "volume": 1200,
        "datetime": "2022-06-10 17:40:00"
    },
    {
        "open": 0.8685,
        "high": 0.8685,
        "low": 0.8685,
        "close": 0.8685,
        "volume": 100,
        "datetime": "2022-06-10 17:44:00"
    },
    {
        "open": 0.8591,
        "high": 0.87555,
        "low": 0.8591,
        "close": 0.87555,
        "volume": 420,
        "datetime": "2022-06-10 18:12:00"
    },
    {
        "open": 0.9249,
        "high": 0.9249,
        "low": 0.9249,
        "close": 0.9249,
        "volume": 200,
        "datetime": "2022-06-10 19:03:00"
    },
    {
        "open": 0.892,
        "high": 0.892,
        "low": 0.892,
        "close": 0.892,
        "volume": 200,
        "datetime": "2022-06-10 19:15:00"
    },
    {
        "open": 0.925,
        "high": 0.925,
        "low": 0.925,
        "close": 0.925,
        "volume": 100,
        "datetime": "2022-06-10 19:16:00"
    }
]