[
    {
        "open": 1.94,
        "high": 1.94,
        "low": 1.94,
        "close": 1.94,
        "volume": 249,
        "datetime": "2022-05-27 13:30:00"
    },
    {
        "open": 1.9364,
        "high": 1.9364,
        "low": 1.9364,
        "close": 1.9364,
        "volume": 458,
        "datetime": "2022-05-27 14:01:00"
    },
    {
        "open": 1.9271,
        "high": 1.9271,
        "low": 1.9271,
        "close": 1.9271,
        "volume": 500,
        "datetime": "2022-05-27 14:28:00"
    },
    {
        "open": 1.9074,
        "high": 1.9074,
        "low": 1.9074,
        "close": 1.9074,
        "volume": 1000,
        "datetime": "2022-05-27 14:41:00"
    },
    {
        "open": 1.9016,
        "high": 1.9016,
        "low": 1.9016,
        "close": 1.9016,
        "volume": 1000,
        "datetime": "2022-05-27 14:42:00"
    },
    {
        "open": 1.902,
        "high": 1.902,
        "low": 1.902,
        "close": 1.902,
        "volume": 187,
        "datetime": "2022-05-27 14:43:00"
    },
    {
        "open": 1.9,
        "high": 1.9048,
        "low": 1.9,
        "close": 1.9048,
        "volume": 1836,
        "datetime": "2022-05-27 14:49:00"
    },
    {
        "open": 1.885,
        "high": 1.91,
        "low": 1.885,
        "close": 1.91,
        "volume": 2000,
        "datetime": "2022-05-27 15:05:00"
    },
    {
        "open": 1.9,
        "high": 1.91,
        "low": 1.9,
        "close": 1.91,
        "volume": 400,
        "datetime": "2022-05-27 15:39:00"
    },
    {
        "open": 1.87,
        "high": 1.87,
        "low": 1.87,
        "close": 1.87,
        "volume": 1968,
        "datetime": "2022-05-27 16:07:00"
    },
    {
        "open": 1.876,
        "high": 1.876,
        "low": 1.876,
        "close": 1.876,
        "volume": 100,
        "datetime": "2022-05-27 16:13:00"
    },
    {
        "open": 1.8756,
        "high": 1.9,
        "low": 1.8756,
        "close": 1.9,
        "volume": 600,
        "datetime": "2022-05-27 16:15:00"
    },
    {
        "open": 1.895,
        "high": 1.91,
        "low": 1.895,
        "close": 1.91,
        "volume": 400,
        "datetime": "2022-05-27 18:12:00"
    },
    {
        "open": 1.895,
        "high": 1.895,
        "low": 1.895,
        "close": 1.895,
        "volume": 200,
        "datetime": "2022-05-27 18:30:00"
    },
    {
        "open": 1.91,
        "high": 1.91,
        "low": 1.91,
        "close": 1.91,
        "volume": 400,
        "datetime": "2022-05-27 18:37:00"
    },
    {
        "open": 1.91,
        "high": 1.91,
        "low": 1.91,
        "close": 1.91,
        "volume": 400,
        "datetime": "2022-05-27 18:39:00"
    },
    {
        "open": 1.91,
        "high": 1.91,
        "low": 1.89,
        "close": 1.89,
        "volume": 600,
        "datetime": "2022-05-27 18:54:00"
    },
    {
        "open": 1.91,
        "high": 1.91,
        "low": 1.91,
        "close": 1.91,
        "volume": 300,
        "datetime": "2022-05-27 18:55:00"
    },
    {
        "open": 1.9076,
        "high": 1.9076,
        "low": 1.9073,
        "close": 1.9073,
        "volume": 400,
        "datetime": "2022-05-27 18:57:00"
    },
    {
        "open": 1.9,
        "high": 1.9,
        "low": 1.9,
        "close": 1.9,
        "volume": 500,
        "datetime": "2022-05-27 19:00:00"
    },
    {
        "open": 1.8889,
        "high": 1.8889,
        "low": 1.8889,
        "close": 1.8889,
        "volume": 100,
        "datetime": "2022-05-27 19:24:00"
    },
    {
        "open": 1.8828,
        "high": 1.885,
        "low": 1.8685,
        "close": 1.8685,
        "volume": 2200,
        "datetime": "2022-05-27 19:31:00"
    },
    {
        "open": 1.8796,
        "high": 1.8796,
        "low": 1.8796,
        "close": 1.8796,
        "volume": 100,
        "datetime": "2022-05-27 19:32:00"
    },
    {
        "open": 1.91,
        "high": 1.91,
        "low": 1.91,
        "close": 1.91,
        "volume": 1000,
        "datetime": "2022-05-27 19:41:00"
    },
    {
        "open": 1.9,
        "high": 1.91,
        "low": 1.9,
        "close": 1.91,
        "volume": 200,
        "datetime": "2022-05-27 19:59:00"
    },
    {
        "open": 1.93,
        "high": 1.93,
        "low": 1.93,
        "close": 1.93,
        "volume": 1039,
        "datetime": "2022-05-31 13:30:00"
    },
    {
        "open": 1.939,
        "high": 1.939,
        "low": 1.939,
        "close": 1.939,
        "volume": 360,
        "datetime": "2022-05-31 13:35:00"
    },
    {
        "open": 1.885,
        "high": 1.885,
        "low": 1.885,
        "close": 1.885,
        "volume": 710,
        "datetime": "2022-05-31 15:40:00"
    },
    {
        "open": 1.885,
        "high": 1.885,
        "low": 1.885,
        "close": 1.885,
        "volume": 400,
        "datetime": "2022-05-31 16:06:00"
    },
    {
        "open": 1.885,
        "high": 1.885,
        "low": 1.885,
        "close": 1.885,
        "volume": 143,
        "datetime": "2022-05-31 16:37:00"
    },
    {
        "open": 1.885,
        "high": 1.885,
        "low": 1.885,
        "close": 1.885,
        "volume": 202,
        "datetime": "2022-05-31 17:34:00"
    },
    {
        "open": 1.9074,
        "high": 1.91,
        "low": 1.9074,
        "close": 1.91,
        "volume": 200,
        "datetime": "2022-05-31 17:42:00"
    },
    {
        "open": 1.85,
        "high": 1.85,
        "low": 1.85,
        "close": 1.85,
        "volume": 100,
        "datetime": "2022-05-31 17:44:00"
    },
    {
        "open": 1.92,
        "high": 1.92,
        "low": 1.92,
        "close": 1.92,
        "volume": 502,
        "datetime": "2022-05-31 17:46:00"
    },
    {
        "open": 1.92,
        "high": 1.92,
        "low": 1.92,
        "close": 1.92,
        "volume": 730,
        "datetime": "2022-05-31 17:47:00"
    },
    {
        "open": 1.91,
        "high": 1.91,
        "low": 1.89,
        "close": 1.89,
        "volume": 1000,
        "datetime": "2022-05-31 19:03:00"
    },
    {
        "open": 1.89,
        "high": 1.89,
        "low": 1.89,
        "close": 1.89,
        "volume": 200,
        "datetime": "2022-05-31 19:10:00"
    },
    {
        "open": 2.05,
        "high": 2.1,
        "low": 2.05,
        "close": 2.1,
        "volume": 982,
        "datetime": "2022-06-01 13:14:00"
    },
    {
        "open": 1.9,
        "high": 1.9,
        "low": 1.9,
        "close": 1.9,
        "volume": 109,
        "datetime": "2022-06-01 13:30:00"
    },
    {
        "open": 1.91,
        "high": 1.91,
        "low": 1.91,
        "close": 1.91,
        "volume": 196,
        "datetime": "2022-06-01 13:32:00"
    },
    {
        "open": 1.9126,
        "high": 1.9126,
        "low": 1.9126,
        "close": 1.9126,
        "volume": 100,
        "datetime": "2022-06-01 13:37:00"
    },
    {
        "open": 1.91,
        "high": 1.91,
        "low": 1.91,
        "close": 1.91,
        "volume": 200,
        "datetime": "2022-06-01 15:11:00"
    },
    {
        "open": 1.9199,
        "high": 1.9199,
        "low": 1.9199,
        "close": 1.9199,
        "volume": 675,
        "datetime": "2022-06-01 15:32:00"
    },
    {
        "open": 1.91,
        "high": 1.91,
        "low": 1.91,
        "close": 1.91,
        "volume": 100,
        "datetime": "2022-06-01 18:21:00"
    },
    {
        "open": 1.91,
        "high": 1.92,
        "low": 1.9,
        "close": 1.92,
        "volume": 1550,
        "datetime": "2022-06-01 18:30:00"
    },
    {
        "open": 1.92,
        "high": 1.92,
        "low": 1.92,
        "close": 1.92,
        "volume": 100,
        "datetime": "2022-06-01 18:31:00"
    },
    {
        "open": 1.91,
        "high": 1.92,
        "low": 1.91,
        "close": 1.92,
        "volume": 594,
        "datetime": "2022-06-01 18:39:00"
    },
    {
        "open": 1.88,
        "high": 1.92,
        "low": 1.88,
        "close": 1.8926,
        "volume": 5900,
        "datetime": "2022-06-02 13:35:00"
    },
    {
        "open": 1.9199,
        "high": 1.94,
        "low": 1.886,
        "close": 1.8957,
        "volume": 4100,
        "datetime": "2022-06-02 13:36:00"
    },
    {
        "open": 1.906,
        "high": 1.94,
        "low": 1.906,
        "close": 1.915,
        "volume": 10486,
        "datetime": "2022-06-02 13:37:00"
    },
    {
        "open": 1.98,
        "high": 1.99,
        "low": 1.915,
        "close": 1.9363,
        "volume": 4897,
        "datetime": "2022-06-02 13:38:00"
    },
    {
        "open": 1.986,
        "high": 1.99,
        "low": 1.915,
        "close": 1.9856,
        "volume": 3494,
        "datetime": "2022-06-02 13:39:00"
    },
    {
        "open": 1.99,
        "high": 1.99,
        "low": 1.915,
        "close": 1.915,
        "volume": 1800,
        "datetime": "2022-06-02 13:41:00"
    },
    {
        "open": 1.9585,
        "high": 1.9585,
        "low": 1.9585,
        "close": 1.9585,
        "volume": 1327,
        "datetime": "2022-06-02 13:43:00"
    },
    {
        "open": 1.9441,
        "high": 1.9441,
        "low": 1.915,
        "close": 1.9441,
        "volume": 2901,
        "datetime": "2022-06-02 13:44:00"
    },
    {
        "open": 1.92,
        "high": 1.94,
        "low": 1.92,
        "close": 1.94,
        "volume": 2631,
        "datetime": "2022-06-02 15:19:00"
    },
    {
        "open": 1.95,
        "high": 1.95,
        "low": 1.95,
        "close": 1.95,
        "volume": 3400,
        "datetime": "2022-06-02 17:11:00"
    },
    {
        "open": 1.93,
        "high": 1.93,
        "low": 1.93,
        "close": 1.93,
        "volume": 100,
        "datetime": "2022-06-02 17:12:00"
    },
    {
        "open": 1.93,
        "high": 1.93,
        "low": 1.93,
        "close": 1.93,
        "volume": 300,
        "datetime": "2022-06-02 18:48:00"
    },
    {
        "open": 1.93,
        "high": 1.93,
        "low": 1.93,
        "close": 1.93,
        "volume": 200,
        "datetime": "2022-06-02 19:46:00"
    },
    {
        "open": 1.9499,
        "high": 1.9499,
        "low": 1.9499,
        "close": 1.9499,
        "volume": 350,
        "datetime": "2022-06-03 13:39:00"
    },
    {
        "open": 1.91,
        "high": 1.91,
        "low": 1.91,
        "close": 1.91,
        "volume": 700,
        "datetime": "2022-06-03 14:29:00"
    },
    {
        "open": 1.91,
        "high": 1.91,
        "low": 1.9,
        "close": 1.9012,
        "volume": 1100,
        "datetime": "2022-06-03 14:32:00"
    },
    {
        "open": 1.9001,
        "high": 1.9001,
        "low": 1.9001,
        "close": 1.9001,
        "volume": 600,
        "datetime": "2022-06-03 14:37:00"
    },
    {
        "open": 1.9,
        "high": 1.9,
        "low": 1.8501,
        "close": 1.8501,
        "volume": 2437,
        "datetime": "2022-06-03 14:38:00"
    },
    {
        "open": 1.8945,
        "high": 1.8945,
        "low": 1.86,
        "close": 1.86,
        "volume": 600,
        "datetime": "2022-06-03 14:42:00"
    },
    {
        "open": 1.9499,
        "high": 1.9499,
        "low": 1.9499,
        "close": 1.9499,
        "volume": 100,
        "datetime": "2022-06-03 14:49:00"
    },
    {
        "open": 1.9443,
        "high": 1.9443,
        "low": 1.9443,
        "close": 1.9443,
        "volume": 993,
        "datetime": "2022-06-03 17:41:00"
    },
    {
        "open": 1.94,
        "high": 1.95,
        "low": 1.94,
        "close": 1.95,
        "volume": 600,
        "datetime": "2022-06-03 18:36:00"
    },
    {
        "open": 1.92,
        "high": 1.92,
        "low": 1.92,
        "close": 1.92,
        "volume": 100,
        "datetime": "2022-06-03 19:52:00"
    },
    {
        "open": 1.87,
        "high": 1.87,
        "low": 1.87,
        "close": 1.87,
        "volume": 1491,
        "datetime": "2022-06-06 13:30:00"
    },
    {
        "open": 1.94,
        "high": 1.96,
        "low": 1.934,
        "close": 1.9498,
        "volume": 8786,
        "datetime": "2022-06-06 13:35:00"
    },
    {
        "open": 1.9499,
        "high": 1.95,
        "low": 1.949,
        "close": 1.9499,
        "volume": 2541,
        "datetime": "2022-06-06 13:39:00"
    },
    {
        "open": 1.9223,
        "high": 1.9223,
        "low": 1.9223,
        "close": 1.9223,
        "volume": 100,
        "datetime": "2022-06-06 14:05:00"
    },
    {
        "open": 1.9599,
        "high": 1.9599,
        "low": 1.9599,
        "close": 1.9599,
        "volume": 100,
        "datetime": "2022-06-06 14:06:00"
    },
    {
        "open": 1.96,
        "high": 1.96,
        "low": 1.96,
        "close": 1.96,
        "volume": 380,
        "datetime": "2022-06-06 14:30:00"
    },
    {
        "open": 1.9,
        "high": 1.92,
        "low": 1.9,
        "close": 1.92,
        "volume": 2097,
        "datetime": "2022-06-06 15:26:00"
    },
    {
        "open": 1.9597,
        "high": 1.9597,
        "low": 1.9597,
        "close": 1.9597,
        "volume": 990,
        "datetime": "2022-06-06 15:30:00"
    },
    {
        "open": 1.95,
        "high": 1.955,
        "low": 1.95,
        "close": 1.955,
        "volume": 500,
        "datetime": "2022-06-06 15:40:00"
    },
    {
        "open": 1.9599,
        "high": 1.9599,
        "low": 1.9599,
        "close": 1.9599,
        "volume": 400,
        "datetime": "2022-06-06 15:59:00"
    },
    {
        "open": 1.955,
        "high": 1.955,
        "low": 1.955,
        "close": 1.955,
        "volume": 100,
        "datetime": "2022-06-06 16:07:00"
    },
    {
        "open": 1.96,
        "high": 1.96,
        "low": 1.96,
        "close": 1.96,
        "volume": 900,
        "datetime": "2022-06-06 17:48:00"
    },
    {
        "open": 1.955,
        "high": 1.955,
        "low": 1.955,
        "close": 1.955,
        "volume": 100,
        "datetime": "2022-06-06 17:50:00"
    },
    {
        "open": 1.955,
        "high": 1.955,
        "low": 1.955,
        "close": 1.955,
        "volume": 100,
        "datetime": "2022-06-06 17:52:00"
    },
    {
        "open": 1.955,
        "high": 1.955,
        "low": 1.955,
        "close": 1.955,
        "volume": 1000,
        "datetime": "2022-06-06 18:03:00"
    },
    {
        "open": 1.955,
        "high": 1.955,
        "low": 1.955,
        "close": 1.955,
        "volume": 200,
        "datetime": "2022-06-06 18:12:00"
    },
    {
        "open": 1.95,
        "high": 1.9502,
        "low": 1.95,
        "close": 1.9502,
        "volume": 200,
        "datetime": "2022-06-06 18:19:00"
    },
    {
        "open": 1.955,
        "high": 1.955,
        "low": 1.955,
        "close": 1.955,
        "volume": 100,
        "datetime": "2022-06-06 18:30:00"
    },
    {
        "open": 1.955,
        "high": 1.955,
        "low": 1.955,
        "close": 1.955,
        "volume": 100,
        "datetime": "2022-06-06 18:47:00"
    },
    {
        "open": 1.9599,
        "high": 1.9599,
        "low": 1.9599,
        "close": 1.9599,
        "volume": 500,
        "datetime": "2022-06-06 18:57:00"
    },
    {
        "open": 1.96,
        "high": 1.96,
        "low": 1.955,
        "close": 1.955,
        "volume": 700,
        "datetime": "2022-06-06 18:58:00"
    },
    {
        "open": 1.95,
        "high": 1.9522,
        "low": 1.95,
        "close": 1.9522,
        "volume": 600,
        "datetime": "2022-06-06 19:06:00"
    },
    {
        "open": 1.95,
        "high": 1.96,
        "low": 1.95,
        "close": 1.96,
        "volume": 613,
        "datetime": "2022-06-06 19:55:00"
    },
    {
        "open": 1.88,
        "high": 1.88,
        "low": 1.88,
        "close": 1.88,
        "volume": 960,
        "datetime": "2022-06-06 19:56:00"
    },
    {
        "open": 1.92,
        "high": 1.92,
        "low": 1.92,
        "close": 1.92,
        "volume": 927,
        "datetime": "2022-06-07 13:30:00"
    },
    {
        "open": 1.9164,
        "high": 1.9164,
        "low": 1.9164,
        "close": 1.9164,
        "volume": 239,
        "datetime": "2022-06-07 14:00:00"
    },
    {
        "open": 1.92,
        "high": 1.9495,
        "low": 1.92,
        "close": 1.9495,
        "volume": 406,
        "datetime": "2022-06-07 14:01:00"
    },
    {
        "open": 1.94,
        "high": 1.94,
        "low": 1.94,
        "close": 1.94,
        "volume": 100,
        "datetime": "2022-06-07 14:25:00"
    },
    {
        "open": 1.94,
        "high": 1.95,
        "low": 1.94,
        "close": 1.95,
        "volume": 500,
        "datetime": "2022-06-07 14:31:00"
    },
    {
        "open": 1.95,
        "high": 1.98,
        "low": 1.9492,
        "close": 1.98,
        "volume": 12218,
        "datetime": "2022-06-07 14:38:00"
    },
    {
        "open": 1.9768,
        "high": 2.0,
        "low": 1.9768,
        "close": 1.9768,
        "volume": 5117,
        "datetime": "2022-06-07 14:55:00"
    },
    {
        "open": 1.9778,
        "high": 1.98,
        "low": 1.9778,
        "close": 1.98,
        "volume": 841,
        "datetime": "2022-06-07 14:58:00"
    },
    {
        "open": 1.98,
        "high": 1.98,
        "low": 1.98,
        "close": 1.98,
        "volume": 1239,
        "datetime": "2022-06-07 15:02:00"
    },
    {
        "open": 1.9664,
        "high": 1.9664,
        "low": 1.9664,
        "close": 1.9664,
        "volume": 250,
        "datetime": "2022-06-07 15:04:00"
    },
    {
        "open": 1.9646,
        "high": 1.9646,
        "low": 1.9646,
        "close": 1.9646,
        "volume": 1110,
        "datetime": "2022-06-07 16:11:00"
    },
    {
        "open": 1.97,
        "high": 1.97,
        "low": 1.97,
        "close": 1.97,
        "volume": 100,
        "datetime": "2022-06-07 16:25:00"
    },
    {
        "open": 1.97,
        "high": 1.97,
        "low": 1.97,
        "close": 1.97,
        "volume": 100,
        "datetime": "2022-06-07 16:27:00"
    },
    {
        "open": 1.96,
        "high": 1.96,
        "low": 1.92,
        "close": 1.93,
        "volume": 1949,
        "datetime": "2022-06-07 17:22:00"
    },
    {
        "open": 1.97,
        "high": 1.98,
        "low": 1.97,
        "close": 1.98,
        "volume": 700,
        "datetime": "2022-06-07 17:24:00"
    },
    {
        "open": 1.9436,
        "high": 1.9436,
        "low": 1.9436,
        "close": 1.9436,
        "volume": 364,
        "datetime": "2022-06-07 18:45:00"
    },
    {
        "open": 1.95,
        "high": 1.95,
        "low": 1.95,
        "close": 1.95,
        "volume": 300,
        "datetime": "2022-06-07 19:00:00"
    },
    {
        "open": 1.9207,
        "high": 1.9207,
        "low": 1.9207,
        "close": 1.9207,
        "volume": 1000,
        "datetime": "2022-06-07 19:11:00"
    },
    {
        "open": 1.95,
        "high": 1.95,
        "low": 1.95,
        "close": 1.95,
        "volume": 100,
        "datetime": "2022-06-07 19:15:00"
    },
    {
        "open": 1.95,
        "high": 1.95,
        "low": 1.95,
        "close": 1.95,
        "volume": 100,
        "datetime": "2022-06-07 19:21:00"
    },
    {
        "open": 1.97,
        "high": 1.97,
        "low": 1.97,
        "close": 1.97,
        "volume": 215,
        "datetime": "2022-06-07 19:40:00"
    },
    {
        "open": 1.955,
        "high": 1.955,
        "low": 1.955,
        "close": 1.955,
        "volume": 200,
        "datetime": "2022-06-07 19:49:00"
    },
    {
        "open": 1.98,
        "high": 1.98,
        "low": 1.98,
        "close": 1.98,
        "volume": 400,
        "datetime": "2022-06-07 19:51:00"
    },
    {
        "open": 1.98,
        "high": 1.98,
        "low": 1.98,
        "close": 1.98,
        "volume": 2200,
        "datetime": "2022-06-07 19:53:00"
    },
    {
        "open": 1.975,
        "high": 1.975,
        "low": 1.975,
        "close": 1.975,
        "volume": 100,
        "datetime": "2022-06-07 19:54:00"
    },
    {
        "open": 1.98,
        "high": 1.99,
        "low": 1.98,
        "close": 1.99,
        "volume": 4319,
        "datetime": "2022-06-07 19:55:00"
    },
    {
        "open": 1.99,
        "high": 2.0,
        "low": 1.99,
        "close": 2.0,
        "volume": 700,
        "datetime": "2022-06-07 19:57:00"
    },
    {
        "open": 1.99,
        "high": 1.99,
        "low": 1.99,
        "close": 1.99,
        "volume": 605,
        "datetime": "2022-06-07 20:00:00"
    },
    {
        "open": 1.97,
        "high": 1.97,
        "low": 1.97,
        "close": 1.97,
        "volume": 486,
        "datetime": "2022-06-08 13:30:00"
    },
    {
        "open": 1.95,
        "high": 1.95,
        "low": 1.95,
        "close": 1.95,
        "volume": 100,
        "datetime": "2022-06-08 13:32:00"
    },
    {
        "open": 1.97,
        "high": 1.97,
        "low": 1.97,
        "close": 1.97,
        "volume": 999,
        "datetime": "2022-06-08 13:41:00"
    },
    {
        "open": 2.06,
        "high": 2.07,
        "low": 2.06,
        "close": 2.07,
        "volume": 200,
        "datetime": "2022-06-08 15:11:00"
    },
    {
        "open": 2.065,
        "high": 2.07,
        "low": 2.06,
        "close": 2.07,
        "volume": 500,
        "datetime": "2022-06-08 15:18:00"
    },
    {
        "open": 2.0602,
        "high": 2.0602,
        "low": 2.0602,
        "close": 2.0602,
        "volume": 1000,
        "datetime": "2022-06-08 15:30:00"
    },
    {
        "open": 2.005,
        "high": 2.005,
        "low": 2.005,
        "close": 2.005,
        "volume": 480,
        "datetime": "2022-06-08 15:35:00"
    },
    {
        "open": 2.06,
        "high": 2.1,
        "low": 2.06,
        "close": 2.1,
        "volume": 5384,
        "datetime": "2022-06-08 15:37:00"
    },
    {
        "open": 2.06,
        "high": 2.0601,
        "low": 2.06,
        "close": 2.0601,
        "volume": 490,
        "datetime": "2022-06-08 16:34:00"
    },
    {
        "open": 2.08,
        "high": 2.08,
        "low": 2.08,
        "close": 2.08,
        "volume": 100,
        "datetime": "2022-06-08 17:38:00"
    },
    {
        "open": 2.075,
        "high": 2.09,
        "low": 2.075,
        "close": 2.09,
        "volume": 1471,
        "datetime": "2022-06-08 18:25:00"
    },
    {
        "open": 2.1,
        "high": 2.1,
        "low": 2.1,
        "close": 2.1,
        "volume": 100,
        "datetime": "2022-06-08 18:43:00"
    },
    {
        "open": 2.11,
        "high": 2.13,
        "low": 2.11,
        "close": 2.13,
        "volume": 2000,
        "datetime": "2022-06-08 19:14:00"
    },
    {
        "open": 2.13,
        "high": 2.13,
        "low": 2.13,
        "close": 2.13,
        "volume": 200,
        "datetime": "2022-06-08 19:15:00"
    },
    {
        "open": 2.2742,
        "high": 2.2742,
        "low": 2.2742,
        "close": 2.2742,
        "volume": 1945,
        "datetime": "2022-06-08 19:21:00"
    },
    {
        "open": 2.27,
        "high": 2.27,
        "low": 2.27,
        "close": 2.27,
        "volume": 597,
        "datetime": "2022-06-08 19:22:00"
    },
    {
        "open": 2.13,
        "high": 2.13,
        "low": 2.13,
        "close": 2.13,
        "volume": 2000,
        "datetime": "2022-06-08 19:31:00"
    },
    {
        "open": 2.235,
        "high": 2.24,
        "low": 2.22,
        "close": 2.24,
        "volume": 1523,
        "datetime": "2022-06-08 19:43:00"
    },
    {
        "open": 1.9176,
        "high": 1.9176,
        "low": 1.9176,
        "close": 1.9176,
        "volume": 203,
        "datetime": "2022-06-09 13:30:00"
    },
    {
        "open": 2.2399,
        "high": 2.2399,
        "low": 2.2399,
        "close": 2.2399,
        "volume": 240,
        "datetime": "2022-06-09 13:32:00"
    },
    {
        "open": 2.2008,
        "high": 2.2008,
        "low": 2.2008,
        "close": 2.2008,
        "volume": 500,
        "datetime": "2022-06-09 13:48:00"
    },
    {
        "open": 2.2201,
        "high": 2.2201,
        "low": 2.2,
        "close": 2.2,
        "volume": 823,
        "datetime": "2022-06-09 13:49:00"
    },
    {
        "open": 2.0911,
        "high": 2.0911,
        "low": 2.0911,
        "close": 2.0911,
        "volume": 100,
        "datetime": "2022-06-09 13:53:00"
    },
    {
        "open": 2.1762,
        "high": 2.1762,
        "low": 2.1762,
        "close": 2.1762,
        "volume": 100,
        "datetime": "2022-06-09 13:59:00"
    },
    {
        "open": 2.1832,
        "high": 2.1832,
        "low": 2.1832,
        "close": 2.1832,
        "volume": 203,
        "datetime": "2022-06-09 14:21:00"
    },
    {
        "open": 2.1999,
        "high": 2.1999,
        "low": 2.1999,
        "close": 2.1999,
        "volume": 100,
        "datetime": "2022-06-09 14:43:00"
    },
    {
        "open": 2.2,
        "high": 2.2,
        "low": 2.195,
        "close": 2.195,
        "volume": 800,
        "datetime": "2022-06-09 16:51:00"
    },
    {
        "open": 2.195,
        "high": 2.195,
        "low": 2.195,
        "close": 2.195,
        "volume": 250,
        "datetime": "2022-06-09 16:56:00"
    },
    {
        "open": 2.19,
        "high": 2.19,
        "low": 2.19,
        "close": 2.19,
        "volume": 197,
        "datetime": "2022-06-09 16:57:00"
    },
    {
        "open": 2.16,
        "high": 2.18,
        "low": 2.16,
        "close": 2.18,
        "volume": 600,
        "datetime": "2022-06-09 17:43:00"
    },
    {
        "open": 2.15,
        "high": 2.15,
        "low": 2.15,
        "close": 2.15,
        "volume": 1256,
        "datetime": "2022-06-09 17:53:00"
    },
    {
        "open": 2.08,
        "high": 2.08,
        "low": 2.08,
        "close": 2.08,
        "volume": 900,
        "datetime": "2022-06-09 18:45:00"
    },
    {
        "open": 2.03,
        "high": 2.03,
        "low": 2.03,
        "close": 2.03,
        "volume": 885,
        "datetime": "2022-06-09 19:02:00"
    },
    {
        "open": 2.0783,
        "high": 2.0783,
        "low": 2.0783,
        "close": 2.0783,
        "volume": 100,
        "datetime": "2022-06-09 19:04:00"
    },
    {
        "open": 2.13,
        "high": 2.13,
        "low": 2.13,
        "close": 2.13,
        "volume": 100,
        "datetime": "2022-06-09 19:13:00"
    },
    {
        "open": 2.14,
        "high": 2.14,
        "low": 2.13,
        "close": 2.13,
        "volume": 400,
        "datetime": "2022-06-09 19:16:00"
    },
    {
        "open": 2.0494,
        "high": 2.0494,
        "low": 2.0494,
        "close": 2.0494,
        "volume": 250,
        "datetime": "2022-06-09 19:46:00"
    },
    {
        "open": 2.13,
        "high": 2.13,
        "low": 2.13,
        "close": 2.13,
        "volume": 100,
        "datetime": "2022-06-09 19:59:00"
    },
    {
        "open": 1.93,
        "high": 1.94,
        "low": 1.93,
        "close": 1.94,
        "volume": 567,
        "datetime": "2022-06-10 11:00:00"
    },
    {
        "open": 1.89,
        "high": 1.89,
        "low": 1.89,
        "close": 1.89,
        "volume": 599,
        "datetime": "2022-06-10 13:30:00"
    },
    {
        "open": 1.88,
        "high": 1.88,
        "low": 1.88,
        "close": 1.88,
        "volume": 275,
        "datetime": "2022-06-10 13:34:00"
    },
    {
        "open": 1.9862,
        "high": 1.9862,
        "low": 1.9862,
        "close": 1.9862,
        "volume": 100,
        "datetime": "2022-06-10 13:35:00"
    },
    {
        "open": 1.98,
        "high": 1.98,
        "low": 1.98,
        "close": 1.98,
        "volume": 100,
        "datetime": "2022-06-10 13:54:00"
    },
    {
        "open": 1.99,
        "high": 1.99,
        "low": 1.99,
        "close": 1.99,
        "volume": 200,
        "datetime": "2022-06-10 14:06:00"
    },
    {
        "open": 1.95,
        "high": 1.95,
        "low": 1.95,
        "close": 1.95,
        "volume": 456,
        "datetime": "2022-06-10 14:15:00"
    },
    {
        "open": 1.94,
        "high": 1.95,
        "low": 1.94,
        "close": 1.95,
        "volume": 600,
        "datetime": "2022-06-10 14:34:00"
    },
    {
        "open": 1.9499,
        "high": 1.9499,
        "low": 1.915,
        "close": 1.915,
        "volume": 4975,
        "datetime": "2022-06-10 14:57:00"
    },
    {
        "open": 1.9484,
        "high": 1.9484,
        "low": 1.9484,
        "close": 1.9484,
        "volume": 500,
        "datetime": "2022-06-10 15:19:00"
    },
    {
        "open": 1.95,
        "high": 1.95,
        "low": 1.915,
        "close": 1.95,
        "volume": 700,
        "datetime": "2022-06-10 15:32:00"
    },
    {
        "open": 1.9402,
        "high": 1.9402,
        "low": 1.9402,
        "close": 1.9402,
        "volume": 100,
        "datetime": "2022-06-10 16:01:00"
    },
    {
        "open": 1.9498,
        "high": 1.9498,
        "low": 1.9498,
        "close": 1.9498,
        "volume": 575,
        "datetime": "2022-06-10 16:18:00"
    },
    {
        "open": 1.9499,
        "high": 1.9499,
        "low": 1.9499,
        "close": 1.9499,
        "volume": 1500,
        "datetime": "2022-06-10 16:22:00"
    },
    {
        "open": 1.95,
        "high": 1.95,
        "low": 1.95,
        "close": 1.95,
        "volume": 400,
        "datetime": "2022-06-10 16:46:00"
    },
    {
        "open": 1.903,
        "high": 1.903,
        "low": 1.903,
        "close": 1.903,
        "volume": 500,
        "datetime": "2022-06-10 16:53:00"
    },
    {
        "open": 1.9499,
        "high": 1.9499,
        "low": 1.9499,
        "close": 1.9499,
        "volume": 209,
        "datetime": "2022-06-10 17:27:00"
    },
    {
        "open": 1.948,
        "high": 1.948,
        "low": 1.948,
        "close": 1.948,
        "volume": 100,
        "datetime": "2022-06-10 17:31:00"
    },
    {
        "open": 1.95,
        "high": 1.95,
        "low": 1.95,
        "close": 1.95,
        "volume": 733,
        "datetime": "2022-06-10 17:42:00"
    },
    {
        "open": 1.95,
        "high": 1.95,
        "low": 1.95,
        "close": 1.95,
        "volume": 100,
        "datetime": "2022-06-10 17:57:00"
    },
    {
        "open": 1.955,
        "high": 1.955,
        "low": 1.955,
        "close": 1.955,
        "volume": 101,
        "datetime": "2022-06-10 19:00:00"
    },
    {
        "open": 1.9499,
        "high": 1.9499,
        "low": 1.9499,
        "close": 1.9499,
        "volume": 100,
        "datetime": "2022-06-10 19:08:00"
    },
    {
        "open": 1.9873,
        "high": 2.0,
        "low": 1.96,
        "close": 1.96,
        "volume": 918,
        "datetime": "2022-06-10 19:24:00"
    },
    {
        "open": 1.96,
        "high": 1.96,
        "low": 1.96,
        "close": 1.96,
        "volume": 100,
        "datetime": "2022-06-10 19:47:00"
    },
    {
        "open": 1.95,
        "high": 1.95,
        "low": 1.95,
        "close": 1.95,
        "volume": 200,
        "datetime": "2022-06-10 19:53:00"
    },
    {
        "open": 1.94,
        "high": 1.94,
        "low": 1.94,
        "close": 1.94,
        "volume": 100,
        "datetime": "2022-06-10 20:00:00"
    }
]