{"candles": [{"open": 9.82, "high": 9.82, "low": 9.82, "close": 9.82, "volume": 10227, "datetime": "2022-05-27 13:30:00"}, {"open": 9.82, "high": 9.82, "low": 9.82, "close": 9.82, "volume": 3308, "datetime": "2022-05-27 13:41:00"}, {"open": 9.825, "high": 9.825, "low": 9.825, "close": 9.825, "volume": 277881, "datetime": "2022-05-27 14:10:00"}, {"open": 9.825, "high": 9.825, "low": 9.825, "close": 9.825, "volume": 100, "datetime": "2022-05-27 15:13:00"}, {"open": 9.825, "high": 9.825, "low": 9.825, "close": 9.825, "volume": 500, "datetime": "2022-05-27 17:19:00"}, {"open": 9.825, "high": 9.825, "low": 9.825, "close": 9.825, "volume": 456, "datetime": "2022-05-27 17:31:00"}, {"open": 9.825, "high": 9.83, "low": 9.82, "close": 9.82, "volume": 3200, "datetime": "2022-05-27 18:06:00"}, {"open": 9.8207, "high": 9.8207, "low": 9.8207, "close": 9.8207, "volume": 575, "datetime": "2022-05-27 19:27:00"}, {"open": 9.825, "high": 9.825, "low": 9.825, "close": 9.825, "volume": 225, "datetime": "2022-05-27 19:33:00"}, {"open": 9.82, "high": 9.82, "low": 9.82, "close": 9.82, "volume": 641, "datetime": "2022-05-27 19:49:00"}, {"open": 9.82, "high": 9.82, "low": 9.82, "close": 9.82, "volume": 1407, "datetime": "2022-05-31 13:30:00"}, {"open": 9.82, "high": 9.82, "low": 9.82, "close": 9.82, "volume": 100, "datetime": "2022-05-31 13:49:00"}, {"open": 9.82, "high": 9.8202, "low": 9.82, "close": 9.8202, "volume": 200, "datetime": "2022-05-31 14:23:00"}, {"open": 9.82, "high": 9.82, "low": 9.82, "close": 9.82, "volume": 2100, "datetime": "2022-05-31 14:35:00"}, {"open": 9.8242, "high": 9.8242, "low": 9.82, "close": 9.82, "volume": 400, "datetime": "2022-05-31 15:45:00"}, {"open": 9.821, "high": 9.821, "low": 9.821, "close": 9.821, "volume": 682, "datetime": "2022-05-31 16:43:00"}, {"open": 9.82, "high": 9.82, "low": 9.82, "close": 9.82, "volume": 179, "datetime": "2022-05-31 18:07:00"}, {"open": 9.82, "high": 9.82, "low": 9.82, "close": 9.82, "volume": 100, "datetime": "2022-05-31 18:25:00"}, {"open": 9.82, "high": 9.82, "low": 9.82, "close": 9.82, "volume": 102, "datetime": "2022-05-31 18:45:00"}, {"open": 9.82, "high": 9.82, "low": 9.82, "close": 9.82, "volume": 100, "datetime": "2022-05-31 18:49:00"}, {"open": 9.8209, "high": 9.8209, "low": 9.8209, "close": 9.8209, "volume": 999, "datetime": "2022-05-31 18:54:00"}, {"open": 9.82, "high": 9.82, "low": 9.82, "close": 9.82, "volume": 100, "datetime": "2022-05-31 19:12:00"}, {"open": 9.82, "high": 9.8201, "low": 9.82, "close": 9.8201, "volume": 600, "datetime": "2022-05-31 19:22:00"}, {"open": 9.82, "high": 9.82, "low": 9.82, "close": 9.82, "volume": 100, "datetime": "2022-05-31 19:24:00"}, {"open": 9.82, "high": 9.82, "low": 9.82, "close": 9.82, "volume": 100, "datetime": "2022-05-31 19:36:00"}, {"open": 9.82, "high": 9.82, "low": 9.82, "close": 9.82, "volume": 200, "datetime": "2022-05-31 19:48:00"}, {"open": 9.82, "high": 9.82, "low": 9.82, "close": 9.82, "volume": 200, "datetime": "2022-05-31 19:59:00"}, {"open": 9.83, "high": 9.83, "low": 9.83, "close": 9.83, "volume": 4065, "datetime": "2022-05-31 20:00:00"}, {"open": 9.82, "high": 9.82, "low": 9.82, "close": 9.82, "volume": 320, "datetime": "2022-06-01 13:30:00"}, {"open": 9.8202, "high": 9.8202, "low": 9.8202, "close": 9.8202, "volume": 200, "datetime": "2022-06-01 13:44:00"}, {"open": 9.82, "high": 9.82, "low": 9.82, "close": 9.82, "volume": 105, "datetime": "2022-06-01 14:39:00"}, {"open": 9.82, "high": 9.82, "low": 9.82, "close": 9.82, "volume": 325, "datetime": "2022-06-01 15:15:00"}, {"open": 9.82, "high": 9.82, "low": 9.82, "close": 9.82, "volume": 4607, "datetime": "2022-06-01 15:24:00"}, {"open": 9.8201, "high": 9.8201, "low": 9.8201, "close": 9.8201, "volume": 100, "datetime": "2022-06-01 16:56:00"}, {"open": 9.8201, "high": 9.8201, "low": 9.8201, "close": 9.8201, "volume": 100, "datetime": "2022-06-01 18:18:00"}, {"open": 9.82, "high": 9.8233, "low": 9.82, "close": 9.82, "volume": 2676, "datetime": "2022-06-01 18:35:00"}, {"open": 9.8201, "high": 9.8201, "low": 9.8201, "close": 9.8201, "volume": 179, "datetime": "2022-06-01 19:00:00"}, {"open": 9.825, "high": 9.825, "low": 9.82, "close": 9.82, "volume": 600, "datetime": "2022-06-01 19:17:00"}, {"open": 9.825, "high": 9.83, "low": 9.825, "close": 9.83, "volume": 4652, "datetime": "2022-06-01 19:18:00"}, {"open": 9.83, "high": 9.83, "low": 9.83, "close": 9.83, "volume": 100, "datetime": "2022-06-01 19:45:00"}, {"open": 9.83, "high": 9.83, "low": 9.83, "close": 9.83, "volume": 276, "datetime": "2022-06-02 13:31:00"}, {"open": 9.8257, "high": 9.8257, "low": 9.8257, "close": 9.8257, "volume": 1650, "datetime": "2022-06-02 13:36:00"}, {"open": 9.8213, "high": 9.8213, "low": 9.8213, "close": 9.8213, "volume": 300, "datetime": "2022-06-02 13:54:00"}, {"open": 9.8201, "high": 9.8201, "low": 9.8201, "close": 9.8201, "volume": 690, "datetime": "2022-06-02 14:14:00"}, {"open": 9.825, "high": 9.825, "low": 9.825, "close": 9.825, "volume": 240, "datetime": "2022-06-02 17:47:00"}, {"open": 9.82, "high": 9.82, "low": 9.82, "close": 9.82, "volume": 480, "datetime": "2022-06-02 18:18:00"}, {"open": 9.83, "high": 9.83, "low": 9.83, "close": 9.83, "volume": 2416, "datetime": "2022-06-02 18:29:00"}, {"open": 9.83, "high": 9.83, "low": 9.83, "close": 9.83, "volume": 500, "datetime": "2022-06-02 18:32:00"}, {"open": 9.83, "high": 9.83, "low": 9.83, "close": 9.83, "volume": 1769, "datetime": "2022-06-02 18:39:00"}, {"open": 9.8236, "high": 9.8236, "low": 9.82, "close": 9.82, "volume": 910, "datetime": "2022-06-02 19:36:00"}, {"open": 9.821, "high": 9.821, "low": 9.821, "close": 9.821, "volume": 500, "datetime": "2022-06-02 19:39:00"}, {"open": 9.8201, "high": 9.8201, "low": 9.82, "close": 9.82, "volume": 1770, "datetime": "2022-06-02 19:50:00"}, {"open": 9.8201, "high": 9.8201, "low": 9.82, "close": 9.82, "volume": 360, "datetime": "2022-06-02 19:52:00"}, {"open": 9.82, "high": 9.82, "low": 9.82, "close": 9.82, "volume": 1003653, "datetime": "2022-06-02 20:07:00"}, {"open": 9.81, "high": 9.82, "low": 9.81, "close": 9.82, "volume": 324, "datetime": "2022-06-03 13:25:00"}, {"open": 9.83, "high": 9.83, "low": 9.83, "close": 9.83, "volume": 1768, "datetime": "2022-06-03 13:30:00"}, {"open": 9.84, "high": 9.84, "low": 9.84, "close": 9.84, "volume": 1100, "datetime": "2022-06-03 13:50:00"}, {"open": 9.83, "high": 9.83, "low": 9.83, "close": 9.83, "volume": 100, "datetime": "2022-06-03 14:42:00"}, {"open": 9.83, "high": 9.8301, "low": 9.83, "close": 9.8301, "volume": 600, "datetime": "2022-06-03 15:34:00"}, {"open": 9.83, "high": 9.83, "low": 9.82, "close": 9.82, "volume": 8281, "datetime": "2022-06-03 16:21:00"}, {"open": 9.825, "high": 9.83, "low": 9.825, "close": 9.8294, "volume": 8119, "datetime": "2022-06-03 16:25:00"}, {"open": 9.83, "high": 9.8301, "low": 9.83, "close": 9.83, "volume": 5801, "datetime": "2022-06-03 16:28:00"}, {"open": 9.83, "high": 9.8301, "low": 9.83, "close": 9.8301, "volume": 200, "datetime": "2022-06-03 16:55:00"}, {"open": 9.83, "high": 9.83, "low": 9.83, "close": 9.83, "volume": 240, "datetime": "2022-06-03 17:23:00"}, {"open": 9.83, "high": 9.83, "low": 9.83, "close": 9.83, "volume": 323, "datetime": "2022-06-03 19:35:00"}, {"open": 9.83, "high": 9.83, "low": 9.83, "close": 9.83, "volume": 2500, "datetime": "2022-06-03 19:50:00"}, {"open": 9.835, "high": 9.835, "low": 9.835, "close": 9.835, "volume": 143, "datetime": "2022-06-03 20:00:00"}, {"open": 9.85, "high": 9.85, "low": 9.85, "close": 9.85, "volume": 610, "datetime": "2022-06-06 13:24:00"}, {"open": 9.82, "high": 9.82, "low": 9.82, "close": 9.82, "volume": 509, "datetime": "2022-06-06 13:30:00"}, {"open": 9.8101, "high": 9.8101, "low": 9.8101, "close": 9.8101, "volume": 333, "datetime": "2022-06-06 13:35:00"}, {"open": 9.81, "high": 9.81, "low": 9.81, "close": 9.81, "volume": 141, "datetime": "2022-06-06 13:36:00"}, {"open": 9.8207, "high": 9.8207, "low": 9.8207, "close": 9.8207, "volume": 450, "datetime": "2022-06-06 13:52:00"}, {"open": 9.82, "high": 9.82, "low": 9.82, "close": 9.82, "volume": 1000, "datetime": "2022-06-06 13:56:00"}, {"open": 9.82, "high": 9.82, "low": 9.82, "close": 9.82, "volume": 138, "datetime": "2022-06-06 15:33:00"}, {"open": 9.82, "high": 9.82, "low": 9.82, "close": 9.82, "volume": 198, "datetime": "2022-06-06 16:32:00"}, {"open": 9.82, "high": 9.82, "low": 9.82, "close": 9.82, "volume": 300, "datetime": "2022-06-06 16:57:00"}, {"open": 9.83, "high": 9.83, "low": 9.82, "close": 9.82, "volume": 1199, "datetime": "2022-06-06 19:32:00"}, {"open": 9.83, "high": 9.83, "low": 9.83, "close": 9.83, "volume": 700, "datetime": "2022-06-06 19:34:00"}, {"open": 9.84, "high": 9.84, "low": 9.84, "close": 9.84, "volume": 363, "datetime": "2022-06-06 19:43:00"}, {"open": 9.83, "high": 9.83, "low": 9.83, "close": 9.83, "volume": 106, "datetime": "2022-06-07 13:30:00"}, {"open": 9.84, "high": 9.84, "low": 9.84, "close": 9.84, "volume": 450, "datetime": "2022-06-07 14:31:00"}, {"open": 9.8356, "high": 9.8356, "low": 9.8356, "close": 9.8356, "volume": 600, "datetime": "2022-06-07 15:13:00"}, {"open": 9.8301, "high": 9.8301, "low": 9.83, "close": 9.83, "volume": 400, "datetime": "2022-06-07 16:15:00"}, {"open": 9.83, "high": 9.83, "low": 9.83, "close": 9.83, "volume": 305, "datetime": "2022-06-07 17:03:00"}, {"open": 9.8301, "high": 9.8301, "low": 9.83, "close": 9.83, "volume": 446, "datetime": "2022-06-07 17:21:00"}, {"open": 9.83, "high": 9.83, "low": 9.83, "close": 9.83, "volume": 300, "datetime": "2022-06-07 18:24:00"}, {"open": 9.84, "high": 9.84, "low": 9.835, "close": 9.84, "volume": 1231, "datetime": "2022-06-07 18:43:00"}, {"open": 9.84, "high": 9.8441, "low": 9.84, "close": 9.8441, "volume": 200, "datetime": "2022-06-07 18:52:00"}, {"open": 9.84, "high": 9.8401, "low": 9.84, "close": 9.8401, "volume": 400, "datetime": "2022-06-07 18:55:00"}, {"open": 9.84, "high": 9.8401, "low": 9.84, "close": 9.8401, "volume": 900, "datetime": "2022-06-07 19:11:00"}, {"open": 9.84, "high": 9.8401, "low": 9.84, "close": 9.8401, "volume": 600, "datetime": "2022-06-07 19:25:00"}, {"open": 9.844, "high": 9.844, "low": 9.844, "close": 9.844, "volume": 100, "datetime": "2022-06-08 14:25:00"}, {"open": 9.83, "high": 9.83, "low": 9.83, "close": 9.83, "volume": 492, "datetime": "2022-06-08 17:35:00"}, {"open": 9.84, "high": 9.84, "low": 9.84, "close": 9.84, "volume": 100, "datetime": "2022-06-09 13:31:00"}, {"open": 9.84, "high": 9.84, "low": 9.84, "close": 9.84, "volume": 100, "datetime": "2022-06-09 13:32:00"}, {"open": 9.83, "high": 9.83, "low": 9.83, "close": 9.83, "volume": 250, "datetime": "2022-06-09 13:53:00"}, {"open": 9.84, "high": 9.84, "low": 9.84, "close": 9.84, "volume": 450, "datetime": "2022-06-09 14:01:00"}, {"open": 9.84, "high": 9.84, "low": 9.84, "close": 9.84, "volume": 493, "datetime": "2022-06-09 17:13:00"}, {"open": 9.835, "high": 9.835, "low": 9.83, "close": 9.83, "volume": 9434, "datetime": "2022-06-09 17:38:00"}, {"open": 9.83, "high": 9.8332, "low": 9.83, "close": 9.8332, "volume": 2400, "datetime": "2022-06-09 19:28:00"}, {"open": 9.87, "high": 9.87, "low": 9.87, "close": 9.87, "volume": 500, "datetime": "2022-06-10 13:07:00"}, {"open": 9.85, "high": 9.85, "low": 9.85, "close": 9.85, "volume": 1809, "datetime": "2022-06-10 13:30:00"}, {"open": 9.85, "high": 9.855, "low": 9.85, "close": 9.855, "volume": 2903, "datetime": "2022-06-10 13:34:00"}, {"open": 9.85, "high": 9.85, "low": 9.85, "close": 9.85, "volume": 2000, "datetime": "2022-06-10 13:45:00"}, {"open": 9.85, "high": 9.85, "low": 9.85, "close": 9.85, "volume": 330, "datetime": "2022-06-10 14:03:00"}, {"open": 9.8501, "high": 9.8501, "low": 9.8501, "close": 9.8501, "volume": 150, "datetime": "2022-06-10 15:25:00"}, {"open": 9.85, "high": 9.8501, "low": 9.85, "close": 9.8501, "volume": 262, "datetime": "2022-06-10 16:12:00"}, {"open": 9.85, "high": 9.8501, "low": 9.85, "close": 9.8501, "volume": 450, "datetime": "2022-06-10 17:13:00"}, {"open": 9.8401, "high": 9.8401, "low": 9.8401, "close": 9.8401, "volume": 100, "datetime": "2022-06-10 17:43:00"}, {"open": 9.84, "high": 9.8433, "low": 9.84, "close": 9.8433, "volume": 2208, "datetime": "2022-06-10 18:06:00"}, {"open": 9.84, "high": 9.8402, "low": 9.84, "close": 9.8402, "volume": 600, "datetime": "2022-06-10 18:50:00"}, {"open": 9.84, "high": 9.84, "low": 9.84, "close": 9.84, "volume": 400, "datetime": "2022-06-10 19:23:00"}, {"open": 9.8403, "high": 9.8403, "low": 9.8403, "close": 9.8403, "volume": 150, "datetime": "2022-06-10 19:28:00"}, {"open": 9.84, "high": 9.8422, "low": 9.84, "close": 9.8422, "volume": 300, "datetime": "2022-06-10 19:47:00"}], "symbol": "PRSR", "empty": false}