{"candles": [{"open": 0.88, "high": 0.88, "low": 0.8751, "close": 0.8751, "volume": 10691, "datetime": "2022-05-27 13:30:00"}, {"open": 0.898, "high": 0.898, "low": 0.898, "close": 0.898, "volume": 3000, "datetime": "2022-05-27 13:31:00"}, {"open": 0.875, "high": 0.875, "low": 0.875, "close": 0.875, "volume": 1331, "datetime": "2022-05-27 13:39:00"}, {"open": 0.8701, "high": 0.8701, "low": 0.8701, "close": 0.8701, "volume": 413, "datetime": "2022-05-27 13:53:00"}, {"open": 0.884951, "high": 0.884951, "low": 0.884951, "close": 0.884951, "volume": 2717, "datetime": "2022-05-27 13:55:00"}, {"open": 0.899, "high": 0.899, "low": 0.899, "close": 0.899, "volume": 280, "datetime": "2022-05-27 14:05:00"}, {"open": 0.8999, "high": 0.8999, "low": 0.89, "close": 0.89, "volume": 1275, "datetime": "2022-05-27 14:37:00"}, {"open": 0.899999, "high": 0.899999, "low": 0.899999, "close": 0.899999, "volume": 500, "datetime": "2022-05-27 15:05:00"}, {"open": 0.8905, "high": 0.8905, "low": 0.8905, "close": 0.8905, "volume": 420, "datetime": "2022-05-27 15:42:00"}, {"open": 0.8891, "high": 0.8891, "low": 0.8891, "close": 0.8891, "volume": 1200, "datetime": "2022-05-27 15:53:00"}, {"open": 0.896, "high": 0.896, "low": 0.896, "close": 0.896, "volume": 1000, "datetime": "2022-05-27 17:11:00"}, {"open": 0.8804, "high": 0.8804, "low": 0.8804, "close": 0.8804, "volume": 100, "datetime": "2022-05-27 17:12:00"}, {"open": 0.8959, "high": 0.8959, "low": 0.8959, "close": 0.8959, "volume": 100, "datetime": "2022-05-27 17:50:00"}, {"open": 0.896, "high": 0.896, "low": 0.896, "close": 0.896, "volume": 500, "datetime": "2022-05-27 18:17:00"}, {"open": 0.8931, "high": 0.8931, "low": 0.8931, "close": 0.8931, "volume": 100, "datetime": "2022-05-27 18:23:00"}, {"open": 0.896, "high": 0.896, "low": 0.896, "close": 0.896, "volume": 100, "datetime": "2022-05-27 18:25:00"}, {"open": 0.8999, "high": 0.9, "low": 0.8991, "close": 0.8999, "volume": 10933, "datetime": "2022-05-27 18:26:00"}, {"open": 0.9, "high": 0.9018, "low": 0.9, "close": 0.9018, "volume": 8828, "datetime": "2022-05-27 18:34:00"}, {"open": 0.9097, "high": 0.9097, "low": 0.8869, "close": 0.8952, "volume": 10600, "datetime": "2022-05-27 18:39:00"}, {"open": 0.91, "high": 0.91, "low": 0.91, "close": 0.91, "volume": 338, "datetime": "2022-05-27 18:47:00"}, {"open": 0.9093, "high": 0.9093, "low": 0.8877, "close": 0.8877, "volume": 7000, "datetime": "2022-05-27 18:49:00"}, {"open": 0.88, "high": 0.88, "low": 0.88, "close": 0.88, "volume": 1000, "datetime": "2022-05-27 19:31:00"}, {"open": 0.8906, "high": 0.8906, "low": 0.8906, "close": 0.8906, "volume": 300, "datetime": "2022-05-27 20:00:00"}, {"open": 0.8842, "high": 0.8842, "low": 0.8842, "close": 0.8842, "volume": 246, "datetime": "2022-05-31 13:30:00"}, {"open": 0.89, "high": 0.89, "low": 0.89, "close": 0.89, "volume": 10901, "datetime": "2022-05-31 13:38:00"}, {"open": 0.8939, "high": 0.8939, "low": 0.8939, "close": 0.8939, "volume": 500, "datetime": "2022-05-31 15:10:00"}, {"open": 0.894, "high": 0.894, "low": 0.894, "close": 0.894, "volume": 2000, "datetime": "2022-05-31 15:11:00"}, {"open": 0.8939, "high": 0.8939, "low": 0.8939, "close": 0.8939, "volume": 4000, "datetime": "2022-05-31 15:17:00"}, {"open": 0.894, "high": 0.894, "low": 0.894, "close": 0.894, "volume": 2000, "datetime": "2022-05-31 15:30:00"}, {"open": 0.894, "high": 0.894, "low": 0.894, "close": 0.894, "volume": 100, "datetime": "2022-05-31 15:58:00"}, {"open": 0.894, "high": 0.894, "low": 0.894, "close": 0.894, "volume": 935, "datetime": "2022-05-31 16:00:00"}, {"open": 0.8939, "high": 0.8939, "low": 0.8939, "close": 0.8939, "volume": 100, "datetime": "2022-05-31 16:05:00"}, {"open": 0.896, "high": 0.896, "low": 0.896, "close": 0.896, "volume": 101, "datetime": "2022-05-31 16:11:00"}, {"open": 0.896, "high": 0.896, "low": 0.896, "close": 0.896, "volume": 500, "datetime": "2022-05-31 16:17:00"}, {"open": 0.896, "high": 0.896, "low": 0.896, "close": 0.896, "volume": 932, "datetime": "2022-05-31 16:33:00"}, {"open": 0.896, "high": 0.896, "low": 0.896, "close": 0.896, "volume": 2592, "datetime": "2022-05-31 16:34:00"}, {"open": 0.89, "high": 0.896, "low": 0.89, "close": 0.896, "volume": 200, "datetime": "2022-05-31 16:36:00"}, {"open": 0.8995, "high": 0.9002, "low": 0.8966, "close": 0.9001, "volume": 3600, "datetime": "2022-05-31 16:37:00"}, {"open": 0.9002, "high": 0.9004, "low": 0.8984, "close": 0.8998, "volume": 1500, "datetime": "2022-05-31 16:38:00"}, {"open": 0.9004, "high": 0.9004, "low": 0.9004, "close": 0.9004, "volume": 300, "datetime": "2022-05-31 16:41:00"}, {"open": 0.9114, "high": 0.9114, "low": 0.9114, "close": 0.9114, "volume": 100, "datetime": "2022-05-31 17:03:00"}, {"open": 0.9122, "high": 0.9122, "low": 0.89, "close": 0.89, "volume": 2174, "datetime": "2022-05-31 17:11:00"}, {"open": 0.8901, "high": 0.8901, "low": 0.8901, "close": 0.8901, "volume": 2000, "datetime": "2022-05-31 17:16:00"}, {"open": 0.905, "high": 0.905, "low": 0.905, "close": 0.905, "volume": 100, "datetime": "2022-05-31 17:58:00"}, {"open": 0.905, "high": 0.905, "low": 0.905, "close": 0.905, "volume": 100, "datetime": "2022-05-31 18:05:00"}, {"open": 0.905, "high": 0.905, "low": 0.905, "close": 0.905, "volume": 496, "datetime": "2022-05-31 18:07:00"}, {"open": 0.9001, "high": 0.9001, "low": 0.9001, "close": 0.9001, "volume": 400, "datetime": "2022-05-31 18:12:00"}, {"open": 0.9045, "high": 0.9048, "low": 0.9045, "close": 0.9045, "volume": 1190, "datetime": "2022-05-31 18:30:00"}, {"open": 0.9045, "high": 0.9045, "low": 0.9045, "close": 0.9045, "volume": 1000, "datetime": "2022-05-31 18:31:00"}, {"open": 0.901001, "high": 0.905, "low": 0.9009, "close": 0.9009, "volume": 3000, "datetime": "2022-05-31 18:36:00"}, {"open": 0.90295, "high": 0.90295, "low": 0.90295, "close": 0.90295, "volume": 100, "datetime": "2022-05-31 19:12:00"}, {"open": 0.9001, "high": 0.905, "low": 0.9, "close": 0.905, "volume": 25500, "datetime": "2022-05-31 19:27:00"}, {"open": 0.9038, "high": 0.9038, "low": 0.9026, "close": 0.9026, "volume": 599, "datetime": "2022-05-31 19:28:00"}, {"open": 0.9034, "high": 0.9034, "low": 0.9034, "close": 0.9034, "volume": 300, "datetime": "2022-05-31 19:36:00"}, {"open": 0.9027, "high": 0.9027, "low": 0.9027, "close": 0.9027, "volume": 100, "datetime": "2022-05-31 19:37:00"}, {"open": 0.9039, "high": 0.9039, "low": 0.9027, "close": 0.9027, "volume": 300, "datetime": "2022-05-31 19:42:00"}, {"open": 0.9027, "high": 0.9027, "low": 0.9027, "close": 0.9027, "volume": 100, "datetime": "2022-05-31 19:43:00"}, {"open": 0.9027, "high": 0.9027, "low": 0.9027, "close": 0.9027, "volume": 200, "datetime": "2022-05-31 19:44:00"}, {"open": 0.9027, "high": 0.9027, "low": 0.9027, "close": 0.9027, "volume": 400, "datetime": "2022-05-31 19:47:00"}, {"open": 0.8981, "high": 0.8981, "low": 0.8981, "close": 0.8981, "volume": 300, "datetime": "2022-05-31 19:53:00"}, {"open": 0.8981, "high": 0.8981, "low": 0.8981, "close": 0.8981, "volume": 300, "datetime": "2022-05-31 19:54:00"}, {"open": 0.8981, "high": 0.8981, "low": 0.8981, "close": 0.8981, "volume": 100, "datetime": "2022-05-31 19:57:00"}, {"open": 0.9021, "high": 0.9021, "low": 0.9021, "close": 0.9021, "volume": 283, "datetime": "2022-05-31 20:00:00"}, {"open": 0.913, "high": 0.913, "low": 0.913, "close": 0.913, "volume": 212, "datetime": "2022-06-01 13:30:00"}, {"open": 0.906499, "high": 0.906499, "low": 0.906499, "close": 0.906499, "volume": 1000, "datetime": "2022-06-01 13:34:00"}, {"open": 0.912999, "high": 0.912999, "low": 0.912999, "close": 0.912999, "volume": 500, "datetime": "2022-06-01 13:46:00"}, {"open": 0.91, "high": 0.91, "low": 0.91, "close": 0.91, "volume": 100, "datetime": "2022-06-01 13:51:00"}, {"open": 0.9129, "high": 0.9129, "low": 0.9129, "close": 0.9129, "volume": 100, "datetime": "2022-06-01 14:10:00"}, {"open": 0.9115, "high": 0.9115, "low": 0.9115, "close": 0.9115, "volume": 100, "datetime": "2022-06-01 14:14:00"}, {"open": 0.9101, "high": 0.9101, "low": 0.9, "close": 0.9, "volume": 818, "datetime": "2022-06-01 14:42:00"}, {"open": 0.895001, "high": 0.895001, "low": 0.895001, "close": 0.895001, "volume": 100, "datetime": "2022-06-01 14:43:00"}, {"open": 0.9, "high": 0.9, "low": 0.9, "close": 0.9, "volume": 500, "datetime": "2022-06-01 15:31:00"}, {"open": 0.8901, "high": 0.8901, "low": 0.8901, "close": 0.8901, "volume": 1000, "datetime": "2022-06-01 15:35:00"}, {"open": 0.8901, "high": 0.8901, "low": 0.8901, "close": 0.8901, "volume": 500, "datetime": "2022-06-01 17:54:00"}, {"open": 0.8989, "high": 0.8989, "low": 0.89, "close": 0.89, "volume": 617, "datetime": "2022-06-01 18:07:00"}, {"open": 0.8944, "high": 0.8944, "low": 0.8944, "close": 0.8944, "volume": 200, "datetime": "2022-06-01 18:17:00"}, {"open": 0.8988, "high": 0.8988, "low": 0.8988, "close": 0.8988, "volume": 200, "datetime": "2022-06-01 18:23:00"}, {"open": 0.8944, "high": 0.8944, "low": 0.8944, "close": 0.8944, "volume": 100, "datetime": "2022-06-01 18:31:00"}, {"open": 0.89435, "high": 0.89435, "low": 0.89435, "close": 0.89435, "volume": 100, "datetime": "2022-06-01 18:36:00"}, {"open": 0.8987, "high": 0.8987, "low": 0.8987, "close": 0.8987, "volume": 200, "datetime": "2022-06-01 18:43:00"}, {"open": 0.8901, "high": 0.8901, "low": 0.8901, "close": 0.8901, "volume": 392, "datetime": "2022-06-01 19:00:00"}, {"open": 0.8943, "high": 0.8943, "low": 0.8943, "close": 0.8943, "volume": 150, "datetime": "2022-06-01 19:06:00"}, {"open": 0.89, "high": 0.89, "low": 0.89, "close": 0.89, "volume": 100, "datetime": "2022-06-01 19:23:00"}, {"open": 0.8986, "high": 0.8986, "low": 0.8986, "close": 0.8986, "volume": 222, "datetime": "2022-06-01 19:48:00"}, {"open": 0.8944, "high": 0.8986, "low": 0.8944, "close": 0.8986, "volume": 266, "datetime": "2022-06-01 19:49:00"}, {"open": 0.8987, "high": 0.8987, "low": 0.8987, "close": 0.8987, "volume": 200, "datetime": "2022-06-01 19:52:00"}, {"open": 0.8987, "high": 0.8987, "low": 0.8987, "close": 0.8987, "volume": 1000, "datetime": "2022-06-01 19:53:00"}, {"open": 0.8987, "high": 0.8987, "low": 0.8987, "close": 0.8987, "volume": 200, "datetime": "2022-06-01 19:55:00"}, {"open": 0.9, "high": 0.9, "low": 0.9, "close": 0.9, "volume": 217, "datetime": "2022-06-01 22:07:00"}, {"open": 0.9, "high": 0.9, "low": 0.9, "close": 0.9, "volume": 100, "datetime": "2022-06-02 13:47:00"}, {"open": 0.890049, "high": 0.890049, "low": 0.890049, "close": 0.890049, "volume": 100, "datetime": "2022-06-02 13:49:00"}, {"open": 0.9, "high": 0.9, "low": 0.9, "close": 0.9, "volume": 100, "datetime": "2022-06-02 14:51:00"}, {"open": 0.8802, "high": 0.8802, "low": 0.8802, "close": 0.8802, "volume": 5158, "datetime": "2022-06-02 15:00:00"}, {"open": 0.8802, "high": 0.8802, "low": 0.88, "close": 0.88, "volume": 10210, "datetime": "2022-06-02 15:01:00"}, {"open": 0.89, "high": 0.89, "low": 0.89, "close": 0.89, "volume": 1600, "datetime": "2022-06-02 15:10:00"}, {"open": 0.9, "high": 0.9, "low": 0.88, "close": 0.88, "volume": 900, "datetime": "2022-06-02 15:27:00"}, {"open": 0.9, "high": 0.9, "low": 0.9, "close": 0.9, "volume": 100, "datetime": "2022-06-02 15:28:00"}, {"open": 0.899899, "high": 0.899899, "low": 0.889999, "close": 0.889999, "volume": 10000, "datetime": "2022-06-02 15:44:00"}, {"open": 0.899899, "high": 0.9, "low": 0.899899, "close": 0.9, "volume": 1100, "datetime": "2022-06-02 15:45:00"}, {"open": 0.8901, "high": 0.8901, "low": 0.8901, "close": 0.8901, "volume": 500, "datetime": "2022-06-02 15:47:00"}, {"open": 0.9, "high": 0.9, "low": 0.9, "close": 0.9, "volume": 100, "datetime": "2022-06-02 15:51:00"}, {"open": 0.9, "high": 0.9, "low": 0.8902, "close": 0.9, "volume": 700, "datetime": "2022-06-02 15:55:00"}, {"open": 0.9, "high": 0.9, "low": 0.8903, "close": 0.9, "volume": 10100, "datetime": "2022-06-02 16:03:00"}, {"open": 0.9, "high": 0.9, "low": 0.9, "close": 0.9, "volume": 1300, "datetime": "2022-06-02 16:10:00"}, {"open": 0.9, "high": 0.9, "low": 0.9, "close": 0.9, "volume": 300, "datetime": "2022-06-02 16:11:00"}, {"open": 0.9, "high": 0.9, "low": 0.8935, "close": 0.9, "volume": 1700, "datetime": "2022-06-02 16:12:00"}, {"open": 0.912899, "high": 0.912899, "low": 0.912899, "close": 0.912899, "volume": 5000, "datetime": "2022-06-02 16:13:00"}, {"open": 0.912899, "high": 0.912899, "low": 0.912899, "close": 0.912899, "volume": 100, "datetime": "2022-06-02 16:14:00"}, {"open": 0.912899, "high": 0.912899, "low": 0.912899, "close": 0.912899, "volume": 100, "datetime": "2022-06-02 16:15:00"}, {"open": 0.9065, "high": 0.9065, "low": 0.9065, "close": 0.9065, "volume": 1000, "datetime": "2022-06-02 16:27:00"}, {"open": 0.913, "high": 0.913, "low": 0.913, "close": 0.913, "volume": 3000, "datetime": "2022-06-02 16:34:00"}, {"open": 0.913, "high": 0.913, "low": 0.913, "close": 0.913, "volume": 500, "datetime": "2022-06-02 16:40:00"}, {"open": 0.912899, "high": 0.912899, "low": 0.912899, "close": 0.912899, "volume": 500, "datetime": "2022-06-02 16:41:00"}, {"open": 0.91, "high": 0.913, "low": 0.91, "close": 0.9119, "volume": 1183, "datetime": "2022-06-02 16:44:00"}, {"open": 0.930699, "high": 0.930699, "low": 0.930699, "close": 0.930699, "volume": 100, "datetime": "2022-06-02 16:45:00"}, {"open": 0.9276, "high": 0.9276, "low": 0.9276, "close": 0.9276, "volume": 100, "datetime": "2022-06-02 17:01:00"}, {"open": 0.9295, "high": 0.9295, "low": 0.9295, "close": 0.9295, "volume": 100, "datetime": "2022-06-02 17:02:00"}, {"open": 0.9299, "high": 0.93, "low": 0.9299, "close": 0.9299, "volume": 2500, "datetime": "2022-06-02 17:06:00"}, {"open": 0.9299, "high": 0.9299, "low": 0.9299, "close": 0.9299, "volume": 1500, "datetime": "2022-06-02 17:09:00"}, {"open": 0.9299, "high": 0.9299, "low": 0.9299, "close": 0.9299, "volume": 300, "datetime": "2022-06-02 17:21:00"}, {"open": 0.93, "high": 0.9301, "low": 0.93, "close": 0.9301, "volume": 4776, "datetime": "2022-06-02 17:36:00"}, {"open": 0.94, "high": 0.94, "low": 0.94, "close": 0.94, "volume": 100, "datetime": "2022-06-02 17:39:00"}, {"open": 0.9399, "high": 0.9399, "low": 0.9399, "close": 0.9399, "volume": 1000, "datetime": "2022-06-02 17:40:00"}, {"open": 0.9399, "high": 0.939943, "low": 0.9399, "close": 0.939943, "volume": 900, "datetime": "2022-06-02 17:41:00"}, {"open": 0.9302, "high": 0.9351, "low": 0.9302, "close": 0.9351, "volume": 11600, "datetime": "2022-06-02 17:49:00"}, {"open": 0.939999, "high": 0.94, "low": 0.9376, "close": 0.9399, "volume": 604, "datetime": "2022-06-02 18:05:00"}, {"open": 0.9401, "high": 0.9401, "low": 0.9401, "close": 0.9401, "volume": 1900, "datetime": "2022-06-02 18:07:00"}, {"open": 0.9445, "high": 0.9445, "low": 0.9445, "close": 0.9445, "volume": 100, "datetime": "2022-06-02 18:11:00"}, {"open": 0.943099, "high": 0.943099, "low": 0.943099, "close": 0.943099, "volume": 1000, "datetime": "2022-06-02 18:53:00"}, {"open": 0.9401, "high": 0.9401, "low": 0.9401, "close": 0.9401, "volume": 1100, "datetime": "2022-06-02 18:54:00"}, {"open": 0.9401, "high": 0.9401, "low": 0.9401, "close": 0.9401, "volume": 1000, "datetime": "2022-06-02 18:59:00"}, {"open": 0.945799, "high": 0.945799, "low": 0.9431, "close": 0.9431, "volume": 5000, "datetime": "2022-06-02 19:18:00"}, {"open": 0.9446, "high": 0.9446, "low": 0.9446, "close": 0.9446, "volume": 100, "datetime": "2022-06-02 19:19:00"}, {"open": 0.9459, "high": 0.949, "low": 0.9458, "close": 0.949, "volume": 5483, "datetime": "2022-06-02 19:22:00"}, {"open": 0.949, "high": 0.949, "low": 0.9489, "close": 0.9489, "volume": 1568, "datetime": "2022-06-02 19:27:00"}, {"open": 0.949, "high": 0.9558, "low": 0.9489, "close": 0.95, "volume": 16587, "datetime": "2022-06-02 19:33:00"}, {"open": 0.9501, "high": 0.9501, "low": 0.94, "close": 0.94, "volume": 10097, "datetime": "2022-06-02 19:43:00"}, {"open": 0.94, "high": 0.9427, "low": 0.94, "close": 0.9427, "volume": 1000, "datetime": "2022-06-02 19:47:00"}, {"open": 0.94, "high": 0.94, "low": 0.94, "close": 0.94, "volume": 100, "datetime": "2022-06-02 19:50:00"}, {"open": 0.94, "high": 0.94, "low": 0.94, "close": 0.94, "volume": 1514, "datetime": "2022-06-02 19:57:00"}, {"open": 0.93, "high": 0.93, "low": 0.93, "close": 0.93, "volume": 119, "datetime": "2022-06-02 20:00:00"}, {"open": 0.91, "high": 0.91, "low": 0.91, "close": 0.91, "volume": 200, "datetime": "2022-06-02 20:06:00"}, {"open": 0.9555, "high": 0.9555, "low": 0.9555, "close": 0.9555, "volume": 100, "datetime": "2022-06-02 21:26:00"}, {"open": 0.9396, "high": 0.9396, "low": 0.9396, "close": 0.9396, "volume": 258, "datetime": "2022-06-03 13:30:00"}, {"open": 0.9301, "high": 0.94, "low": 0.9301, "close": 0.94, "volume": 1855, "datetime": "2022-06-03 13:48:00"}, {"open": 0.960999, "high": 0.960999, "low": 0.960999, "close": 0.960999, "volume": 5000, "datetime": "2022-06-03 13:50:00"}, {"open": 0.9667, "high": 0.9667, "low": 0.9667, "close": 0.9667, "volume": 100, "datetime": "2022-06-03 13:57:00"}, {"open": 0.9669, "high": 0.9669, "low": 0.9669, "close": 0.9669, "volume": 6062, "datetime": "2022-06-03 14:04:00"}, {"open": 0.966999, "high": 0.966999, "low": 0.966999, "close": 0.966999, "volume": 204, "datetime": "2022-06-03 14:06:00"}, {"open": 0.9601, "high": 0.9601, "low": 0.9153, "close": 0.9153, "volume": 10461, "datetime": "2022-06-03 14:36:00"}, {"open": 0.9366, "high": 0.9367, "low": 0.9366, "close": 0.9367, "volume": 4000, "datetime": "2022-06-03 14:40:00"}, {"open": 0.9669, "high": 0.9669, "low": 0.9669, "close": 0.9669, "volume": 100, "datetime": "2022-06-03 14:41:00"}, {"open": 0.9646, "high": 0.967, "low": 0.958499, "close": 0.958499, "volume": 1893, "datetime": "2022-06-03 14:42:00"}, {"open": 0.967, "high": 0.967, "low": 0.967, "close": 0.967, "volume": 100, "datetime": "2022-06-03 14:43:00"}, {"open": 0.9669, "high": 0.9669, "low": 0.9669, "close": 0.9669, "volume": 1500, "datetime": "2022-06-03 14:44:00"}, {"open": 0.9601, "high": 0.9669, "low": 0.9601, "close": 0.9669, "volume": 700, "datetime": "2022-06-03 14:47:00"}, {"open": 0.960101, "high": 0.960101, "low": 0.960101, "close": 0.960101, "volume": 1000, "datetime": "2022-06-03 15:03:00"}, {"open": 0.962, "high": 0.962, "low": 0.962, "close": 0.962, "volume": 1400, "datetime": "2022-06-03 15:06:00"}, {"open": 0.9601, "high": 0.9601, "low": 0.96, "close": 0.96, "volume": 4596, "datetime": "2022-06-03 15:17:00"}, {"open": 0.932, "high": 0.932, "low": 0.93, "close": 0.93, "volume": 300, "datetime": "2022-06-03 15:19:00"}, {"open": 0.932, "high": 0.932, "low": 0.932, "close": 0.932, "volume": 200, "datetime": "2022-06-03 15:20:00"}, {"open": 0.9381, "high": 0.9548, "low": 0.9381, "close": 0.9548, "volume": 400, "datetime": "2022-06-03 15:27:00"}, {"open": 0.9461, "high": 0.9461, "low": 0.9461, "close": 0.9461, "volume": 200, "datetime": "2022-06-03 15:32:00"}, {"open": 0.95, "high": 0.95, "low": 0.95, "close": 0.95, "volume": 248, "datetime": "2022-06-03 15:36:00"}, {"open": 0.9512, "high": 0.9512, "low": 0.9512, "close": 0.9512, "volume": 100, "datetime": "2022-06-03 15:41:00"}, {"open": 0.9414, "high": 0.9441, "low": 0.9414, "close": 0.9441, "volume": 1000, "datetime": "2022-06-03 16:07:00"}, {"open": 0.961, "high": 0.961, "low": 0.9414, "close": 0.9414, "volume": 900, "datetime": "2022-06-03 18:07:00"}, {"open": 0.9608, "high": 0.9608, "low": 0.9608, "close": 0.9608, "volume": 3974, "datetime": "2022-06-03 18:45:00"}, {"open": 0.928, "high": 0.928, "low": 0.928, "close": 0.928, "volume": 100, "datetime": "2022-06-03 19:25:00"}, {"open": 0.93, "high": 0.93, "low": 0.93, "close": 0.93, "volume": 1500, "datetime": "2022-06-03 19:45:00"}, {"open": 0.9494, "high": 0.9494, "low": 0.9494, "close": 0.9494, "volume": 870, "datetime": "2022-06-03 19:57:00"}, {"open": 0.95, "high": 0.95, "low": 0.95, "close": 0.95, "volume": 192, "datetime": "2022-06-06 13:33:00"}, {"open": 0.95, "high": 0.95, "low": 0.95, "close": 0.95, "volume": 295, "datetime": "2022-06-06 13:36:00"}, {"open": 0.9545, "high": 0.9545, "low": 0.9545, "close": 0.9545, "volume": 768, "datetime": "2022-06-06 14:03:00"}, {"open": 0.9651, "high": 0.9651, "low": 0.9646, "close": 0.9646, "volume": 640, "datetime": "2022-06-06 14:08:00"}, {"open": 0.9668, "high": 0.9668, "low": 0.9668, "close": 0.9668, "volume": 969, "datetime": "2022-06-06 14:21:00"}, {"open": 0.9646, "high": 0.9647, "low": 0.9347, "close": 0.9347, "volume": 9099, "datetime": "2022-06-06 14:23:00"}, {"open": 0.967, "high": 0.967, "low": 0.967, "close": 0.967, "volume": 288, "datetime": "2022-06-06 14:24:00"}, {"open": 0.967, "high": 0.967, "low": 0.967, "close": 0.967, "volume": 100, "datetime": "2022-06-06 14:29:00"}, {"open": 0.967, "high": 0.967, "low": 0.967, "close": 0.967, "volume": 400, "datetime": "2022-06-06 14:41:00"}, {"open": 0.967, "high": 0.967, "low": 0.967, "close": 0.967, "volume": 115, "datetime": "2022-06-06 15:24:00"}, {"open": 0.967, "high": 0.967, "low": 0.967, "close": 0.967, "volume": 2197, "datetime": "2022-06-06 16:07:00"}, {"open": 0.9672, "high": 0.9672, "low": 0.9672, "close": 0.9672, "volume": 100, "datetime": "2022-06-06 16:09:00"}, {"open": 0.97, "high": 0.97, "low": 0.97, "close": 0.97, "volume": 200, "datetime": "2022-06-06 16:44:00"}, {"open": 0.9788, "high": 0.9788, "low": 0.9788, "close": 0.9788, "volume": 300, "datetime": "2022-06-06 16:48:00"}, {"open": 0.9721, "high": 0.9721, "low": 0.9721, "close": 0.9721, "volume": 200, "datetime": "2022-06-06 16:51:00"}, {"open": 0.9721, "high": 0.972268, "low": 0.9721, "close": 0.972268, "volume": 3400, "datetime": "2022-06-06 16:52:00"}, {"open": 0.9553, "high": 0.9553, "low": 0.9553, "close": 0.9553, "volume": 800, "datetime": "2022-06-06 17:12:00"}, {"open": 0.96, "high": 0.96, "low": 0.96, "close": 0.96, "volume": 1100, "datetime": "2022-06-06 17:20:00"}, {"open": 0.9525, "high": 0.9525, "low": 0.9525, "close": 0.9525, "volume": 2545, "datetime": "2022-06-06 18:07:00"}, {"open": 0.9501, "high": 0.9501, "low": 0.9501, "close": 0.9501, "volume": 100, "datetime": "2022-06-06 18:15:00"}, {"open": 0.9563, "high": 0.9563, "low": 0.95, "close": 0.9545, "volume": 467, "datetime": "2022-06-06 18:45:00"}, {"open": 0.9545, "high": 0.9545, "low": 0.95, "close": 0.95, "volume": 1100, "datetime": "2022-06-06 18:55:00"}, {"open": 0.965, "high": 0.965, "low": 0.965, "close": 0.965, "volume": 100, "datetime": "2022-06-06 18:59:00"}, {"open": 0.9501, "high": 0.9501, "low": 0.9501, "close": 0.9501, "volume": 3740, "datetime": "2022-06-06 19:15:00"}, {"open": 0.9575, "high": 0.9575, "low": 0.9575, "close": 0.9575, "volume": 100, "datetime": "2022-06-06 19:33:00"}, {"open": 0.95, "high": 0.95, "low": 0.95, "close": 0.95, "volume": 9894, "datetime": "2022-06-06 19:40:00"}, {"open": 0.94, "high": 0.94, "low": 0.94, "close": 0.94, "volume": 131, "datetime": "2022-06-06 19:45:00"}, {"open": 0.91, "high": 0.91, "low": 0.91, "close": 0.91, "volume": 1529, "datetime": "2022-06-07 13:30:00"}, {"open": 0.9405, "high": 0.9405, "low": 0.9405, "close": 0.9405, "volume": 2059, "datetime": "2022-06-07 13:39:00"}, {"open": 0.95, "high": 0.95, "low": 0.95, "close": 0.95, "volume": 400, "datetime": "2022-06-07 14:06:00"}, {"open": 0.95, "high": 0.95, "low": 0.95, "close": 0.95, "volume": 300, "datetime": "2022-06-07 14:37:00"}, {"open": 0.95, "high": 0.95, "low": 0.95, "close": 0.95, "volume": 802, "datetime": "2022-06-07 14:43:00"}, {"open": 0.964, "high": 0.964, "low": 0.964, "close": 0.964, "volume": 180, "datetime": "2022-06-07 14:45:00"}, {"open": 0.965, "high": 0.965, "low": 0.965, "close": 0.965, "volume": 300, "datetime": "2022-06-07 14:48:00"}, {"open": 0.96, "high": 0.96, "low": 0.96, "close": 0.96, "volume": 800, "datetime": "2022-06-07 15:17:00"}, {"open": 0.965, "high": 0.965, "low": 0.965, "close": 0.965, "volume": 300, "datetime": "2022-06-07 15:19:00"}, {"open": 0.965, "high": 0.965, "low": 0.965, "close": 0.965, "volume": 300, "datetime": "2022-06-07 15:35:00"}, {"open": 0.965, "high": 0.965, "low": 0.965, "close": 0.965, "volume": 300, "datetime": "2022-06-07 15:49:00"}, {"open": 0.96, "high": 0.96, "low": 0.96, "close": 0.96, "volume": 300, "datetime": "2022-06-07 16:05:00"}, {"open": 0.96, "high": 0.96, "low": 0.96, "close": 0.96, "volume": 300, "datetime": "2022-06-07 16:18:00"}, {"open": 0.96, "high": 0.96, "low": 0.96, "close": 0.96, "volume": 295, "datetime": "2022-06-07 16:34:00"}, {"open": 0.97, "high": 0.97, "low": 0.97, "close": 0.97, "volume": 186, "datetime": "2022-06-07 16:47:00"}, {"open": 0.9552, "high": 0.9552, "low": 0.9552, "close": 0.9552, "volume": 100, "datetime": "2022-06-07 16:58:00"}, {"open": 0.96, "high": 0.9699, "low": 0.96, "close": 0.9699, "volume": 1200, "datetime": "2022-06-07 17:04:00"}, {"open": 0.9649, "high": 0.9649, "low": 0.9649, "close": 0.9649, "volume": 100, "datetime": "2022-06-07 17:05:00"}, {"open": 0.9649, "high": 0.9649, "low": 0.9649, "close": 0.9649, "volume": 100, "datetime": "2022-06-07 17:07:00"}, {"open": 0.9649, "high": 0.9698, "low": 0.9649, "close": 0.9698, "volume": 1400, "datetime": "2022-06-07 17:09:00"}, {"open": 0.9649, "high": 0.9649, "low": 0.9649, "close": 0.9649, "volume": 200, "datetime": "2022-06-07 17:10:00"}, {"open": 0.9649, "high": 0.9698, "low": 0.9649, "close": 0.9649, "volume": 3900, "datetime": "2022-06-07 17:12:00"}, {"open": 0.9649, "high": 0.9649, "low": 0.9649, "close": 0.9649, "volume": 699, "datetime": "2022-06-07 17:13:00"}, {"open": 0.9649, "high": 0.9649, "low": 0.9649, "close": 0.9649, "volume": 100, "datetime": "2022-06-07 17:14:00"}, {"open": 0.9649, "high": 0.9649, "low": 0.9649, "close": 0.9649, "volume": 100, "datetime": "2022-06-07 17:16:00"}, {"open": 0.9555, "high": 0.9555, "low": 0.9555, "close": 0.9555, "volume": 100, "datetime": "2022-06-07 17:28:00"}, {"open": 0.9552, "high": 0.9552, "low": 0.9552, "close": 0.9552, "volume": 100, "datetime": "2022-06-07 17:29:00"}, {"open": 0.9557, "high": 0.9586, "low": 0.9499, "close": 0.9558, "volume": 3637, "datetime": "2022-06-07 17:30:00"}, {"open": 0.9558, "high": 0.9558, "low": 0.9558, "close": 0.9558, "volume": 300, "datetime": "2022-06-07 17:38:00"}, {"open": 0.9558, "high": 0.9558, "low": 0.9558, "close": 0.9558, "volume": 200, "datetime": "2022-06-07 17:51:00"}, {"open": 0.9564, "high": 0.9564, "low": 0.9561, "close": 0.9561, "volume": 400, "datetime": "2022-06-07 17:52:00"}, {"open": 0.9561, "high": 0.9561, "low": 0.9561, "close": 0.9561, "volume": 175, "datetime": "2022-06-07 17:55:00"}, {"open": 0.957, "high": 0.957, "low": 0.9558, "close": 0.9558, "volume": 400, "datetime": "2022-06-07 17:56:00"}, {"open": 0.957, "high": 0.957, "low": 0.957, "close": 0.957, "volume": 100, "datetime": "2022-06-07 17:58:00"}, {"open": 0.9569, "high": 0.9569, "low": 0.9569, "close": 0.9569, "volume": 1000, "datetime": "2022-06-07 18:04:00"}, {"open": 0.9558, "high": 0.9558, "low": 0.9558, "close": 0.9558, "volume": 1000, "datetime": "2022-06-07 18:05:00"}, {"open": 0.9558, "high": 0.9558, "low": 0.9558, "close": 0.9558, "volume": 1000, "datetime": "2022-06-07 18:06:00"}, {"open": 0.9559, "high": 0.9559, "low": 0.9558, "close": 0.9558, "volume": 1100, "datetime": "2022-06-07 18:07:00"}, {"open": 0.9559, "high": 0.9559, "low": 0.9559, "close": 0.9559, "volume": 200, "datetime": "2022-06-07 18:09:00"}, {"open": 0.9558, "high": 0.9558, "low": 0.9558, "close": 0.9558, "volume": 100, "datetime": "2022-06-07 18:18:00"}, {"open": 0.9559, "high": 0.9559, "low": 0.9558, "close": 0.9559, "volume": 700, "datetime": "2022-06-07 18:19:00"}, {"open": 0.9559, "high": 0.9559, "low": 0.9558, "close": 0.9559, "volume": 3097, "datetime": "2022-06-07 18:20:00"}, {"open": 0.956, "high": 0.956, "low": 0.956, "close": 0.956, "volume": 300, "datetime": "2022-06-07 18:26:00"}, {"open": 0.9559, "high": 0.9559, "low": 0.9559, "close": 0.9559, "volume": 2311, "datetime": "2022-06-07 18:32:00"}, {"open": 0.9559, "high": 0.9559, "low": 0.9559, "close": 0.9559, "volume": 200, "datetime": "2022-06-07 18:37:00"}, {"open": 0.9558, "high": 0.9559, "low": 0.9558, "close": 0.9558, "volume": 461, "datetime": "2022-06-07 18:38:00"}, {"open": 0.9559, "high": 0.9559, "low": 0.9559, "close": 0.9559, "volume": 100, "datetime": "2022-06-07 18:39:00"}, {"open": 0.9558, "high": 0.9558, "low": 0.9558, "close": 0.9558, "volume": 100, "datetime": "2022-06-07 18:42:00"}, {"open": 0.9559, "high": 0.956, "low": 0.9558, "close": 0.9558, "volume": 10841, "datetime": "2022-06-07 18:43:00"}, {"open": 0.9359, "high": 0.9359, "low": 0.9359, "close": 0.9359, "volume": 2000, "datetime": "2022-06-07 18:46:00"}, {"open": 0.9359, "high": 0.9359, "low": 0.9357, "close": 0.9357, "volume": 400, "datetime": "2022-06-07 18:47:00"}, {"open": 0.9356, "high": 0.9356, "low": 0.9356, "close": 0.9356, "volume": 1500, "datetime": "2022-06-07 18:48:00"}, {"open": 0.9346, "high": 0.9346, "low": 0.9346, "close": 0.9346, "volume": 100, "datetime": "2022-06-07 18:49:00"}, {"open": 0.9346, "high": 0.9359, "low": 0.9346, "close": 0.9359, "volume": 3200, "datetime": "2022-06-07 18:51:00"}, {"open": 0.9507, "high": 0.9507, "low": 0.9507, "close": 0.9507, "volume": 100, "datetime": "2022-06-07 18:52:00"}, {"open": 0.9651, "high": 0.9651, "low": 0.9651, "close": 0.9651, "volume": 300, "datetime": "2022-06-07 19:06:00"}, {"open": 0.9558, "high": 0.9558, "low": 0.9558, "close": 0.9558, "volume": 100, "datetime": "2022-06-07 19:08:00"}, {"open": 0.9651, "high": 0.9651, "low": 0.9651, "close": 0.9651, "volume": 100, "datetime": "2022-06-07 19:09:00"}, {"open": 0.9601, "high": 0.9601, "low": 0.9601, "close": 0.9601, "volume": 400, "datetime": "2022-06-07 19:13:00"}, {"open": 0.9601, "high": 0.9601, "low": 0.9601, "close": 0.9601, "volume": 100, "datetime": "2022-06-07 19:17:00"}, {"open": 0.9626, "high": 0.9626, "low": 0.9626, "close": 0.9626, "volume": 100, "datetime": "2022-06-07 19:18:00"}, {"open": 0.965, "high": 0.9651, "low": 0.965, "close": 0.9651, "volume": 300, "datetime": "2022-06-07 19:19:00"}, {"open": 0.9601, "high": 0.9601, "low": 0.9601, "close": 0.9601, "volume": 200, "datetime": "2022-06-07 19:25:00"}, {"open": 0.9651, "high": 0.9651, "low": 0.9651, "close": 0.9651, "volume": 300, "datetime": "2022-06-07 19:27:00"}, {"open": 0.965, "high": 0.9651, "low": 0.965, "close": 0.9651, "volume": 300, "datetime": "2022-06-07 19:33:00"}, {"open": 0.9625, "high": 0.9625, "low": 0.96, "close": 0.9612, "volume": 32749, "datetime": "2022-06-07 19:35:00"}, {"open": 0.94035, "high": 0.9622, "low": 0.94035, "close": 0.9622, "volume": 1471, "datetime": "2022-06-07 19:37:00"}, {"open": 0.95105, "high": 0.9621, "low": 0.95105, "close": 0.9621, "volume": 300, "datetime": "2022-06-07 19:46:00"}, {"open": 0.94, "high": 0.94, "low": 0.94, "close": 0.94, "volume": 200, "datetime": "2022-06-07 19:47:00"}, {"open": 0.94, "high": 0.94, "low": 0.94, "close": 0.94, "volume": 200, "datetime": "2022-06-07 19:49:00"}, {"open": 0.94, "high": 0.94, "low": 0.94, "close": 0.94, "volume": 100, "datetime": "2022-06-07 19:50:00"}, {"open": 0.94, "high": 0.94, "low": 0.94, "close": 0.94, "volume": 200, "datetime": "2022-06-07 19:51:00"}, {"open": 0.94, "high": 0.94, "low": 0.94, "close": 0.94, "volume": 200, "datetime": "2022-06-07 19:52:00"}, {"open": 0.951, "high": 0.951, "low": 0.951, "close": 0.951, "volume": 300, "datetime": "2022-06-07 19:53:00"}, {"open": 0.94, "high": 0.94, "low": 0.94, "close": 0.94, "volume": 100, "datetime": "2022-06-07 19:54:00"}, {"open": 0.94, "high": 0.951, "low": 0.94, "close": 0.94, "volume": 318, "datetime": "2022-06-07 19:55:00"}, {"open": 0.962, "high": 0.962, "low": 0.962, "close": 0.962, "volume": 100, "datetime": "2022-06-07 19:57:00"}, {"open": 0.94, "high": 0.94, "low": 0.94, "close": 0.94, "volume": 100, "datetime": "2022-06-07 19:58:00"}, {"open": 0.94, "high": 0.951, "low": 0.94, "close": 0.94, "volume": 974, "datetime": "2022-06-07 19:59:00"}, {"open": 0.94, "high": 0.94, "low": 0.94, "close": 0.94, "volume": 2073, "datetime": "2022-06-07 20:00:00"}, {"open": 0.96, "high": 0.9681, "low": 0.96, "close": 0.9681, "volume": 1370, "datetime": "2022-06-08 13:30:00"}, {"open": 0.9698, "high": 0.9711, "low": 0.9698, "close": 0.9711, "volume": 200, "datetime": "2022-06-08 13:33:00"}, {"open": 0.973, "high": 0.973, "low": 0.973, "close": 0.973, "volume": 700, "datetime": "2022-06-08 13:37:00"}, {"open": 0.933501, "high": 0.933501, "low": 0.9335, "close": 0.9335, "volume": 274, "datetime": "2022-06-08 13:44:00"}, {"open": 0.97, "high": 0.9731, "low": 0.97, "close": 0.9731, "volume": 400, "datetime": "2022-06-08 13:48:00"}, {"open": 0.9751, "high": 0.9788, "low": 0.9751, "close": 0.9755, "volume": 800, "datetime": "2022-06-08 13:56:00"}, {"open": 0.98, "high": 0.98, "low": 0.98, "close": 0.98, "volume": 400, "datetime": "2022-06-08 13:57:00"}, {"open": 0.9851, "high": 0.9851, "low": 0.9851, "close": 0.9851, "volume": 1350, "datetime": "2022-06-08 13:58:00"}, {"open": 0.9851, "high": 0.9851, "low": 0.9851, "close": 0.9851, "volume": 100, "datetime": "2022-06-08 13:59:00"}, {"open": 0.9851, "high": 0.9851, "low": 0.985, "close": 0.985, "volume": 400, "datetime": "2022-06-08 14:00:00"}, {"open": 0.9851, "high": 0.9851, "low": 0.9851, "close": 0.9851, "volume": 100, "datetime": "2022-06-08 14:01:00"}, {"open": 0.985, "high": 0.9851, "low": 0.985, "close": 0.985, "volume": 4773, "datetime": "2022-06-08 14:02:00"}, {"open": 0.9851, "high": 0.9851, "low": 0.9851, "close": 0.9851, "volume": 200, "datetime": "2022-06-08 14:03:00"}, {"open": 0.9851, "high": 0.9851, "low": 0.9851, "close": 0.9851, "volume": 300, "datetime": "2022-06-08 14:04:00"}, {"open": 0.9851, "high": 0.9851, "low": 0.985, "close": 0.985, "volume": 1405, "datetime": "2022-06-08 14:12:00"}, {"open": 0.95, "high": 0.95, "low": 0.9335, "close": 0.9335, "volume": 13469, "datetime": "2022-06-08 14:19:00"}, {"open": 0.98, "high": 0.98, "low": 0.98, "close": 0.98, "volume": 100, "datetime": "2022-06-08 14:42:00"}, {"open": 0.9701, "high": 0.9701, "low": 0.97, "close": 0.97, "volume": 10500, "datetime": "2022-06-08 14:50:00"}, {"open": 0.97, "high": 0.97, "low": 0.97, "close": 0.97, "volume": 2572, "datetime": "2022-06-08 14:53:00"}, {"open": 0.9402, "high": 0.9402, "low": 0.9402, "close": 0.9402, "volume": 100, "datetime": "2022-06-08 14:56:00"}, {"open": 0.9402, "high": 0.9402, "low": 0.9402, "close": 0.9402, "volume": 300, "datetime": "2022-06-08 14:57:00"}, {"open": 0.9402, "high": 0.9689, "low": 0.9402, "close": 0.9689, "volume": 2000, "datetime": "2022-06-08 15:19:00"}, {"open": 0.974, "high": 0.9851, "low": 0.974, "close": 0.9851, "volume": 1500, "datetime": "2022-06-08 16:06:00"}, {"open": 0.974, "high": 0.974, "low": 0.964219, "close": 0.964219, "volume": 400, "datetime": "2022-06-08 16:19:00"}, {"open": 0.972, "high": 0.972, "low": 0.972, "close": 0.972, "volume": 813, "datetime": "2022-06-08 16:31:00"}, {"open": 0.9851, "high": 0.9851, "low": 0.9851, "close": 0.9851, "volume": 1600, "datetime": "2022-06-08 16:44:00"}, {"open": 0.9785, "high": 0.9785, "low": 0.9785, "close": 0.9785, "volume": 100, "datetime": "2022-06-08 16:53:00"}, {"open": 0.9786, "high": 0.9786, "low": 0.9786, "close": 0.9786, "volume": 5000, "datetime": "2022-06-08 17:10:00"}, {"open": 0.9851, "high": 0.9851, "low": 0.9851, "close": 0.9851, "volume": 800, "datetime": "2022-06-08 17:16:00"}, {"open": 0.98, "high": 0.98, "low": 0.98, "close": 0.98, "volume": 700, "datetime": "2022-06-08 17:22:00"}, {"open": 0.98, "high": 0.98, "low": 0.98, "close": 0.98, "volume": 400, "datetime": "2022-06-08 17:24:00"}, {"open": 0.98, "high": 0.98, "low": 0.98, "close": 0.98, "volume": 386, "datetime": "2022-06-08 17:37:00"}, {"open": 0.98, "high": 0.98, "low": 0.98, "close": 0.98, "volume": 1700, "datetime": "2022-06-08 17:59:00"}, {"open": 0.98, "high": 0.98, "low": 0.98, "close": 0.98, "volume": 200, "datetime": "2022-06-08 18:06:00"}, {"open": 0.98, "high": 0.98, "low": 0.98, "close": 0.98, "volume": 400, "datetime": "2022-06-08 18:07:00"}, {"open": 0.98, "high": 0.98, "low": 0.98, "close": 0.98, "volume": 300, "datetime": "2022-06-08 18:15:00"}, {"open": 0.9801, "high": 0.9801, "low": 0.9801, "close": 0.9801, "volume": 200, "datetime": "2022-06-08 18:18:00"}, {"open": 0.982301, "high": 0.982301, "low": 0.982301, "close": 0.982301, "volume": 200, "datetime": "2022-06-08 18:32:00"}, {"open": 0.9846, "high": 0.9846, "low": 0.9846, "close": 0.9846, "volume": 1099, "datetime": "2022-06-08 18:37:00"}, {"open": 0.9847, "high": 0.9847, "low": 0.9847, "close": 0.9847, "volume": 300, "datetime": "2022-06-08 18:40:00"}, {"open": 0.9851, "high": 0.9851, "low": 0.9851, "close": 0.9851, "volume": 400, "datetime": "2022-06-08 18:42:00"}, {"open": 0.9851, "high": 0.9851, "low": 0.9851, "close": 0.9851, "volume": 400, "datetime": "2022-06-08 18:45:00"}, {"open": 0.9851, "high": 0.9851, "low": 0.9851, "close": 0.9851, "volume": 300, "datetime": "2022-06-08 18:49:00"}, {"open": 0.98, "high": 0.98, "low": 0.98, "close": 0.98, "volume": 400, "datetime": "2022-06-08 19:00:00"}, {"open": 0.98, "high": 0.98, "low": 0.98, "close": 0.98, "volume": 200, "datetime": "2022-06-08 19:03:00"}, {"open": 0.985, "high": 0.985, "low": 0.985, "close": 0.985, "volume": 500, "datetime": "2022-06-08 19:18:00"}, {"open": 0.98, "high": 0.9819, "low": 0.964, "close": 0.978, "volume": 12750, "datetime": "2022-06-08 19:23:00"}, {"open": 0.9741, "high": 0.9741, "low": 0.9741, "close": 0.9741, "volume": 100, "datetime": "2022-06-08 19:24:00"}, {"open": 0.9607, "high": 0.9607, "low": 0.96, "close": 0.96, "volume": 496, "datetime": "2022-06-08 19:27:00"}, {"open": 0.96, "high": 0.96, "low": 0.96, "close": 0.96, "volume": 10000, "datetime": "2022-06-08 19:37:00"}, {"open": 0.96, "high": 0.96, "low": 0.9448, "close": 0.9448, "volume": 10008, "datetime": "2022-06-08 19:38:00"}, {"open": 0.949999, "high": 0.949999, "low": 0.949999, "close": 0.949999, "volume": 657, "datetime": "2022-06-08 19:59:00"}, {"open": 0.92, "high": 0.92, "low": 0.92, "close": 0.92, "volume": 200, "datetime": "2022-06-08 20:22:00"}, {"open": 0.982, "high": 1.01, "low": 0.982, "close": 1.01, "volume": 9880, "datetime": "2022-06-09 13:30:00"}, {"open": 0.9335, "high": 0.9335, "low": 0.9335, "close": 0.9335, "volume": 500, "datetime": "2022-06-09 13:32:00"}, {"open": 0.9335, "high": 0.9335, "low": 0.9335, "close": 0.9335, "volume": 250, "datetime": "2022-06-09 13:45:00"}, {"open": 0.9335, "high": 0.9335, "low": 0.9335, "close": 0.9335, "volume": 3296, "datetime": "2022-06-09 13:53:00"}, {"open": 0.98, "high": 0.98, "low": 0.98, "close": 0.98, "volume": 100, "datetime": "2022-06-09 14:08:00"}, {"open": 0.98, "high": 0.98, "low": 0.98, "close": 0.98, "volume": 100, "datetime": "2022-06-09 14:09:00"}, {"open": 0.98, "high": 0.98, "low": 0.98, "close": 0.98, "volume": 200, "datetime": "2022-06-09 14:10:00"}, {"open": 0.98, "high": 0.98, "low": 0.98, "close": 0.98, "volume": 100, "datetime": "2022-06-09 14:11:00"}, {"open": 0.98, "high": 0.98, "low": 0.98, "close": 0.98, "volume": 100, "datetime": "2022-06-09 14:12:00"}, {"open": 0.98, "high": 0.98, "low": 0.98, "close": 0.98, "volume": 100, "datetime": "2022-06-09 14:13:00"}, {"open": 0.98, "high": 0.98, "low": 0.98, "close": 0.98, "volume": 100, "datetime": "2022-06-09 14:14:00"}, {"open": 0.98, "high": 0.98, "low": 0.98, "close": 0.98, "volume": 100, "datetime": "2022-06-09 14:15:00"}, {"open": 0.98, "high": 0.98, "low": 0.98, "close": 0.98, "volume": 100, "datetime": "2022-06-09 14:16:00"}, {"open": 0.98, "high": 0.98, "low": 0.98, "close": 0.98, "volume": 100, "datetime": "2022-06-09 14:17:00"}, {"open": 0.98, "high": 0.98, "low": 0.98, "close": 0.98, "volume": 100, "datetime": "2022-06-09 14:18:00"}, {"open": 0.98, "high": 0.98, "low": 0.98, "close": 0.98, "volume": 200, "datetime": "2022-06-09 14:19:00"}, {"open": 0.98, "high": 0.98, "low": 0.98, "close": 0.98, "volume": 100, "datetime": "2022-06-09 14:20:00"}, {"open": 0.98, "high": 0.98, "low": 0.98, "close": 0.98, "volume": 100, "datetime": "2022-06-09 14:21:00"}, {"open": 0.98, "high": 0.98, "low": 0.98, "close": 0.98, "volume": 100, "datetime": "2022-06-09 14:22:00"}, {"open": 0.98, "high": 0.98, "low": 0.98, "close": 0.98, "volume": 200, "datetime": "2022-06-09 14:23:00"}, {"open": 0.98, "high": 0.98, "low": 0.98, "close": 0.98, "volume": 100, "datetime": "2022-06-09 14:24:00"}, {"open": 0.98, "high": 0.98, "low": 0.98, "close": 0.98, "volume": 100, "datetime": "2022-06-09 14:25:00"}, {"open": 0.98, "high": 0.98, "low": 0.98, "close": 0.98, "volume": 100, "datetime": "2022-06-09 14:26:00"}, {"open": 0.98, "high": 0.98, "low": 0.98, "close": 0.98, "volume": 200, "datetime": "2022-06-09 14:27:00"}, {"open": 0.98, "high": 0.98, "low": 0.98, "close": 0.98, "volume": 100, "datetime": "2022-06-09 14:28:00"}, {"open": 0.98, "high": 0.98, "low": 0.98, "close": 0.98, "volume": 100, "datetime": "2022-06-09 14:29:00"}, {"open": 0.98, "high": 0.98, "low": 0.98, "close": 0.98, "volume": 100, "datetime": "2022-06-09 14:30:00"}, {"open": 0.98, "high": 0.98, "low": 0.98, "close": 0.98, "volume": 200, "datetime": "2022-06-09 14:31:00"}, {"open": 0.98, "high": 0.98, "low": 0.98, "close": 0.98, "volume": 100, "datetime": "2022-06-09 14:32:00"}, {"open": 0.98, "high": 0.98, "low": 0.98, "close": 0.98, "volume": 100, "datetime": "2022-06-09 14:33:00"}, {"open": 0.98, "high": 0.98, "low": 0.98, "close": 0.98, "volume": 100, "datetime": "2022-06-09 14:34:00"}, {"open": 0.98, "high": 0.98, "low": 0.98, "close": 0.98, "volume": 100, "datetime": "2022-06-09 14:35:00"}, {"open": 0.98, "high": 0.98, "low": 0.98, "close": 0.98, "volume": 5200, "datetime": "2022-06-09 14:36:00"}, {"open": 0.98, "high": 0.98, "low": 0.98, "close": 0.98, "volume": 100, "datetime": "2022-06-09 14:37:00"}, {"open": 0.98, "high": 0.98, "low": 0.98, "close": 0.98, "volume": 100, "datetime": "2022-06-09 14:38:00"}, {"open": 0.985, "high": 0.985, "low": 0.985, "close": 0.985, "volume": 163, "datetime": "2022-06-09 14:39:00"}, {"open": 0.985, "high": 0.985, "low": 0.985, "close": 0.985, "volume": 100, "datetime": "2022-06-09 14:40:00"}, {"open": 0.985, "high": 0.985, "low": 0.985, "close": 0.985, "volume": 300, "datetime": "2022-06-09 14:41:00"}, {"open": 0.985, "high": 0.985, "low": 0.985, "close": 0.985, "volume": 100, "datetime": "2022-06-09 14:44:00"}, {"open": 0.985, "high": 0.985, "low": 0.985, "close": 0.985, "volume": 100, "datetime": "2022-06-09 14:45:00"}, {"open": 0.985, "high": 0.985, "low": 0.985, "close": 0.985, "volume": 100, "datetime": "2022-06-09 14:46:00"}, {"open": 0.985, "high": 0.985, "low": 0.985, "close": 0.985, "volume": 200, "datetime": "2022-06-09 14:47:00"}, {"open": 0.985, "high": 0.985, "low": 0.961, "close": 0.9709, "volume": 300, "datetime": "2022-06-09 14:48:00"}, {"open": 0.989899, "high": 0.9899, "low": 0.961, "close": 0.989899, "volume": 400, "datetime": "2022-06-09 14:49:00"}, {"open": 0.99, "high": 0.99, "low": 0.99, "close": 0.99, "volume": 100, "datetime": "2022-06-09 14:50:00"}, {"open": 0.99, "high": 0.99, "low": 0.99, "close": 0.99, "volume": 200, "datetime": "2022-06-09 14:51:00"}, {"open": 0.99, "high": 0.99, "low": 0.99, "close": 0.99, "volume": 200, "datetime": "2022-06-09 14:52:00"}, {"open": 0.99, "high": 0.99, "low": 0.99, "close": 0.99, "volume": 300, "datetime": "2022-06-09 14:54:00"}, {"open": 0.99, "high": 0.99, "low": 0.99, "close": 0.99, "volume": 100, "datetime": "2022-06-09 14:56:00"}, {"open": 0.99, "high": 0.99, "low": 0.99, "close": 0.99, "volume": 200, "datetime": "2022-06-09 14:57:00"}, {"open": 0.99, "high": 0.99, "low": 0.99, "close": 0.99, "volume": 100, "datetime": "2022-06-09 14:58:00"}, {"open": 0.99, "high": 0.99, "low": 0.99, "close": 0.99, "volume": 200, "datetime": "2022-06-09 14:59:00"}, {"open": 0.99, "high": 0.99, "low": 0.99, "close": 0.99, "volume": 300, "datetime": "2022-06-09 15:00:00"}, {"open": 0.99, "high": 0.9939, "low": 0.99, "close": 0.9939, "volume": 200, "datetime": "2022-06-09 15:02:00"}, {"open": 0.9853, "high": 0.9853, "low": 0.9853, "close": 0.9853, "volume": 200, "datetime": "2022-06-09 15:04:00"}, {"open": 1.0, "high": 1.0, "low": 1.0, "close": 1.0, "volume": 100, "datetime": "2022-06-09 15:05:00"}, {"open": 1.0, "high": 1.0, "low": 1.0, "close": 1.0, "volume": 100, "datetime": "2022-06-09 15:06:00"}, {"open": 1.0, "high": 1.0, "low": 1.0, "close": 1.0, "volume": 100, "datetime": "2022-06-09 15:07:00"}, {"open": 1.0045, "high": 1.0099, "low": 1.0001, "close": 1.0001, "volume": 1550, "datetime": "2022-06-09 15:10:00"}, {"open": 1.0001, "high": 1.0001, "low": 1.0001, "close": 1.0001, "volume": 1250, "datetime": "2022-06-09 15:11:00"}, {"open": 1.0, "high": 1.0001, "low": 0.993, "close": 0.993, "volume": 400, "datetime": "2022-06-09 15:17:00"}, {"open": 0.9975, "high": 0.9999, "low": 0.9851, "close": 0.9999, "volume": 600, "datetime": "2022-06-09 15:18:00"}, {"open": 1.0, "high": 1.0, "low": 0.96, "close": 0.96, "volume": 2238, "datetime": "2022-06-09 15:19:00"}, {"open": 1.0, "high": 1.0, "low": 1.0, "close": 1.0, "volume": 162, "datetime": "2022-06-09 15:20:00"}, {"open": 1.0, "high": 1.0, "low": 1.0, "close": 1.0, "volume": 100, "datetime": "2022-06-09 15:22:00"}, {"open": 1.0099, "high": 1.0099, "low": 1.0099, "close": 1.0099, "volume": 100, "datetime": "2022-06-09 15:23:00"}, {"open": 1.0, "high": 1.0099, "low": 0.995, "close": 1.0099, "volume": 300, "datetime": "2022-06-09 15:24:00"}, {"open": 1.01, "high": 1.01, "low": 0.9827, "close": 0.9827, "volume": 1900, "datetime": "2022-06-09 15:25:00"}, {"open": 1.0, "high": 1.0, "low": 1.0, "close": 1.0, "volume": 100, "datetime": "2022-06-09 15:29:00"}, {"open": 1.0, "high": 1.0, "low": 1.0, "close": 1.0, "volume": 200, "datetime": "2022-06-09 15:48:00"}, {"open": 1.0, "high": 1.0, "low": 1.0, "close": 1.0, "volume": 100, "datetime": "2022-06-09 15:49:00"}, {"open": 1.0099, "high": 1.0099, "low": 0.9933, "close": 0.9933, "volume": 300, "datetime": "2022-06-09 15:55:00"}, {"open": 1.0001, "high": 1.0001, "low": 1.0001, "close": 1.0001, "volume": 1000, "datetime": "2022-06-09 15:59:00"}, {"open": 1.0, "high": 1.0002, "low": 0.99, "close": 0.9901, "volume": 800, "datetime": "2022-06-09 16:03:00"}, {"open": 0.99, "high": 0.99, "low": 0.99, "close": 0.99, "volume": 300, "datetime": "2022-06-09 16:06:00"}, {"open": 0.99, "high": 0.99, "low": 0.9875, "close": 0.9875, "volume": 300, "datetime": "2022-06-09 16:08:00"}, {"open": 0.99, "high": 0.9939, "low": 0.99, "close": 0.99, "volume": 300, "datetime": "2022-06-09 16:09:00"}, {"open": 0.99, "high": 0.99, "low": 0.99, "close": 0.99, "volume": 100, "datetime": "2022-06-09 16:11:00"}, {"open": 1.0, "high": 1.0, "low": 1.0, "close": 1.0, "volume": 200, "datetime": "2022-06-09 16:13:00"}, {"open": 1.005, "high": 1.01, "low": 1.0, "close": 1.0, "volume": 400, "datetime": "2022-06-09 16:14:00"}, {"open": 1.0, "high": 1.0, "low": 1.0, "close": 1.0, "volume": 100, "datetime": "2022-06-09 16:15:00"}, {"open": 1.0, "high": 1.0, "low": 1.0, "close": 1.0, "volume": 200, "datetime": "2022-06-09 16:19:00"}, {"open": 1.0, "high": 1.01, "low": 1.0, "close": 1.01, "volume": 329, "datetime": "2022-06-09 16:20:00"}, {"open": 1.005, "high": 1.009, "low": 1.005, "close": 1.009, "volume": 300, "datetime": "2022-06-09 16:25:00"}, {"open": 1.0001, "high": 1.0001, "low": 0.9774, "close": 0.9774, "volume": 3524, "datetime": "2022-06-09 16:28:00"}, {"open": 1.0, "high": 1.0, "low": 1.0, "close": 1.0, "volume": 200, "datetime": "2022-06-09 16:32:00"}, {"open": 1.0, "high": 1.0, "low": 1.0, "close": 1.0, "volume": 300, "datetime": "2022-06-09 16:44:00"}, {"open": 1.0, "high": 1.0, "low": 1.0, "close": 1.0, "volume": 100, "datetime": "2022-06-09 16:45:00"}, {"open": 1.0, "high": 1.0, "low": 1.0, "close": 1.0, "volume": 100, "datetime": "2022-06-09 16:47:00"}, {"open": 1.0, "high": 1.0, "low": 1.0, "close": 1.0, "volume": 200, "datetime": "2022-06-09 16:48:00"}, {"open": 1.0, "high": 1.0, "low": 1.0, "close": 1.0, "volume": 300, "datetime": "2022-06-09 16:49:00"}, {"open": 1.0, "high": 1.0, "low": 1.0, "close": 1.0, "volume": 100, "datetime": "2022-06-09 16:52:00"}, {"open": 1.0, "high": 1.0001, "low": 1.0, "close": 1.0001, "volume": 600, "datetime": "2022-06-09 16:55:00"}, {"open": 1.0, "high": 1.0, "low": 1.0, "close": 1.0, "volume": 402, "datetime": "2022-06-09 17:22:00"}, {"open": 1.0, "high": 1.0, "low": 1.0, "close": 1.0, "volume": 300, "datetime": "2022-06-09 17:23:00"}, {"open": 1.0, "high": 1.0, "low": 1.0, "close": 1.0, "volume": 200, "datetime": "2022-06-09 17:25:00"}, {"open": 1.0, "high": 1.0, "low": 1.0, "close": 1.0, "volume": 200, "datetime": "2022-06-09 17:26:00"}, {"open": 1.0, "high": 1.0, "low": 1.0, "close": 1.0, "volume": 100, "datetime": "2022-06-09 17:32:00"}, {"open": 1.0, "high": 1.0, "low": 0.9744, "close": 0.98, "volume": 2700, "datetime": "2022-06-09 17:43:00"}, {"open": 0.98, "high": 0.98, "low": 0.9619, "close": 0.9619, "volume": 4192, "datetime": "2022-06-09 17:45:00"}, {"open": 0.98, "high": 0.9999, "low": 0.98, "close": 0.9999, "volume": 597, "datetime": "2022-06-09 17:46:00"}, {"open": 1.0, "high": 1.0, "low": 1.0, "close": 1.0, "volume": 100, "datetime": "2022-06-09 17:47:00"}, {"open": 1.0, "high": 1.0, "low": 1.0, "close": 1.0, "volume": 100, "datetime": "2022-06-09 17:48:00"}, {"open": 0.9752, "high": 0.9752, "low": 0.9752, "close": 0.9752, "volume": 168, "datetime": "2022-06-09 17:50:00"}, {"open": 1.0, "high": 1.0, "low": 1.0, "close": 1.0, "volume": 100, "datetime": "2022-06-09 17:55:00"}, {"open": 1.0, "high": 1.0, "low": 1.0, "close": 1.0, "volume": 200, "datetime": "2022-06-09 17:58:00"}, {"open": 1.0, "high": 1.0, "low": 1.0, "close": 1.0, "volume": 600, "datetime": "2022-06-09 17:59:00"}, {"open": 1.0, "high": 1.0, "low": 0.985, "close": 0.985, "volume": 1674, "datetime": "2022-06-09 18:01:00"}, {"open": 1.0, "high": 1.0, "low": 1.0, "close": 1.0, "volume": 300, "datetime": "2022-06-09 18:02:00"}, {"open": 1.0, "high": 1.0, "low": 1.0, "close": 1.0, "volume": 200, "datetime": "2022-06-09 18:03:00"}, {"open": 1.0, "high": 1.0, "low": 1.0, "close": 1.0, "volume": 200, "datetime": "2022-06-09 18:04:00"}, {"open": 1.0, "high": 1.0, "low": 1.0, "close": 1.0, "volume": 200, "datetime": "2022-06-09 18:05:00"}, {"open": 1.0, "high": 1.0, "low": 1.0, "close": 1.0, "volume": 400, "datetime": "2022-06-09 18:06:00"}, {"open": 1.0, "high": 1.0, "low": 1.0, "close": 1.0, "volume": 200, "datetime": "2022-06-09 18:07:00"}, {"open": 0.9999, "high": 0.9999, "low": 0.985, "close": 0.985, "volume": 400, "datetime": "2022-06-09 18:08:00"}, {"open": 0.9999, "high": 0.9999, "low": 0.9999, "close": 0.9999, "volume": 100, "datetime": "2022-06-09 18:09:00"}, {"open": 0.9999, "high": 0.9999, "low": 0.9999, "close": 0.9999, "volume": 300, "datetime": "2022-06-09 18:10:00"}, {"open": 0.9999, "high": 0.9999, "low": 0.9999, "close": 0.9999, "volume": 300, "datetime": "2022-06-09 18:11:00"}, {"open": 0.9999, "high": 0.9999, "low": 0.9999, "close": 0.9999, "volume": 200, "datetime": "2022-06-09 18:12:00"}, {"open": 0.9999, "high": 1.0, "low": 0.985, "close": 1.0, "volume": 2178, "datetime": "2022-06-09 18:13:00"}, {"open": 1.0, "high": 1.0, "low": 1.0, "close": 1.0, "volume": 200, "datetime": "2022-06-09 18:14:00"}, {"open": 1.0, "high": 1.0, "low": 1.0, "close": 1.0, "volume": 400, "datetime": "2022-06-09 18:15:00"}, {"open": 1.0, "high": 1.0, "low": 1.0, "close": 1.0, "volume": 200, "datetime": "2022-06-09 18:16:00"}, {"open": 1.0, "high": 1.0, "low": 1.0, "close": 1.0, "volume": 400, "datetime": "2022-06-09 18:17:00"}, {"open": 1.0, "high": 1.0, "low": 1.0, "close": 1.0, "volume": 800, "datetime": "2022-06-09 18:18:00"}, {"open": 0.9999, "high": 1.0, "low": 0.9999, "close": 1.0, "volume": 300, "datetime": "2022-06-09 18:19:00"}, {"open": 0.9999, "high": 1.0, "low": 0.9999, "close": 1.0, "volume": 200, "datetime": "2022-06-09 18:20:00"}, {"open": 1.0, "high": 1.0, "low": 0.9997, "close": 1.0, "volume": 600, "datetime": "2022-06-09 18:21:00"}, {"open": 1.0, "high": 1.0, "low": 1.0, "close": 1.0, "volume": 100, "datetime": "2022-06-09 18:22:00"}, {"open": 1.0, "high": 1.0, "low": 1.0, "close": 1.0, "volume": 400, "datetime": "2022-06-09 18:29:00"}, {"open": 1.0, "high": 1.0, "low": 1.0, "close": 1.0, "volume": 100, "datetime": "2022-06-09 18:30:00"}, {"open": 1.0008, "high": 1.0008, "low": 1.0008, "close": 1.0008, "volume": 200, "datetime": "2022-06-09 18:39:00"}, {"open": 1.0, "high": 1.0, "low": 1.0, "close": 1.0, "volume": 200, "datetime": "2022-06-09 18:44:00"}, {"open": 1.0001, "high": 1.0002, "low": 1.0, "close": 1.0, "volume": 900, "datetime": "2022-06-09 18:47:00"}, {"open": 0.99255, "high": 0.99255, "low": 0.99255, "close": 0.99255, "volume": 100, "datetime": "2022-06-09 18:48:00"}, {"open": 1.0, "high": 1.0, "low": 1.0, "close": 1.0, "volume": 350, "datetime": "2022-06-09 18:49:00"}, {"open": 1.0, "high": 1.0, "low": 0.9801, "close": 0.9801, "volume": 950, "datetime": "2022-06-09 18:52:00"}, {"open": 1.0, "high": 1.0, "low": 1.0, "close": 1.0, "volume": 100, "datetime": "2022-06-09 18:55:00"}, {"open": 1.0, "high": 1.0, "low": 1.0, "close": 1.0, "volume": 100, "datetime": "2022-06-09 18:56:00"}, {"open": 1.0, "high": 1.0, "low": 1.0, "close": 1.0, "volume": 200, "datetime": "2022-06-09 18:57:00"}, {"open": 1.0, "high": 1.0, "low": 1.0, "close": 1.0, "volume": 300, "datetime": "2022-06-09 19:13:00"}, {"open": 1.0, "high": 1.0, "low": 1.0, "close": 1.0, "volume": 400, "datetime": "2022-06-09 19:14:00"}, {"open": 1.0, "high": 1.0, "low": 1.0, "close": 1.0, "volume": 300, "datetime": "2022-06-09 19:15:00"}, {"open": 1.0, "high": 1.0, "low": 1.0, "close": 1.0, "volume": 100, "datetime": "2022-06-09 19:16:00"}, {"open": 1.0, "high": 1.0, "low": 1.0, "close": 1.0, "volume": 100, "datetime": "2022-06-09 19:22:00"}, {"open": 0.99595, "high": 0.99595, "low": 0.99595, "close": 0.99595, "volume": 200, "datetime": "2022-06-09 19:28:00"}, {"open": 0.9819, "high": 0.9819, "low": 0.9819, "close": 0.9819, "volume": 196, "datetime": "2022-06-09 19:35:00"}, {"open": 0.995, "high": 0.995, "low": 0.995, "close": 0.995, "volume": 1000, "datetime": "2022-06-09 19:39:00"}, {"open": 0.98, "high": 0.98, "low": 0.98, "close": 0.98, "volume": 844, "datetime": "2022-06-09 19:40:00"}, {"open": 0.98, "high": 0.98, "low": 0.98, "close": 0.98, "volume": 200, "datetime": "2022-06-09 19:49:00"}, {"open": 0.98, "high": 0.98, "low": 0.98, "close": 0.98, "volume": 200, "datetime": "2022-06-09 19:54:00"}, {"open": 1.0099, "high": 1.0099, "low": 1.0099, "close": 1.0099, "volume": 100, "datetime": "2022-06-09 19:56:00"}, {"open": 0.98, "high": 1.0099, "low": 0.97, "close": 1.0099, "volume": 10986, "datetime": "2022-06-09 19:57:00"}, {"open": 1.0075, "high": 1.0075, "low": 0.972, "close": 0.972, "volume": 10100, "datetime": "2022-06-09 19:58:00"}, {"open": 1.01, "high": 1.01, "low": 0.97, "close": 0.99, "volume": 10516, "datetime": "2022-06-09 19:59:00"}, {"open": 0.99, "high": 0.99, "low": 0.99, "close": 0.99, "volume": 257, "datetime": "2022-06-10 13:30:00"}, {"open": 0.99, "high": 0.99, "low": 0.96, "close": 0.96, "volume": 11504, "datetime": "2022-06-10 13:34:00"}, {"open": 0.96, "high": 0.96, "low": 0.96, "close": 0.96, "volume": 1753, "datetime": "2022-06-10 14:14:00"}, {"open": 1.0, "high": 1.0, "low": 1.0, "close": 1.0, "volume": 100, "datetime": "2022-06-10 14:18:00"}, {"open": 0.9506, "high": 1.0, "low": 0.9506, "close": 1.0, "volume": 200, "datetime": "2022-06-10 14:19:00"}, {"open": 1.0, "high": 1.0, "low": 1.0, "close": 1.0, "volume": 200, "datetime": "2022-06-10 14:20:00"}, {"open": 1.0, "high": 1.0, "low": 1.0, "close": 1.0, "volume": 100, "datetime": "2022-06-10 14:21:00"}, {"open": 1.0, "high": 1.0, "low": 1.0, "close": 1.0, "volume": 100, "datetime": "2022-06-10 14:22:00"}, {"open": 1.0, "high": 1.0, "low": 1.0, "close": 1.0, "volume": 100, "datetime": "2022-06-10 14:23:00"}, {"open": 1.0, "high": 1.0, "low": 1.0, "close": 1.0, "volume": 100, "datetime": "2022-06-10 14:24:00"}, {"open": 1.0, "high": 1.0, "low": 1.0, "close": 1.0, "volume": 100, "datetime": "2022-06-10 14:26:00"}, {"open": 1.0, "high": 1.0, "low": 1.0, "close": 1.0, "volume": 200, "datetime": "2022-06-10 14:27:00"}, {"open": 1.0, "high": 1.0, "low": 1.0, "close": 1.0, "volume": 100, "datetime": "2022-06-10 14:28:00"}, {"open": 1.0, "high": 1.0, "low": 1.0, "close": 1.0, "volume": 100, "datetime": "2022-06-10 14:29:00"}, {"open": 1.0, "high": 1.0, "low": 1.0, "close": 1.0, "volume": 100, "datetime": "2022-06-10 14:30:00"}, {"open": 1.0, "high": 1.0, "low": 1.0, "close": 1.0, "volume": 200, "datetime": "2022-06-10 14:31:00"}, {"open": 1.0, "high": 1.0, "low": 1.0, "close": 1.0, "volume": 100, "datetime": "2022-06-10 14:32:00"}, {"open": 1.0, "high": 1.0, "low": 1.0, "close": 1.0, "volume": 100, "datetime": "2022-06-10 14:33:00"}, {"open": 1.0, "high": 1.0, "low": 1.0, "close": 1.0, "volume": 100, "datetime": "2022-06-10 14:34:00"}, {"open": 1.0, "high": 1.0, "low": 1.0, "close": 1.0, "volume": 200, "datetime": "2022-06-10 14:35:00"}, {"open": 1.0, "high": 1.0, "low": 1.0, "close": 1.0, "volume": 200, "datetime": "2022-06-10 14:36:00"}, {"open": 0.9999, "high": 1.0, "low": 0.9752, "close": 0.9752, "volume": 300, "datetime": "2022-06-10 14:37:00"}, {"open": 1.0, "high": 1.0, "low": 1.0, "close": 1.0, "volume": 100, "datetime": "2022-06-10 14:38:00"}, {"open": 1.0, "high": 1.0, "low": 1.0, "close": 1.0, "volume": 100, "datetime": "2022-06-10 14:39:00"}, {"open": 1.0, "high": 1.0, "low": 1.0, "close": 1.0, "volume": 200, "datetime": "2022-06-10 14:40:00"}, {"open": 1.0, "high": 1.0, "low": 1.0, "close": 1.0, "volume": 100, "datetime": "2022-06-10 14:41:00"}, {"open": 1.0, "high": 1.0, "low": 1.0, "close": 1.0, "volume": 100, "datetime": "2022-06-10 14:42:00"}, {"open": 1.0, "high": 1.0, "low": 1.0, "close": 1.0, "volume": 100, "datetime": "2022-06-10 14:43:00"}, {"open": 1.0, "high": 1.0, "low": 1.0, "close": 1.0, "volume": 2200, "datetime": "2022-06-10 14:44:00"}, {"open": 1.0, "high": 1.0, "low": 1.0, "close": 1.0, "volume": 100, "datetime": "2022-06-10 14:45:00"}, {"open": 1.0, "high": 1.0, "low": 1.0, "close": 1.0, "volume": 200, "datetime": "2022-06-10 14:46:00"}, {"open": 1.0, "high": 1.0, "low": 1.0, "close": 1.0, "volume": 100, "datetime": "2022-06-10 14:47:00"}, {"open": 1.0, "high": 1.0, "low": 1.0, "close": 1.0, "volume": 200, "datetime": "2022-06-10 14:48:00"}, {"open": 1.0, "high": 1.0, "low": 1.0, "close": 1.0, "volume": 100, "datetime": "2022-06-10 14:49:00"}, {"open": 1.0, "high": 1.0, "low": 1.0, "close": 1.0, "volume": 100, "datetime": "2022-06-10 14:50:00"}, {"open": 1.0, "high": 1.0, "low": 1.0, "close": 1.0, "volume": 100, "datetime": "2022-06-10 14:51:00"}, {"open": 1.0, "high": 1.0, "low": 1.0, "close": 1.0, "volume": 100, "datetime": "2022-06-10 14:52:00"}, {"open": 1.0, "high": 1.0, "low": 1.0, "close": 1.0, "volume": 200, "datetime": "2022-06-10 14:53:00"}, {"open": 1.0, "high": 1.0, "low": 0.9754, "close": 0.9754, "volume": 800, "datetime": "2022-06-10 14:54:00"}, {"open": 1.0, "high": 1.0, "low": 1.0, "close": 1.0, "volume": 100, "datetime": "2022-06-10 14:55:00"}, {"open": 1.0, "high": 1.0, "low": 1.0, "close": 1.0, "volume": 100, "datetime": "2022-06-10 14:56:00"}, {"open": 0.99, "high": 0.99, "low": 0.99, "close": 0.99, "volume": 100, "datetime": "2022-06-10 14:57:00"}, {"open": 0.99, "high": 0.99, "low": 0.99, "close": 0.99, "volume": 200, "datetime": "2022-06-10 14:58:00"}, {"open": 0.99, "high": 0.99, "low": 0.99, "close": 0.99, "volume": 100, "datetime": "2022-06-10 14:59:00"}, {"open": 0.99, "high": 0.99, "low": 0.99, "close": 0.99, "volume": 100, "datetime": "2022-06-10 15:00:00"}, {"open": 0.99, "high": 0.99, "low": 0.99, "close": 0.99, "volume": 200, "datetime": "2022-06-10 15:01:00"}, {"open": 0.99, "high": 0.99, "low": 0.99, "close": 0.99, "volume": 200, "datetime": "2022-06-10 15:02:00"}, {"open": 0.99, "high": 0.99, "low": 0.99, "close": 0.99, "volume": 1099, "datetime": "2022-06-10 15:03:00"}, {"open": 1.0, "high": 1.0, "low": 1.0, "close": 1.0, "volume": 100, "datetime": "2022-06-10 15:04:00"}, {"open": 1.0, "high": 1.0, "low": 1.0, "close": 1.0, "volume": 200, "datetime": "2022-06-10 15:05:00"}, {"open": 1.0, "high": 1.0, "low": 1.0, "close": 1.0, "volume": 100, "datetime": "2022-06-10 15:06:00"}, {"open": 1.0, "high": 1.0, "low": 1.0, "close": 1.0, "volume": 100, "datetime": "2022-06-10 15:07:00"}, {"open": 1.0, "high": 1.0, "low": 1.0, "close": 1.0, "volume": 100, "datetime": "2022-06-10 15:08:00"}, {"open": 1.0, "high": 1.0, "low": 1.0, "close": 1.0, "volume": 200, "datetime": "2022-06-10 15:09:00"}, {"open": 1.0, "high": 1.0, "low": 1.0, "close": 1.0, "volume": 100, "datetime": "2022-06-10 15:10:00"}, {"open": 1.0, "high": 1.0, "low": 1.0, "close": 1.0, "volume": 100, "datetime": "2022-06-10 15:11:00"}, {"open": 1.0, "high": 1.0, "low": 0.9999, "close": 0.9999, "volume": 4200, "datetime": "2022-06-10 15:12:00"}, {"open": 1.0, "high": 1.0, "low": 1.0, "close": 1.0, "volume": 100, "datetime": "2022-06-10 15:13:00"}, {"open": 1.0, "high": 1.0, "low": 1.0, "close": 1.0, "volume": 200, "datetime": "2022-06-10 15:14:00"}, {"open": 1.0, "high": 1.0, "low": 1.0, "close": 1.0, "volume": 100, "datetime": "2022-06-10 15:15:00"}, {"open": 1.0, "high": 1.0, "low": 1.0, "close": 1.0, "volume": 200, "datetime": "2022-06-10 15:17:00"}, {"open": 1.0, "high": 1.0, "low": 1.0, "close": 1.0, "volume": 200, "datetime": "2022-06-10 15:18:00"}, {"open": 1.0, "high": 1.0, "low": 1.0, "close": 1.0, "volume": 200, "datetime": "2022-06-10 15:19:00"}, {"open": 1.0, "high": 1.0, "low": 1.0, "close": 1.0, "volume": 200, "datetime": "2022-06-10 15:20:00"}, {"open": 1.0, "high": 1.0, "low": 1.0, "close": 1.0, "volume": 200, "datetime": "2022-06-10 15:21:00"}, {"open": 1.0, "high": 1.0, "low": 0.963, "close": 0.963, "volume": 1200, "datetime": "2022-06-10 15:22:00"}, {"open": 1.0, "high": 1.0, "low": 1.0, "close": 1.0, "volume": 100, "datetime": "2022-06-10 15:23:00"}, {"open": 1.0, "high": 1.0, "low": 1.0, "close": 1.0, "volume": 100, "datetime": "2022-06-10 15:24:00"}, {"open": 0.9629, "high": 0.9629, "low": 0.9629, "close": 0.9629, "volume": 100, "datetime": "2022-06-10 15:25:00"}, {"open": 1.0, "high": 1.0, "low": 1.0, "close": 1.0, "volume": 100, "datetime": "2022-06-10 15:26:00"}, {"open": 1.0, "high": 1.0, "low": 1.0, "close": 1.0, "volume": 200, "datetime": "2022-06-10 15:27:00"}, {"open": 1.0, "high": 1.0, "low": 1.0, "close": 1.0, "volume": 100, "datetime": "2022-06-10 15:28:00"}, {"open": 1.0, "high": 1.0, "low": 1.0, "close": 1.0, "volume": 200, "datetime": "2022-06-10 15:29:00"}, {"open": 1.0, "high": 1.0, "low": 1.0, "close": 1.0, "volume": 100, "datetime": "2022-06-10 15:30:00"}, {"open": 1.0, "high": 1.0, "low": 1.0, "close": 1.0, "volume": 2100, "datetime": "2022-06-10 15:31:00"}, {"open": 1.0, "high": 1.0, "low": 1.0, "close": 1.0, "volume": 100, "datetime": "2022-06-10 15:32:00"}, {"open": 1.0, "high": 1.0, "low": 1.0, "close": 1.0, "volume": 2200, "datetime": "2022-06-10 15:33:00"}, {"open": 1.0, "high": 1.0, "low": 1.0, "close": 1.0, "volume": 100, "datetime": "2022-06-10 15:34:00"}, {"open": 1.0, "high": 1.0, "low": 1.0, "close": 1.0, "volume": 1195, "datetime": "2022-06-10 15:35:00"}, {"open": 1.0, "high": 1.0, "low": 1.0, "close": 1.0, "volume": 100, "datetime": "2022-06-10 15:36:00"}, {"open": 1.0, "high": 1.0, "low": 1.0, "close": 1.0, "volume": 2300, "datetime": "2022-06-10 15:37:00"}, {"open": 1.0, "high": 1.0, "low": 1.0, "close": 1.0, "volume": 2100, "datetime": "2022-06-10 15:38:00"}, {"open": 1.0, "high": 1.0, "low": 1.0, "close": 1.0, "volume": 100, "datetime": "2022-06-10 15:39:00"}, {"open": 1.0, "high": 1.0, "low": 1.0, "close": 1.0, "volume": 564, "datetime": "2022-06-10 15:40:00"}, {"open": 1.01, "high": 1.01, "low": 1.01, "close": 1.01, "volume": 200, "datetime": "2022-06-10 15:41:00"}, {"open": 1.01, "high": 1.01, "low": 1.01, "close": 1.01, "volume": 100, "datetime": "2022-06-10 15:42:00"}, {"open": 1.01, "high": 1.01, "low": 1.01, "close": 1.01, "volume": 100, "datetime": "2022-06-10 15:43:00"}, {"open": 1.01, "high": 1.01, "low": 1.01, "close": 1.01, "volume": 100, "datetime": "2022-06-10 15:44:00"}, {"open": 1.01, "high": 1.01, "low": 1.01, "close": 1.01, "volume": 100, "datetime": "2022-06-10 15:45:00"}, {"open": 1.01, "high": 1.01, "low": 1.01, "close": 1.01, "volume": 457, "datetime": "2022-06-10 15:46:00"}, {"open": 1.01, "high": 1.01, "low": 1.01, "close": 1.01, "volume": 100, "datetime": "2022-06-10 15:47:00"}, {"open": 1.01, "high": 1.01, "low": 1.01, "close": 1.01, "volume": 100, "datetime": "2022-06-10 15:48:00"}, {"open": 1.02, "high": 1.02, "low": 1.02, "close": 1.02, "volume": 100, "datetime": "2022-06-10 15:49:00"}, {"open": 1.02, "high": 1.02, "low": 1.02, "close": 1.02, "volume": 882, "datetime": "2022-06-10 15:51:00"}, {"open": 1.02, "high": 1.02, "low": 1.02, "close": 1.02, "volume": 200, "datetime": "2022-06-10 15:52:00"}, {"open": 1.02, "high": 1.02, "low": 1.02, "close": 1.02, "volume": 200, "datetime": "2022-06-10 15:53:00"}, {"open": 1.02, "high": 1.02, "low": 1.02, "close": 1.02, "volume": 100, "datetime": "2022-06-10 15:54:00"}, {"open": 1.02, "high": 1.02, "low": 1.02, "close": 1.02, "volume": 200, "datetime": "2022-06-10 15:55:00"}, {"open": 1.02, "high": 1.02, "low": 1.02, "close": 1.02, "volume": 100, "datetime": "2022-06-10 15:56:00"}, {"open": 1.02, "high": 1.02, "low": 1.02, "close": 1.02, "volume": 100, "datetime": "2022-06-10 15:57:00"}, {"open": 1.02, "high": 1.02, "low": 1.02, "close": 1.02, "volume": 200, "datetime": "2022-06-10 15:58:00"}, {"open": 1.02, "high": 1.02, "low": 1.02, "close": 1.02, "volume": 100, "datetime": "2022-06-10 15:59:00"}, {"open": 1.02, "high": 1.02, "low": 1.02, "close": 1.02, "volume": 200, "datetime": "2022-06-10 16:00:00"}, {"open": 1.02, "high": 1.02, "low": 1.02, "close": 1.02, "volume": 100, "datetime": "2022-06-10 16:01:00"}, {"open": 1.02, "high": 1.02, "low": 1.02, "close": 1.02, "volume": 100, "datetime": "2022-06-10 16:02:00"}, {"open": 1.02, "high": 1.02, "low": 1.02, "close": 1.02, "volume": 100, "datetime": "2022-06-10 16:03:00"}, {"open": 1.02, "high": 1.02, "low": 1.02, "close": 1.02, "volume": 200, "datetime": "2022-06-10 16:04:00"}, {"open": 1.02, "high": 1.02, "low": 1.02, "close": 1.02, "volume": 200, "datetime": "2022-06-10 16:05:00"}, {"open": 1.02, "high": 1.02, "low": 1.02, "close": 1.02, "volume": 100, "datetime": "2022-06-10 16:06:00"}, {"open": 1.02, "high": 1.02, "low": 1.02, "close": 1.02, "volume": 100, "datetime": "2022-06-10 16:07:00"}, {"open": 1.02, "high": 1.02, "low": 1.02, "close": 1.02, "volume": 200, "datetime": "2022-06-10 16:08:00"}, {"open": 1.02, "high": 1.02, "low": 1.02, "close": 1.02, "volume": 100, "datetime": "2022-06-10 16:09:00"}, {"open": 1.02, "high": 1.02, "low": 1.02, "close": 1.02, "volume": 100, "datetime": "2022-06-10 16:10:00"}, {"open": 1.02, "high": 1.02, "low": 1.02, "close": 1.02, "volume": 100, "datetime": "2022-06-10 16:11:00"}, {"open": 1.02, "high": 1.02, "low": 1.02, "close": 1.02, "volume": 200, "datetime": "2022-06-10 16:12:00"}, {"open": 1.02, "high": 1.02, "low": 1.02, "close": 1.02, "volume": 100, "datetime": "2022-06-10 16:13:00"}, {"open": 1.02, "high": 1.02, "low": 0.9828, "close": 0.9828, "volume": 4089, "datetime": "2022-06-10 16:14:00"}, {"open": 1.02, "high": 1.02, "low": 1.02, "close": 1.02, "volume": 300, "datetime": "2022-06-10 16:15:00"}, {"open": 1.02, "high": 1.02, "low": 1.01, "close": 1.01, "volume": 1200, "datetime": "2022-06-10 16:16:00"}, {"open": 1.01, "high": 1.01, "low": 1.0, "close": 1.0, "volume": 2000, "datetime": "2022-06-10 16:17:00"}, {"open": 1.00305, "high": 1.00305, "low": 0.9861, "close": 0.9861, "volume": 300, "datetime": "2022-06-10 16:24:00"}, {"open": 0.9861, "high": 0.995, "low": 0.9649, "close": 0.9649, "volume": 1310, "datetime": "2022-06-10 16:28:00"}, {"open": 0.9625, "high": 0.9625, "low": 0.9612, "close": 0.9612, "volume": 300, "datetime": "2022-06-10 16:29:00"}, {"open": 0.99, "high": 0.99, "low": 0.9889, "close": 0.9889, "volume": 200, "datetime": "2022-06-10 16:30:00"}, {"open": 0.99, "high": 0.99, "low": 0.99, "close": 0.99, "volume": 200, "datetime": "2022-06-10 16:31:00"}, {"open": 0.99, "high": 0.99, "low": 0.99, "close": 0.99, "volume": 779, "datetime": "2022-06-10 16:32:00"}, {"open": 0.99, "high": 0.99, "low": 0.99, "close": 0.99, "volume": 100, "datetime": "2022-06-10 16:33:00"}, {"open": 0.99, "high": 0.99, "low": 0.99, "close": 0.99, "volume": 100, "datetime": "2022-06-10 16:34:00"}, {"open": 0.9939, "high": 0.9939, "low": 0.99, "close": 0.99, "volume": 200, "datetime": "2022-06-10 16:35:00"}, {"open": 1.01, "high": 1.01, "low": 1.01, "close": 1.01, "volume": 100, "datetime": "2022-06-10 16:37:00"}, {"open": 1.01, "high": 1.01, "low": 1.01, "close": 1.01, "volume": 300, "datetime": "2022-06-10 16:38:00"}, {"open": 1.02, "high": 1.02, "low": 1.02, "close": 1.02, "volume": 200, "datetime": "2022-06-10 16:39:00"}, {"open": 1.02, "high": 1.02, "low": 1.02, "close": 1.02, "volume": 100, "datetime": "2022-06-10 16:40:00"}, {"open": 1.02, "high": 1.02, "low": 1.02, "close": 1.02, "volume": 100, "datetime": "2022-06-10 16:41:00"}, {"open": 1.02, "high": 1.02, "low": 1.02, "close": 1.02, "volume": 800, "datetime": "2022-06-10 16:42:00"}, {"open": 1.02, "high": 1.02, "low": 1.02, "close": 1.02, "volume": 200, "datetime": "2022-06-10 16:43:00"}, {"open": 1.02, "high": 1.02, "low": 1.02, "close": 1.02, "volume": 200, "datetime": "2022-06-10 16:44:00"}, {"open": 1.02, "high": 1.02, "low": 1.02, "close": 1.02, "volume": 100, "datetime": "2022-06-10 16:45:00"}, {"open": 1.0007, "high": 1.02, "low": 1.0007, "close": 1.02, "volume": 1450, "datetime": "2022-06-10 16:46:00"}, {"open": 1.02, "high": 1.03, "low": 1.0, "close": 1.01, "volume": 16152, "datetime": "2022-06-10 16:47:00"}, {"open": 0.9949, "high": 0.9949, "low": 0.9922, "close": 0.9922, "volume": 800, "datetime": "2022-06-10 16:50:00"}, {"open": 0.9899, "high": 0.9899, "low": 0.9899, "close": 0.9899, "volume": 1000, "datetime": "2022-06-10 16:53:00"}, {"open": 0.989899, "high": 0.989899, "low": 0.989899, "close": 0.989899, "volume": 1000, "datetime": "2022-06-10 16:54:00"}, {"open": 0.99, "high": 0.99, "low": 0.99, "close": 0.99, "volume": 100, "datetime": "2022-06-10 17:04:00"}, {"open": 0.9899, "high": 0.9899, "low": 0.9899, "close": 0.9899, "volume": 200, "datetime": "2022-06-10 17:05:00"}, {"open": 0.99, "high": 0.99, "low": 0.99, "close": 0.99, "volume": 100, "datetime": "2022-06-10 17:06:00"}, {"open": 0.9978, "high": 0.9978, "low": 0.9939, "close": 0.9939, "volume": 200, "datetime": "2022-06-10 17:07:00"}, {"open": 1.02, "high": 1.02, "low": 1.02, "close": 1.02, "volume": 100, "datetime": "2022-06-10 17:10:00"}, {"open": 1.02, "high": 1.02, "low": 1.02, "close": 1.02, "volume": 100, "datetime": "2022-06-10 17:11:00"}, {"open": 0.9954, "high": 1.02, "low": 0.9954, "close": 1.02, "volume": 200, "datetime": "2022-06-10 17:12:00"}, {"open": 1.03, "high": 1.03, "low": 1.03, "close": 1.03, "volume": 100, "datetime": "2022-06-10 17:13:00"}, {"open": 1.03, "high": 1.03, "low": 1.03, "close": 1.03, "volume": 100, "datetime": "2022-06-10 17:14:00"}, {"open": 0.985, "high": 1.03, "low": 0.985, "close": 1.03, "volume": 440, "datetime": "2022-06-10 17:15:00"}, {"open": 1.03, "high": 1.03, "low": 1.03, "close": 1.03, "volume": 200, "datetime": "2022-06-10 17:16:00"}, {"open": 1.03, "high": 1.03, "low": 1.03, "close": 1.03, "volume": 200, "datetime": "2022-06-10 17:17:00"}, {"open": 1.03, "high": 1.03, "low": 1.03, "close": 1.03, "volume": 100, "datetime": "2022-06-10 17:18:00"}, {"open": 1.03, "high": 1.03, "low": 1.03, "close": 1.03, "volume": 100, "datetime": "2022-06-10 17:19:00"}, {"open": 1.03, "high": 1.03, "low": 1.03, "close": 1.03, "volume": 100, "datetime": "2022-06-10 17:20:00"}, {"open": 1.02, "high": 1.02, "low": 1.02, "close": 1.02, "volume": 200, "datetime": "2022-06-10 17:21:00"}, {"open": 1.02, "high": 1.02, "low": 1.02, "close": 1.02, "volume": 100, "datetime": "2022-06-10 17:22:00"}, {"open": 1.02, "high": 1.02, "low": 1.02, "close": 1.02, "volume": 100, "datetime": "2022-06-10 17:23:00"}, {"open": 1.02, "high": 1.02, "low": 1.02, "close": 1.02, "volume": 200, "datetime": "2022-06-10 17:24:00"}, {"open": 1.03, "high": 1.03, "low": 1.03, "close": 1.03, "volume": 100, "datetime": "2022-06-10 17:25:00"}, {"open": 1.04, "high": 1.04, "low": 1.04, "close": 1.04, "volume": 169, "datetime": "2022-06-10 17:27:00"}, {"open": 1.04, "high": 1.04, "low": 1.04, "close": 1.04, "volume": 100, "datetime": "2022-06-10 17:28:00"}, {"open": 1.04, "high": 1.04, "low": 1.04, "close": 1.04, "volume": 350, "datetime": "2022-06-10 17:29:00"}, {"open": 1.03, "high": 1.03, "low": 1.03, "close": 1.03, "volume": 100, "datetime": "2022-06-10 17:30:00"}, {"open": 1.03, "high": 1.03, "low": 1.03, "close": 1.03, "volume": 100, "datetime": "2022-06-10 17:31:00"}, {"open": 1.03, "high": 1.03, "low": 1.03, "close": 1.03, "volume": 100, "datetime": "2022-06-10 17:32:00"}, {"open": 1.03, "high": 1.03, "low": 1.03, "close": 1.03, "volume": 200, "datetime": "2022-06-10 17:33:00"}, {"open": 1.0073, "high": 1.04, "low": 1.0073, "close": 1.04, "volume": 850, "datetime": "2022-06-10 17:34:00"}, {"open": 1.04, "high": 1.05, "low": 1.04, "close": 1.05, "volume": 200, "datetime": "2022-06-10 17:36:00"}, {"open": 1.03, "high": 1.04, "low": 1.03, "close": 1.04, "volume": 490, "datetime": "2022-06-10 17:37:00"}, {"open": 1.01, "high": 1.01, "low": 0.9757, "close": 0.9757, "volume": 10000, "datetime": "2022-06-10 17:38:00"}, {"open": 1.04, "high": 1.04, "low": 1.04, "close": 1.04, "volume": 100, "datetime": "2022-06-10 17:41:00"}, {"open": 1.04, "high": 1.04, "low": 1.04, "close": 1.04, "volume": 100, "datetime": "2022-06-10 17:42:00"}, {"open": 1.04, "high": 1.04, "low": 1.04, "close": 1.04, "volume": 200, "datetime": "2022-06-10 17:43:00"}, {"open": 1.04, "high": 1.04, "low": 1.04, "close": 1.04, "volume": 100, "datetime": "2022-06-10 17:44:00"}, {"open": 1.04, "high": 1.05, "low": 1.04, "close": 1.05, "volume": 200, "datetime": "2022-06-10 17:45:00"}, {"open": 1.04, "high": 1.04, "low": 1.04, "close": 1.04, "volume": 100, "datetime": "2022-06-10 17:46:00"}, {"open": 1.04, "high": 1.04, "low": 1.02, "close": 1.02, "volume": 5100, "datetime": "2022-06-10 17:47:00"}, {"open": 1.02, "high": 1.03, "low": 1.02, "close": 1.03, "volume": 1100, "datetime": "2022-06-10 17:48:00"}, {"open": 1.03, "high": 1.03, "low": 0.96, "close": 0.96, "volume": 6600, "datetime": "2022-06-10 17:49:00"}, {"open": 0.9751, "high": 0.9751, "low": 0.9751, "close": 0.9751, "volume": 1500, "datetime": "2022-06-10 17:50:00"}, {"open": 0.9752, "high": 0.9752, "low": 0.975099, "close": 0.975099, "volume": 1100, "datetime": "2022-06-10 17:52:00"}, {"open": 0.9752, "high": 0.9752, "low": 0.9752, "close": 0.9752, "volume": 100, "datetime": "2022-06-10 17:53:00"}, {"open": 0.9752, "high": 0.9752, "low": 0.9752, "close": 0.9752, "volume": 300, "datetime": "2022-06-10 17:54:00"}, {"open": 0.9752, "high": 0.9752, "low": 0.9752, "close": 0.9752, "volume": 200, "datetime": "2022-06-10 17:55:00"}, {"open": 0.9752, "high": 0.9752, "low": 0.9752, "close": 0.9752, "volume": 200, "datetime": "2022-06-10 17:57:00"}, {"open": 0.9752, "high": 0.9752, "low": 0.9752, "close": 0.9752, "volume": 100, "datetime": "2022-06-10 17:58:00"}, {"open": 0.9752, "high": 0.9752, "low": 0.9752, "close": 0.9752, "volume": 100, "datetime": "2022-06-10 17:59:00"}, {"open": 0.9752, "high": 0.9752, "low": 0.9752, "close": 0.9752, "volume": 172, "datetime": "2022-06-10 18:00:00"}, {"open": 0.9752, "high": 0.9752, "low": 0.9752, "close": 0.9752, "volume": 100, "datetime": "2022-06-10 18:01:00"}, {"open": 0.9752, "high": 0.9791, "low": 0.9752, "close": 0.9752, "volume": 672, "datetime": "2022-06-10 18:02:00"}, {"open": 0.9985, "high": 0.9986, "low": 0.9985, "close": 0.9985, "volume": 2200, "datetime": "2022-06-10 18:03:00"}, {"open": 0.99, "high": 0.99, "low": 0.9638, "close": 0.9638, "volume": 700, "datetime": "2022-06-10 18:04:00"}, {"open": 0.99, "high": 0.99, "low": 0.9899, "close": 0.9899, "volume": 600, "datetime": "2022-06-10 18:05:00"}, {"open": 0.99, "high": 0.99, "low": 0.9899, "close": 0.9899, "volume": 400, "datetime": "2022-06-10 18:06:00"}, {"open": 0.99, "high": 0.99, "low": 0.99, "close": 0.99, "volume": 100, "datetime": "2022-06-10 18:07:00"}, {"open": 0.99, "high": 0.99, "low": 0.99, "close": 0.99, "volume": 100, "datetime": "2022-06-10 18:08:00"}, {"open": 0.99, "high": 0.99, "low": 0.99, "close": 0.99, "volume": 200, "datetime": "2022-06-10 18:09:00"}, {"open": 0.99, "high": 0.99, "low": 0.99, "close": 0.99, "volume": 100, "datetime": "2022-06-10 18:10:00"}, {"open": 0.99, "high": 0.99, "low": 0.99, "close": 0.99, "volume": 100, "datetime": "2022-06-10 18:11:00"}, {"open": 0.99, "high": 0.99, "low": 0.99, "close": 0.99, "volume": 100, "datetime": "2022-06-10 18:12:00"}, {"open": 0.99, "high": 0.99, "low": 0.99, "close": 0.99, "volume": 100, "datetime": "2022-06-10 18:13:00"}, {"open": 0.99, "high": 0.99, "low": 0.99, "close": 0.99, "volume": 400, "datetime": "2022-06-10 18:14:00"}, {"open": 0.99, "high": 0.99, "low": 0.99, "close": 0.99, "volume": 300, "datetime": "2022-06-10 18:15:00"}, {"open": 0.99, "high": 1.0, "low": 0.985049, "close": 1.0, "volume": 7097, "datetime": "2022-06-10 18:16:00"}, {"open": 1.0, "high": 1.01, "low": 0.9951, "close": 0.9951, "volume": 400, "datetime": "2022-06-10 18:17:00"}, {"open": 1.01, "high": 1.01, "low": 1.01, "close": 1.01, "volume": 200, "datetime": "2022-06-10 18:18:00"}, {"open": 1.01, "high": 1.01, "low": 1.01, "close": 1.01, "volume": 100, "datetime": "2022-06-10 18:19:00"}, {"open": 1.01, "high": 1.01, "low": 1.01, "close": 1.01, "volume": 200, "datetime": "2022-06-10 18:20:00"}, {"open": 1.02, "high": 1.02, "low": 1.01, "close": 1.01, "volume": 200, "datetime": "2022-06-10 18:21:00"}, {"open": 1.02, "high": 1.02, "low": 1.02, "close": 1.02, "volume": 100, "datetime": "2022-06-10 18:22:00"}, {"open": 1.02, "high": 1.02, "low": 1.02, "close": 1.02, "volume": 100, "datetime": "2022-06-10 18:24:00"}, {"open": 1.02, "high": 1.02, "low": 1.0197, "close": 1.0198, "volume": 4100, "datetime": "2022-06-10 18:25:00"}, {"open": 1.02, "high": 1.02, "low": 1.0001, "close": 1.0001, "volume": 5200, "datetime": "2022-06-10 18:26:00"}, {"open": 1.02, "high": 1.02, "low": 1.01, "close": 1.01, "volume": 200, "datetime": "2022-06-10 18:27:00"}, {"open": 1.02, "high": 1.03, "low": 1.02, "close": 1.03, "volume": 200, "datetime": "2022-06-10 18:29:00"}, {"open": 1.015, "high": 1.0286, "low": 1.015, "close": 1.02, "volume": 600, "datetime": "2022-06-10 18:30:00"}, {"open": 1.02, "high": 1.02, "low": 1.02, "close": 1.02, "volume": 200, "datetime": "2022-06-10 18:31:00"}, {"open": 1.0299, "high": 1.0299, "low": 1.0299, "close": 1.0299, "volume": 1200, "datetime": "2022-06-10 18:34:00"}, {"open": 1.03, "high": 1.03, "low": 1.03, "close": 1.03, "volume": 1100, "datetime": "2022-06-10 18:35:00"}, {"open": 1.04, "high": 1.04, "low": 1.04, "close": 1.04, "volume": 200, "datetime": "2022-06-10 18:36:00"}, {"open": 1.04, "high": 1.04, "low": 1.04, "close": 1.04, "volume": 100, "datetime": "2022-06-10 18:37:00"}, {"open": 1.04, "high": 1.04, "low": 1.04, "close": 1.04, "volume": 100, "datetime": "2022-06-10 18:38:00"}, {"open": 1.04, "high": 1.04, "low": 1.04, "close": 1.04, "volume": 200, "datetime": "2022-06-10 18:39:00"}, {"open": 1.04, "high": 1.04, "low": 1.04, "close": 1.04, "volume": 100, "datetime": "2022-06-10 18:40:00"}, {"open": 1.04, "high": 1.04, "low": 1.04, "close": 1.04, "volume": 200, "datetime": "2022-06-10 18:41:00"}, {"open": 1.04, "high": 1.04, "low": 1.04, "close": 1.04, "volume": 200, "datetime": "2022-06-10 18:42:00"}, {"open": 1.04, "high": 1.04, "low": 1.04, "close": 1.04, "volume": 100, "datetime": "2022-06-10 18:44:00"}, {"open": 1.04, "high": 1.04, "low": 1.04, "close": 1.04, "volume": 100, "datetime": "2022-06-10 18:45:00"}, {"open": 1.04, "high": 1.04, "low": 1.04, "close": 1.04, "volume": 190, "datetime": "2022-06-10 18:46:00"}, {"open": 1.04, "high": 1.04, "low": 1.04, "close": 1.04, "volume": 300, "datetime": "2022-06-10 18:47:00"}, {"open": 1.04, "high": 1.04, "low": 1.035, "close": 1.035, "volume": 404, "datetime": "2022-06-10 18:48:00"}, {"open": 1.035, "high": 1.039, "low": 1.035, "close": 1.039, "volume": 400, "datetime": "2022-06-10 18:50:00"}, {"open": 1.035, "high": 1.035, "low": 1.035, "close": 1.035, "volume": 100, "datetime": "2022-06-10 18:51:00"}, {"open": 1.03, "high": 1.03, "low": 1.01, "close": 1.025, "volume": 1600, "datetime": "2022-06-10 18:52:00"}, {"open": 1.0099, "high": 1.0099, "low": 1.0099, "close": 1.0099, "volume": 100, "datetime": "2022-06-10 18:54:00"}, {"open": 1.01, "high": 1.01, "low": 1.01, "close": 1.01, "volume": 200, "datetime": "2022-06-10 18:55:00"}, {"open": 1.02, "high": 1.02, "low": 1.01, "close": 1.01, "volume": 300, "datetime": "2022-06-10 18:56:00"}, {"open": 1.02, "high": 1.02, "low": 1.02, "close": 1.02, "volume": 100, "datetime": "2022-06-10 18:57:00"}, {"open": 1.03, "high": 1.03, "low": 1.03, "close": 1.03, "volume": 100, "datetime": "2022-06-10 18:58:00"}, {"open": 1.03, "high": 1.03, "low": 1.03, "close": 1.03, "volume": 200, "datetime": "2022-06-10 18:59:00"}, {"open": 1.02, "high": 1.02, "low": 1.02, "close": 1.02, "volume": 100, "datetime": "2022-06-10 19:00:00"}, {"open": 1.01, "high": 1.03, "low": 1.01, "close": 1.03, "volume": 400, "datetime": "2022-06-10 19:01:00"}, {"open": 1.03, "high": 1.03, "low": 1.02, "close": 1.02, "volume": 200, "datetime": "2022-06-10 19:02:00"}, {"open": 1.02, "high": 1.02, "low": 1.0001, "close": 1.02, "volume": 1700, "datetime": "2022-06-10 19:03:00"}, {"open": 1.0001, "high": 1.02, "low": 1.0001, "close": 1.02, "volume": 2100, "datetime": "2022-06-10 19:04:00"}, {"open": 1.03, "high": 1.03, "low": 1.03, "close": 1.03, "volume": 100, "datetime": "2022-06-10 19:05:00"}, {"open": 1.03, "high": 1.03, "low": 1.005, "close": 1.005, "volume": 300, "datetime": "2022-06-10 19:06:00"}, {"open": 1.005, "high": 1.0079, "low": 1.0, "close": 1.0, "volume": 6178, "datetime": "2022-06-10 19:08:00"}, {"open": 1.01, "high": 1.01, "low": 1.01, "close": 1.01, "volume": 100, "datetime": "2022-06-10 19:15:00"}, {"open": 1.01, "high": 1.01, "low": 1.01, "close": 1.01, "volume": 200, "datetime": "2022-06-10 19:16:00"}, {"open": 1.01, "high": 1.01, "low": 1.01, "close": 1.01, "volume": 100, "datetime": "2022-06-10 19:17:00"}, {"open": 1.01, "high": 1.01, "low": 0.9853, "close": 0.9853, "volume": 400, "datetime": "2022-06-10 19:18:00"}, {"open": 0.9851, "high": 0.9851, "low": 0.985, "close": 0.985, "volume": 1100, "datetime": "2022-06-10 19:19:00"}, {"open": 1.01, "high": 1.01, "low": 1.01, "close": 1.01, "volume": 200, "datetime": "2022-06-10 19:20:00"}, {"open": 1.01, "high": 1.01, "low": 1.01, "close": 1.01, "volume": 1500, "datetime": "2022-06-10 19:21:00"}, {"open": 1.00255, "high": 1.02, "low": 1.00255, "close": 1.02, "volume": 200, "datetime": "2022-06-10 19:22:00"}, {"open": 1.02, "high": 1.02, "low": 0.99755, "close": 0.99755, "volume": 400, "datetime": "2022-06-10 19:23:00"}, {"open": 1.02, "high": 1.02, "low": 1.02, "close": 1.02, "volume": 200, "datetime": "2022-06-10 19:25:00"}, {"open": 1.02, "high": 1.02, "low": 1.02, "close": 1.02, "volume": 100, "datetime": "2022-06-10 19:26:00"}, {"open": 1.02, "high": 1.02, "low": 1.0, "close": 1.0007, "volume": 9440, "datetime": "2022-06-10 19:27:00"}, {"open": 0.995, "high": 1.0075, "low": 0.995, "close": 1.0075, "volume": 200, "datetime": "2022-06-10 19:42:00"}, {"open": 1.01, "high": 1.01, "low": 1.01, "close": 1.01, "volume": 100, "datetime": "2022-06-10 19:43:00"}, {"open": 0.98, "high": 0.98, "low": 0.98, "close": 0.98, "volume": 200, "datetime": "2022-06-10 19:50:00"}, {"open": 0.97, "high": 0.97, "low": 0.97, "close": 0.97, "volume": 200, "datetime": "2022-06-10 19:55:00"}, {"open": 0.97, "high": 0.97, "low": 0.97, "close": 0.97, "volume": 300, "datetime": "2022-06-10 19:57:00"}, {"open": 0.97, "high": 0.97, "low": 0.9676, "close": 0.9676, "volume": 2015, "datetime": "2022-06-10 19:58:00"}, {"open": 0.9798, "high": 0.9798, "low": 0.9798, "close": 0.9798, "volume": 146, "datetime": "2022-06-10 20:00:00"}], "symbol": "RAVE", "empty": false}